Workbook
Name lstCategorias: Configurações!$B$5:$B$57
Name lstEstado: Configurações!$F$5:$F$8
Name lstEstoque: Configurações!$L$5:$L$6
Name lstTipos: Configurações!$I$5:$I$15

Sheet Dashboard
B2: BTG PACTUAL · INVENTÁRIO CONSOLIDADO · DASHBOARD
B3: Atualizado automaticamente · dados puxados das abas Catálogo e Movimentações
B5: PRODUTOS | E5: PEÇAS EM ESTOQUE | H5: CUSTO TOTAL DO ESTOQUE | K5: AD VALOREM MENSAL (0,50%)
B6: =Catálogo!B6 -> 600 | E6: =Catálogo!D6 -> 13596 | H6: =Catálogo!G6 -> 0 | K6: =H6*0.005 -> 0
B7: códigos únicos da cliente | E7: soma do saldo atual | H7: Qtde × Preço de Custo | K7: 0,50% sobre custo total
B10: RESUMO POR CATEGORIA
B11: CATEGORIA | C11: PRODUTOS | D11: PEÇAS | E11: CUSTO TOTAL | F11: % ESTOQUE | G11: % CUSTO
B12: VESTUÁRIO | C12: =COUNTIF(Catalogo[GRUPO],B12) -> 457 | D12: =SUMIFS(Catalogo[ESTOQUE BTG],Catalogo[GRUPO],B12) -> 6855 | E12: =SUMIFS(Catalogo[CUSTO TOTAL],Catalogo[GRUPO],B12) -> 0 | F12: =IFERROR(D12/$E$6,0) -> 0.50419241 | G12: =IFERROR(E12/$H$6,0) -> 0
B13: BOLSAS E MALAS | C13: =COUNTIF(Catalogo[GRUPO],B13) -> 24 | D13: =SUMIFS(Catalogo[ESTOQUE BTG],Catalogo[GRUPO],B13) -> 2457 | E13: =SUMIFS(Catalogo[CUSTO TOTAL],Catalogo[GRUPO],B13) -> 0 | F13: =IFERROR(D13/$E$6,0) -> 0.18071492 | G13: =IFERROR(E13/$H$6,0) -> 0
B14: BEBIDAS E MESA | C14: =COUNTIF(Catalogo[GRUPO],B14) -> 19 | D14: =SUMIFS(Catalogo[ESTOQUE BTG],Catalogo[GRUPO],B14) -> 51 | E14: =SUMIFS(Catalogo[CUSTO TOTAL],Catalogo[GRUPO],B14) -> 0 | F14: =IFERROR(D14/$E$6,0) -> 0.0037511033 | G14: =IFERROR(E14/$H$6,0) -> 0
B15: ESCRITÓRIOS E PAPELARIA | C15: =COUNTIF(Catalogo[GRUPO],B15) -> 12 | D15: =SUMIFS(Catalogo[ESTOQUE BTG],Catalogo[GRUPO],B15) -> 257 | E15: =SUMIFS(Catalogo[CUSTO TOTAL],Catalogo[GRUPO],B15) -> 0 | F15: =IFERROR(D15/$E$6,0) -> 0.018902618 | G15: =IFERROR(E15/$H$6,0) -> 0
B16: ACESSÓRIOS | C16: =COUNTIF(Catalogo[GRUPO],B16) -> 15 | D16: =SUMIFS(Catalogo[ESTOQUE BTG],Catalogo[GRUPO],B16) -> 1483 | E16: =SUMIFS(Catalogo[CUSTO TOTAL],Catalogo[GRUPO],B16) -> 0 | F16: =IFERROR(D16/$E$6,0) -> 0.1090762 | G16: =IFERROR(E16/$H$6,0) -> 0
B17: MATERIAL DE EVENTO | C17: =COUNTIF(Catalogo[GRUPO],B17) -> 20 | D17: =SUMIFS(Catalogo[ESTOQUE BTG],Catalogo[GRUPO],B17) -> 201 | E17: =SUMIFS(Catalogo[CUSTO TOTAL],Catalogo[GRUPO],B17) -> 0 | F17: =IFERROR(D17/$E$6,0) -> 0.01478376 | G17: =IFERROR(E17/$H$6,0) -> 0
B18: TOTAL | C18: =SUM(C12:C17) -> 547 | D18: =SUM(D12:D17) -> 11304 | E18: =SUM(E12:E17) -> 0 | F18: =SUM(F12:F17) -> 0.83142101 | G18: =SUM(G12:G17) -> 0
B21: ÚLTIMAS 20 MOVIMENTAÇÕES
B22: DATA | C22: TIPO MOV. | D22: CÓD. SKU | E22: PRODUTO | F22: QTDE | G22: ESTOQUE | H22: RESPONSÁVEL
B23: =IFERROR(INDEX(Movimentações!$A$6:$A$4773,COUNTA(Movimentações!$C$6:$C$4773)-0),"") -> 0 | C23: =IFERROR(INDEX(Movimentações!$B$6:$B$4773,COUNTA(Movimentações!$C$6:$C$4773)-0),"") -> 0 | D23: =IFERROR(INDEX(Movimentações!$C$6:$C$4773,COUNTA(Movimentações!$C$6:$C$4773)-0),"") -> 0 | E23: =IFERROR(INDEX(Movimentações!$D$6:$D$4773,COUNTA(Movimentações!$C$6:$C$4773)-0),"") | F23: =IFERROR(INDEX(Movimentações!$E$6:$E$4773,COUNTA(Movimentações!$C$6:$C$4773)-0),"") -> 0 | G23: =IFERROR(INDEX(Movimentações!$G$6:$G$4773,COUNTA(Movimentações!$C$6:$C$4773)-0),"") -> 0 | H23: =IFERROR(INDEX(Movimentações!$K$6:$K$4773,COUNTA(Movimentações!$C$6:$C$4773)-0),"") -> 0
B24: =IFERROR(INDEX(Movimentações!$A$6:$A$4773,COUNTA(Movimentações!$C$6:$C$4773)-1),"") -> 0 | C24: =IFERROR(INDEX(Movimentações!$B$6:$B$4773,COUNTA(Movimentações!$C$6:$C$4773)-1),"") -> 0 | D24: =IFERROR(INDEX(Movimentações!$C$6:$C$4773,COUNTA(Movimentações!$C$6:$C$4773)-1),"") -> 0 | E24: =IFERROR(INDEX(Movimentações!$D$6:$D$4773,COUNTA(Movimentações!$C$6:$C$4773)-1),"") | F24: =IFERROR(INDEX(Movimentações!$E$6:$E$4773,COUNTA(Movimentações!$C$6:$C$4773)-1),"") -> 0 | G24: =IFERROR(INDEX(Movimentações!$G$6:$G$4773,COUNTA(Movimentações!$C$6:$C$4773)-1),"") -> 0 | H24: =IFERROR(INDEX(Movimentações!$K$6:$K$4773,COUNTA(Movimentações!$C$6:$C$4773)-1),"") -> 0
B25: =IFERROR(INDEX(Movimentações!$A$6:$A$4773,COUNTA(Movimentações!$C$6:$C$4773)-2),"") -> 0 | C25: =IFERROR(INDEX(Movimentações!$B$6:$B$4773,COUNTA(Movimentações!$C$6:$C$4773)-2),"") -> 0 | D25: =IFERROR(INDEX(Movimentações!$C$6:$C$4773,COUNTA(Movimentações!$C$6:$C$4773)-2),"") -> 0 | E25: =IFERROR(INDEX(Movimentações!$D$6:$D$4773,COUNTA(Movimentações!$C$6:$C$4773)-2),"") | F25: =IFERROR(INDEX(Movimentações!$E$6:$E$4773,COUNTA(Movimentações!$C$6:$C$4773)-2),"") -> 0 | G25: =IFERROR(INDEX(Movimentações!$G$6:$G$4773,COUNTA(Movimentações!$C$6:$C$4773)-2),"") -> 0 | H25: =IFERROR(INDEX(Movimentações!$K$6:$K$4773,COUNTA(Movimentações!$C$6:$C$4773)-2),"") -> 0
B26: =IFERROR(INDEX(Movimentações!$A$6:$A$4773,COUNTA(Movimentações!$C$6:$C$4773)-3),"") -> 0 | C26: =IFERROR(INDEX(Movimentações!$B$6:$B$4773,COUNTA(Movimentações!$C$6:$C$4773)-3),"") -> 0 | D26: =IFERROR(INDEX(Movimentações!$C$6:$C$4773,COUNTA(Movimentações!$C$6:$C$4773)-3),"") -> 0 | E26: =IFERROR(INDEX(Movimentações!$D$6:$D$4773,COUNTA(Movimentações!$C$6:$C$4773)-3),"") | F26: =IFERROR(INDEX(Movimentações!$E$6:$E$4773,COUNTA(Movimentações!$C$6:$C$4773)-3),"") -> 0 | G26: =IFERROR(INDEX(Movimentações!$G$6:$G$4773,COUNTA(Movimentações!$C$6:$C$4773)-3),"") -> 0 | H26: =IFERROR(INDEX(Movimentações!$K$6:$K$4773,COUNTA(Movimentações!$C$6:$C$4773)-3),"") -> 0
B27: =IFERROR(INDEX(Movimentações!$A$6:$A$4773,COUNTA(Movimentações!$C$6:$C$4773)-4),"") -> 0 | C27: =IFERROR(INDEX(Movimentações!$B$6:$B$4773,COUNTA(Movimentações!$C$6:$C$4773)-4),"") -> 0 | D27: =IFERROR(INDEX(Movimentações!$C$6:$C$4773,COUNTA(Movimentações!$C$6:$C$4773)-4),"") -> 0 | E27: =IFERROR(INDEX(Movimentações!$D$6:$D$4773,COUNTA(Movimentações!$C$6:$C$4773)-4),"") | F27: =IFERROR(INDEX(Movimentações!$E$6:$E$4773,COUNTA(Movimentações!$C$6:$C$4773)-4),"") -> 0 | G27: =IFERROR(INDEX(Movimentações!$G$6:$G$4773,COUNTA(Movimentações!$C$6:$C$4773)-4),"") -> 0 | H27: =IFERROR(INDEX(Movimentações!$K$6:$K$4773,COUNTA(Movimentações!$C$6:$C$4773)-4),"") -> 0
B28: =IFERROR(INDEX(Movimentações!$A$6:$A$4773,COUNTA(Movimentações!$C$6:$C$4773)-5),"") -> 0 | C28: =IFERROR(INDEX(Movimentações!$B$6:$B$4773,COUNTA(Movimentações!$C$6:$C$4773)-5),"") -> 0 | D28: =IFERROR(INDEX(Movimentações!$C$6:$C$4773,COUNTA(Movimentações!$C$6:$C$4773)-5),"") -> 0 | E28: =IFERROR(INDEX(Movimentações!$D$6:$D$4773,COUNTA(Movimentações!$C$6:$C$4773)-5),"") | F28: =IFERROR(INDEX(Movimentações!$E$6:$E$4773,COUNTA(Movimentações!$C$6:$C$4773)-5),"") -> 0 | G28: =IFERROR(INDEX(Movimentações!$G$6:$G$4773,COUNTA(Movimentações!$C$6:$C$4773)-5),"") -> 0 | H28: =IFERROR(INDEX(Movimentações!$K$6:$K$4773,COUNTA(Movimentações!$C$6:$C$4773)-5),"") -> 0
B29: =IFERROR(INDEX(Movimentações!$A$6:$A$4773,COUNTA(Movimentações!$C$6:$C$4773)-6),"") -> 0 | C29: =IFERROR(INDEX(Movimentações!$B$6:$B$4773,COUNTA(Movimentações!$C$6:$C$4773)-6),"") -> 0 | D29: =IFERROR(INDEX(Movimentações!$C$6:$C$4773,COUNTA(Movimentações!$C$6:$C$4773)-6),"") -> 0 | E29: =IFERROR(INDEX(Movimentações!$D$6:$D$4773,COUNTA(Movimentações!$C$6:$C$4773)-6),"") | F29: =IFERROR(INDEX(Movimentações!$E$6:$E$4773,COUNTA(Movimentações!$C$6:$C$4773)-6),"") -> 0 | G29: =IFERROR(INDEX(Movimentações!$G$6:$G$4773,COUNTA(Movimentações!$C$6:$C$4773)-6),"") -> 0 | H29: =IFERROR(INDEX(Movimentações!$K$6:$K$4773,COUNTA(Movimentações!$C$6:$C$4773)-6),"") -> 0
B30: =IFERROR(INDEX(Movimentações!$A$6:$A$4773,COUNTA(Movimentações!$C$6:$C$4773)-7),"") -> 0 | C30: =IFERROR(INDEX(Movimentações!$B$6:$B$4773,COUNTA(Movimentações!$C$6:$C$4773)-7),"") -> 0 | D30: =IFERROR(INDEX(Movimentações!$C$6:$C$4773,COUNTA(Movimentações!$C$6:$C$4773)-7),"") -> 0 | E30: =IFERROR(INDEX(Movimentações!$D$6:$D$4773,COUNTA(Movimentações!$C$6:$C$4773)-7),"") | F30: =IFERROR(INDEX(Movimentações!$E$6:$E$4773,COUNTA(Movimentações!$C$6:$C$4773)-7),"") -> 0 | G30: =IFERROR(INDEX(Movimentações!$G$6:$G$4773,COUNTA(Movimentações!$C$6:$C$4773)-7),"") -> 0 | H30: =IFERROR(INDEX(Movimentações!$K$6:$K$4773,COUNTA(Movimentações!$C$6:$C$4773)-7),"") -> 0
B31: =IFERROR(INDEX(Movimentações!$A$6:$A$4773,COUNTA(Movimentações!$C$6:$C$4773)-8),"") -> 0 | C31: =IFERROR(INDEX(Movimentações!$B$6:$B$4773,COUNTA(Movimentações!$C$6:$C$4773)-8),"") -> 0 | D31: =IFERROR(INDEX(Movimentações!$C$6:$C$4773,COUNTA(Movimentações!$C$6:$C$4773)-8),"") -> 0 | E31: =IFERROR(INDEX(Movimentações!$D$6:$D$4773,COUNTA(Movimentações!$C$6:$C$4773)-8),"") | F31: =IFERROR(INDEX(Movimentações!$E$6:$E$4773,COUNTA(Movimentações!$C$6:$C$4773)-8),"") -> 0 | G31: =IFERROR(INDEX(Movimentações!$G$6:$G$4773,COUNTA(Movimentações!$C$6:$C$4773)-8),"") -> 0 | H31: =IFERROR(INDEX(Movimentações!$K$6:$K$4773,COUNTA(Movimentações!$C$6:$C$4773)-8),"") -> 0
B32: =IFERROR(INDEX(Movimentações!$A$6:$A$4773,COUNTA(Movimentações!$C$6:$C$4773)-9),"") -> 46204 | C32: =IFERROR(INDEX(Movimentações!$B$6:$B$4773,COUNTA(Movimentações!$C$6:$C$4773)-9),"") -> ENTRADA | D32: =IFERROR(INDEX(Movimentações!$C$6:$C$4773,COUNTA(Movimentações!$C$6:$C$4773)-9),"") -> BTG-2210 | E32: =IFERROR(INDEX(Movimentações!$D$6:$D$4773,COUNTA(Movimentações!$C$6:$C$4773)-9),"") -> POLO PIQUET ARPOADOR MASC. | F32: =IFERROR(INDEX(Movimentações!$E$6:$E$4773,COUNTA(Movimentações!$C$6:$C$4773)-9),"") -> 2 | G32: =IFERROR(INDEX(Movimentações!$G$6:$G$4773,COUNTA(Movimentações!$C$6:$C$4773)-9),"") -> Store | H32: =IFERROR(INDEX(Movimentações!$K$6:$K$4773,COUNTA(Movimentações!$C$6:$C$4773)-9),"") -> RAFAEL
B33: =IFERROR(INDEX(Movimentações!$A$6:$A$4773,COUNTA(Movimentações!$C$6:$C$4773)-10),"") -> 46204 | C33: =IFERROR(INDEX(Movimentações!$B$6:$B$4773,COUNTA(Movimentações!$C$6:$C$4773)-10),"") -> ENTRADA | D33: =IFERROR(INDEX(Movimentações!$C$6:$C$4773,COUNTA(Movimentações!$C$6:$C$4773)-10),"") -> BTG-2209 | E33: =IFERROR(INDEX(Movimentações!$D$6:$D$4773,COUNTA(Movimentações!$C$6:$C$4773)-10),"") -> POLO PIQUET ARPOADOR MASC. | F33: =IFERROR(INDEX(Movimentações!$E$6:$E$4773,COUNTA(Movimentações!$C$6:$C$4773)-10),"") -> 1 | G33: =IFERROR(INDEX(Movimentações!$G$6:$G$4773,COUNTA(Movimentações!$C$6:$C$4773)-10),"") -> Store | H33: =IFERROR(INDEX(Movimentações!$K$6:$K$4773,COUNTA(Movimentações!$C$6:$C$4773)-10),"") -> RAFAEL
B34: =IFERROR(INDEX(Movimentações!$A$6:$A$4773,COUNTA(Movimentações!$C$6:$C$4773)-11),"") -> 46204 | C34: =IFERROR(INDEX(Movimentações!$B$6:$B$4773,COUNTA(Movimentações!$C$6:$C$4773)-11),"") -> ENTRADA | D34: =IFERROR(INDEX(Movimentações!$C$6:$C$4773,COUNTA(Movimentações!$C$6:$C$4773)-11),"") -> BTG-2208 | E34: =IFERROR(INDEX(Movimentações!$D$6:$D$4773,COUNTA(Movimentações!$C$6:$C$4773)-11),"") -> POLO PIQUET ARPOADOR MASC. | F34: =IFERROR(INDEX(Movimentações!$E$6:$E$4773,COUNTA(Movimentações!$C$6:$C$4773)-11),"") -> 7 | G34: =IFERROR(INDEX(Movimentações!$G$6:$G$4773,COUNTA(Movimentações!$C$6:$C$4773)-11),"") -> Store | H34: =IFERROR(INDEX(Movimentações!$K$6:$K$4773,COUNTA(Movimentações!$C$6:$C$4773)-11),"") -> RAFAEL
B35: =IFERROR(INDEX(Movimentações!$A$6:$A$4773,COUNTA(Movimentações!$C$6:$C$4773)-12),"") -> 46204 | C35: =IFERROR(INDEX(Movimentações!$B$6:$B$4773,COUNTA(Movimentações!$C$6:$C$4773)-12),"") -> ENTRADA | D35: =IFERROR(INDEX(Movimentações!$C$6:$C$4773,COUNTA(Movimentações!$C$6:$C$4773)-12),"") -> BTG-2213 | E35: =IFERROR(INDEX(Movimentações!$D$6:$D$4773,COUNTA(Movimentações!$C$6:$C$4773)-12),"") -> POLO PIQUET ARPOADOR MASC. | F35: =IFERROR(INDEX(Movimentações!$E$6:$E$4773,COUNTA(Movimentações!$C$6:$C$4773)-12),"") -> 68 | G35: =IFERROR(INDEX(Movimentações!$G$6:$G$4773,COUNTA(Movimentações!$C$6:$C$4773)-12),"") -> Store | H35: =IFERROR(INDEX(Movimentações!$K$6:$K$4773,COUNTA(Movimentações!$C$6:$C$4773)-12),"") -> RAFAEL
B36: =IFERROR(INDEX(Movimentações!$A$6:$A$4773,COUNTA(Movimentações!$C$6:$C$4773)-13),"") -> 46204 | C36: =IFERROR(INDEX(Movimentações!$B$6:$B$4773,COUNTA(Movimentações!$C$6:$C$4773)-13),"") -> ENTRADA | D36: =IFERROR(INDEX(Movimentações!$C$6:$C$4773,COUNTA(Movimentações!$C$6:$C$4773)-13),"") -> BTG-2212 | E36: =IFERROR(INDEX(Movimentações!$D$6:$D$4773,COUNTA(Movimentações!$C$6:$C$4773)-13),"") -> POLO PIQUET ARPOADOR MASC. | F36: =IFERROR(INDEX(Movimentações!$E$6:$E$4773,COUNTA(Movimentações!$C$6:$C$4773)-13),"") -> 1 | G36: =IFERROR(INDEX(Movimentações!$G$6:$G$4773,COUNTA(Movimentações!$C$6:$C$4773)-13),"") -> Store | H36: =IFERROR(INDEX(Movimentações!$K$6:$K$4773,COUNTA(Movimentações!$C$6:$C$4773)-13),"") -> RAFAEL
B37: =IFERROR(INDEX(Movimentações!$A$6:$A$4773,COUNTA(Movimentações!$C$6:$C$4773)-14),"") -> 46204 | C37: =IFERROR(INDEX(Movimentações!$B$6:$B$4773,COUNTA(Movimentações!$C$6:$C$4773)-14),"") -> ENTRADA | D37: =IFERROR(INDEX(Movimentações!$C$6:$C$4773,COUNTA(Movimentações!$C$6:$C$4773)-14),"") -> BTG-2211 | E37: =IFERROR(INDEX(Movimentações!$D$6:$D$4773,COUNTA(Movimentações!$C$6:$C$4773)-14),"") -> POLO PIQUET ARPOADOR MASC. | F37: =IFERROR(INDEX(Movimentações!$E$6:$E$4773,COUNTA(Movimentações!$C$6:$C$4773)-14),"") -> 50 | G37: =IFERROR(INDEX(Movimentações!$G$6:$G$4773,COUNTA(Movimentações!$C$6:$C$4773)-14),"") -> Store | H37: =IFERROR(INDEX(Movimentações!$K$6:$K$4773,COUNTA(Movimentações!$C$6:$C$4773)-14),"") -> RAFAEL
B38: =IFERROR(INDEX(Movimentações!$A$6:$A$4773,COUNTA(Movimentações!$C$6:$C$4773)-15),"") -> 46204 | C38: =IFERROR(INDEX(Movimentações!$B$6:$B$4773,COUNTA(Movimentações!$C$6:$C$4773)-15),"") -> ENTRADA | D38: =IFERROR(INDEX(Movimentações!$C$6:$C$4773,COUNTA(Movimentações!$C$6:$C$4773)-15),"") -> BTG-2212 | E38: =IFERROR(INDEX(Movimentações!$D$6:$D$4773,COUNTA(Movimentações!$C$6:$C$4773)-15),"") -> POLO PIQUET ARPOADOR MASC. | F38: =IFERROR(INDEX(Movimentações!$E$6:$E$4773,COUNTA(Movimentações!$C$6:$C$4773)-15),"") -> 17 | G38: =IFERROR(INDEX(Movimentações!$G$6:$G$4773,COUNTA(Movimentações!$C$6:$C$4773)-15),"") -> Store | H38: =IFERROR(INDEX(Movimentações!$K$6:$K$4773,COUNTA(Movimentações!$C$6:$C$4773)-15),"") -> RAFAEL
B39: =IFERROR(INDEX(Movimentações!$A$6:$A$4773,COUNTA(Movimentações!$C$6:$C$4773)-16),"") -> 46204 | C39: =IFERROR(INDEX(Movimentações!$B$6:$B$4773,COUNTA(Movimentações!$C$6:$C$4773)-16),"") -> ENTRADA | D39: =IFERROR(INDEX(Movimentações!$C$6:$C$4773,COUNTA(Movimentações!$C$6:$C$4773)-16),"") -> BTG-2211 | E39: =IFERROR(INDEX(Movimentações!$D$6:$D$4773,COUNTA(Movimentações!$C$6:$C$4773)-16),"") -> POLO PIQUET ARPOADOR MASC. | F39: =IFERROR(INDEX(Movimentações!$E$6:$E$4773,COUNTA(Movimentações!$C$6:$C$4773)-16),"") -> 18 | G39: =IFERROR(INDEX(Movimentações!$G$6:$G$4773,COUNTA(Movimentações!$C$6:$C$4773)-16),"") -> Store | H39: =IFERROR(INDEX(Movimentações!$K$6:$K$4773,COUNTA(Movimentações!$C$6:$C$4773)-16),"") -> RAFAEL
B40: =IFERROR(INDEX(Movimentações!$A$6:$A$4773,COUNTA(Movimentações!$C$6:$C$4773)-17),"") -> 46204 | C40: =IFERROR(INDEX(Movimentações!$B$6:$B$4773,COUNTA(Movimentações!$C$6:$C$4773)-17),"") -> ENTRADA | D40: =IFERROR(INDEX(Movimentações!$C$6:$C$4773,COUNTA(Movimentações!$C$6:$C$4773)-17),"") -> BTG-2210 | E40: =IFERROR(INDEX(Movimentações!$D$6:$D$4773,COUNTA(Movimentações!$C$6:$C$4773)-17),"") -> POLO PIQUET ARPOADOR MASC. | F40: =IFERROR(INDEX(Movimentações!$E$6:$E$4773,COUNTA(Movimentações!$C$6:$C$4773)-17),"") -> 60 | G40: =IFERROR(INDEX(Movimentações!$G$6:$G$4773,COUNTA(Movimentações!$C$6:$C$4773)-17),"") -> Store | H40: =IFERROR(INDEX(Movimentações!$K$6:$K$4773,COUNTA(Movimentações!$C$6:$C$4773)-17),"") -> RAFAEL
B41: =IFERROR(INDEX(Movimentações!$A$6:$A$4773,COUNTA(Movimentações!$C$6:$C$4773)-18),"") -> 46204 | C41: =IFERROR(INDEX(Movimentações!$B$6:$B$4773,COUNTA(Movimentações!$C$6:$C$4773)-18),"") -> ENTRADA | D41: =IFERROR(INDEX(Movimentações!$C$6:$C$4773,COUNTA(Movimentações!$C$6:$C$4773)-18),"") -> BTG-2210 | E41: =IFERROR(INDEX(Movimentações!$D$6:$D$4773,COUNTA(Movimentações!$C$6:$C$4773)-18),"") -> POLO PIQUET ARPOADOR MASC. | F41: =IFERROR(INDEX(Movimentações!$E$6:$E$4773,COUNTA(Movimentações!$C$6:$C$4773)-18),"") -> 24 | G41: =IFERROR(INDEX(Movimentações!$G$6:$G$4773,COUNTA(Movimentações!$C$6:$C$4773)-18),"") -> Store | H41: =IFERROR(INDEX(Movimentações!$K$6:$K$4773,COUNTA(Movimentações!$C$6:$C$4773)-18),"") -> RAFAEL
B42: =IFERROR(INDEX(Movimentações!$A$6:$A$4773,COUNTA(Movimentações!$C$6:$C$4773)-19),"") -> 46204 | C42: =IFERROR(INDEX(Movimentações!$B$6:$B$4773,COUNTA(Movimentações!$C$6:$C$4773)-19),"") -> ENTRADA | D42: =IFERROR(INDEX(Movimentações!$C$6:$C$4773,COUNTA(Movimentações!$C$6:$C$4773)-19),"") -> BTG-2208 | E42: =IFERROR(INDEX(Movimentações!$D$6:$D$4773,COUNTA(Movimentações!$C$6:$C$4773)-19),"") -> POLO PIQUET ARPOADOR MASC. | F42: =IFERROR(INDEX(Movimentações!$E$6:$E$4773,COUNTA(Movimentações!$C$6:$C$4773)-19),"") -> 60 | G42: =IFERROR(INDEX(Movimentações!$G$6:$G$4773,COUNTA(Movimentações!$C$6:$C$4773)-19),"") -> Store | H42: =IFERROR(INDEX(Movimentações!$K$6:$K$4773,COUNTA(Movimentações!$C$6:$C$4773)-19),"") -> RAFAEL

Sheet Catálogo
B2: BTG PACTUAL · CATÁLOGO · ESTOQUE BTG
B3: 1 linha por produto (código da cliente) · Estoque BTG consolidado · filtre por GRUPO ou CATEGORIA
B5: PRODUTOS | D5: PEÇAS EM ESTOQUE | G5: CUSTO TOTAL DO ESTOQUE
B6: =COUNTA(Catalogo[CÓD. CLIENTE]) -> 600 | D6: =SUM(Catalogo[ESTOQUE BTG]) -> 13596 | G6: =SUM(Catalogo[CUSTO TOTAL]) -> 0
A7: # | B7: CÓD. CLIENTE | C7: GÊNERO | D7: CATEGORIA | E7: GRUPO | F7: PRODUTO | G7: COR | H7: TAM | I7: PREÇO UNIT. | J7: ESTOQUE BTG | K7: CUSTO TOTAL | L7: # SKUs | M7: PEDIDO 1- entregar BTG (saida) | N7: PEDIDO 2 BTG entregar Dutelog (entrada) | O7: PEDIDO 3- applicato entregar duelog 12/06 | P7: PEDIDO 4- applicato entregar duelog 29/06 | Q7: PEDIDO 5- applicato entregar duelog 15/07 | R7: PEDIDO 6- applicato entregar duelog 20/07 | S7: PEDIDO 7- applicato entregar duelog 30/07 | T7: PEDIDO 8- applicato entregar duelog 01/11 | U7: QTD SOLIC. | V7: DISPONÍVEL
A8: 1 | B8: A.01.0782.001.P | C8: =IF(B8="","",IFERROR(IF(TRIM(MID(SUBSTITUTE(B8,".",REPT(" ",50)),51,50))="01","Masculino",IF(TRIM(MID(SUBSTITUTE(B8,".",REPT(" ",50)),51,50))="02","Feminino",IF(TRIM(MID(SUBSTITUTE(B8,".",REPT(" ",50)),51,50))="03","Outros","—"))),"—")) -> Masculino | D8: =IFERROR(INDEX(SKUs!$E$6:$E$1997,MATCH(B8,SKUs!$C$6:$C$1997,0)),"") -> POLO | E8: =IFERROR(VLOOKUP(D8,Configurações!$N$5:$O$46,2,FALSE()),"OUTROS") -> VESTUÁRIO | F8: =IFERROR(INDEX(SKUs!$F$6:$F$1997,MATCH(B8,SKUs!$C$6:$C$1997,0)),"") -> POLO COPA MASC. | G8: =IFERROR(INDEX(SKUs!$G$6:$G$1997,MATCH(B8,SKUs!$C$6:$C$1997,0)),"") -> AZUL | H8: =IFERROR(INDEX(SKUs!$H$6:$H$1997,MATCH(B8,SKUs!$C$6:$C$1997,0)),"") -> G | I8: =IFERROR(INDEX(SKUs!#REF!,MATCH(B8,SKUs!$C$6:$C$1997,0)),"") | J8: =SUMIFS(SKUs!$I$6:$I$1997,SKUs!$C$6:$C$1997,B8) -> 0 | K8: =IFERROR(I8*J8,0) -> 0 | L8: =COUNTIF(SKUs!$C$6:$C$1997,B8) -> 1 | U8: =SUM(M8:R8) -> 0 | V8: =IF(B8="","",J8) -> 0
A9: 2 | B9: A.01.0782.001.M | C9: =IF(B9="","",IFERROR(IF(TRIM(MID(SUBSTITUTE(B9,".",REPT(" ",50)),51,50))="01","Masculino",IF(TRIM(MID(SUBSTITUTE(B9,".",REPT(" ",50)),51,50))="02","Feminino",IF(TRIM(MID(SUBSTITUTE(B9,".",REPT(" ",50)),51,50))="03","Outros","—"))),"—")) -> Masculino | D9: =IFERROR(INDEX(SKUs!$E$6:$E$1997,MATCH(B9,SKUs!$C$6:$C$1997,0)),"") -> POLO | E9: =IFERROR(VLOOKUP(D9,Configurações!$N$5:$O$46,2,FALSE()),"OUTROS") -> VESTUÁRIO | F9: =IFERROR(INDEX(SKUs!$F$6:$F$1997,MATCH(B9,SKUs!$C$6:$C$1997,0)),"") -> POLO COPA MASC. | G9: =IFERROR(INDEX(SKUs!$G$6:$G$1997,MATCH(B9,SKUs!$C$6:$C$1997,0)),"") -> AZUL | H9: =IFERROR(INDEX(SKUs!$H$6:$H$1997,MATCH(B9,SKUs!$C$6:$C$1997,0)),"") -> M | I9: =IFERROR(INDEX(SKUs!#REF!,MATCH(B9,SKUs!$C$6:$C$1997,0)),"") | J9: =SUMIFS(SKUs!$I$6:$I$1997,SKUs!$C$6:$C$1997,B9) -> 0 | K9: =IFERROR(I9*J9,0) -> 0 | L9: =COUNTIF(SKUs!$C$6:$C$1997,B9) -> 1 | U9: =SUM(M9:R9) -> 0 | V9: =IF(B9="","",J9) -> 0
A10: 3 | B10: A.01.0782.001.G | C10: =IF(B10="","",IFERROR(IF(TRIM(MID(SUBSTITUTE(B10,".",REPT(" ",50)),51,50))="01","Masculino",IF(TRIM(MID(SUBSTITUTE(B10,".",REPT(" ",50)),51,50))="02","Feminino",IF(TRIM(MID(SUBSTITUTE(B10,".",REPT(" ",50)),51,50))="03","Outros","—"))),"—")) -> Masculino | D10: =IFERROR(INDEX(SKUs!$E$6:$E$1997,MATCH(B10,SKUs!$C$6:$C$1997,0)),"") -> POLO | E10: =IFERROR(VLOOKUP(D10,Configurações!$N$5:$O$46,2,FALSE()),"OUTROS") -> VESTUÁRIO | F10: =IFERROR(INDEX(SKUs!$F$6:$F$1997,MATCH(B10,SKUs!$C$6:$C$1997,0)),"") -> POLO COPA MASC. | G10: =IFERROR(INDEX(SKUs!$G$6:$G$1997,MATCH(B10,SKUs!$C$6:$C$1997,0)),"") -> AZUL | H10: =IFERROR(INDEX(SKUs!$H$6:$H$1997,MATCH(B10,SKUs!$C$6:$C$1997,0)),"") -> XG | I10: =IFERROR(INDEX(SKUs!#REF!,MATCH(B10,SKUs!$C$6:$C$1997,0)),"") | J10: =SUMIFS(SKUs!$I$6:$I$1997,SKUs!$C$6:$C$1997,B10) -> 0 | K10: =IFERROR(I10*J10,0) -> 0 | L10: =COUNTIF(SKUs!$C$6:$C$1997,B10) -> 2 | U10: =SUM(M10:R10) -> 0 | V10: =IF(B10="","",J10) -> 0
A11: 4 | B11: A.01.0782.001.2G | C11: =IF(B11="","",IFERROR(IF(TRIM(MID(SUBSTITUTE(B11,".",REPT(" ",50)),51,50))="01","Masculino",IF(TRIM(MID(SUBSTITUTE(B11,".",REPT(" ",50)),51,50))="02","Feminino",IF(TRIM(MID(SUBSTITUTE(B11,".",REPT(" ",50)),51,50))="03","Outros","—"))),"—")) -> Masculino | D11: =IFERROR(INDEX(SKUs!$E$6:$E$1997,MATCH(B11,SKUs!$C$6:$C$1997,0)),"") -> POLO | E11: =IFERROR(VLOOKUP(D11,Configurações!$N$5:$O$46,2,FALSE()),"OUTROS") -> VESTUÁRIO | F11: =IFERROR(INDEX(SKUs!$F$6:$F$1997,MATCH(B11,SKUs!$C$6:$C$1997,0)),"") -> POLO COPA MASC. | G11: =IFERROR(INDEX(SKUs!$G$6:$G$1997,MATCH(B11,SKUs!$C$6:$C$1997,0)),"") -> AZUL | H11: =IFERROR(INDEX(SKUs!$H$6:$H$1997,MATCH(B11,SKUs!$C$6:$C$1997,0)),"") -> P | I11: =IFERROR(INDEX(SKUs!#REF!,MATCH(B11,SKUs!$C$6:$C$1997,0)),"") | J11: =SUMIFS(SKUs!$I$6:$I$1997,SKUs!$C$6:$C$1997,B11) -> 0 | K11: =IFERROR(I11*J11,0) -> 0 | L11: =COUNTIF(SKUs!$C$6:$C$1997,B11) -> 2 | U11: =SUM(M11:R11) -> 0 | V11: =IF(B11="","",J11) -> 0
A12: 5 | B12: A.01.0782.001.3G | C12: =IF(B12="","",IFERROR(IF(TRIM(MID(SUBSTITUTE(B12,".",REPT(" ",50)),51,50))="01","Masculino",IF(TRIM(MID(SUBSTITUTE(B12,".",REPT(" ",50)),51,50))="02","Feminino",IF(TRIM(MID(SUBSTITUTE(B12,".",REPT(" ",50)),51,50))="03","Outros","—"))),"—")) -> Masculino | D12: =IFERROR(INDEX(SKUs!$E$6:$E$1997,MATCH(B12,SKUs!$C$6:$C$1997,0)),"") -> POLO | E12: =IFERROR(VLOOKUP(D12,Configurações!$N$5:$O$46,2,FALSE()),"OUTROS") -> VESTUÁRIO | F12: =IFERROR(INDEX(SKUs!$F$6:$F$1997,MATCH(B12,SKUs!$C$6:$C$1997,0)),"") -> POLO COPA MASC. | G12: =IFERROR(INDEX(SKUs!$G$6:$G$1997,MATCH(B12,SKUs!$C$6:$C$1997,0)),"") -> AZUL | H12: =IFERROR(INDEX(SKUs!$H$6:$H$1997,MATCH(B12,SKUs!$C$6:$C$1997,0)),"") -> GG | I12: =IFERROR(INDEX(SKUs!#REF!,MATCH(B12,SKUs!$C$6:$C$1997,0)),"") | J12: =SUMIFS(SKUs!$I$6:$I$1997,SKUs!$C$6:$C$1997,B12) -> 0 | K12: =IFERROR(I12*J12,0) -> 0 | L12: =COUNTIF(SKUs!$C$6:$C$1997,B12) -> 1 | U12: =SUM(M12:R12) -> 0 | V12: =IF(B12="","",J12) -> 0
A13: 6 | B13: A.01.0782.001.4G | C13: =IF(B13="","",IFERROR(IF(TRIM(MID(SUBSTITUTE(B13,".",REPT(" ",50)),51,50))="01","Masculino",IF(TRIM(MID(SUBSTITUTE(B13,".",REPT(" ",50)),51,50))="02","Feminino",IF(TRIM(MID(SUBSTITUTE(B13,".",REPT(" ",50)),51,50))="03","Outros","—"))),"—")) -> Masculino | D13: =IFERROR(INDEX(SKUs!$E$6:$E$1997,MATCH(B13,SKUs!$C$6:$C$1997,0)),"") -> CAMISETA | E13: =IFERROR(VLOOKUP(D13,Configurações!$N$5:$O$46,2,FALSE()),"OUTROS") -> VESTUÁRIO | F13: =IFERROR(INDEX(SKUs!$F$6:$F$1997,MATCH(B13,SKUs!$C$6:$C$1997,0)),"") -> CAMISETA COPA MASC. | G13: =IFERROR(INDEX(SKUs!$G$6:$G$1997,MATCH(B13,SKUs!$C$6:$C$1997,0)),"") -> AZUL | H13: =IFERROR(INDEX(SKUs!$H$6:$H$1997,MATCH(B13,SKUs!$C$6:$C$1997,0)),"") -> P | I13: =IFERROR(INDEX(SKUs!#REF!,MATCH(B13,SKUs!$C$6:$C$1997,0)),"") | J13: =SUMIFS(SKUs!$I$6:$I$1997,SKUs!$C$6:$C$1997,B13) -> 0 | K13: =IFERROR(I13*J13,0) -> 0 | L13: =COUNTIF(SKUs!$C$6:$C$1997,B13) -> 1 | U13: =SUM(M13:R13) -> 0 | V13: =IF(B13="","",J13) -> 0
A14: 7 | B14: A.01.0776.001.M | C14: =IF(B14="","",IFERROR(IF(TRIM(MID(SUBSTITUTE(B14,".",REPT(" ",50)),51,50))="01","Masculino",IF(TRIM(MID(SUBSTITUTE(B14,".",REPT(" ",50)),51,50))="02","Feminino",IF(TRIM(MID(SUBSTITUTE(B14,".",REPT(" ",50)),51,50))="03","Outros","—"))),"—")) -> Masculino | D14: =IFERROR(INDEX(SKUs!$E$6:$E$1997,MATCH(B14,SKUs!$C$6:$C$1997,0)),"") -> CAMISETA | E14: =IFERROR(VLOOKUP(D14,Configurações!$N$5:$O$46,2,FALSE()),"OUTROS") -> VESTUÁRIO | F14: =IFERROR(INDEX(SKUs!$F$6:$F$1997,MATCH(B14,SKUs!$C$6:$C$1997,0)),"") -> CAMISETA COPA MASC. | G14: =IFERROR(INDEX(SKUs!$G$6:$G$1997,MATCH(B14,SKUs!$C$6:$C$1997,0)),"") -> AZUL | H14: =IFERROR(INDEX(SKUs!$H$6:$H$1997,MATCH(B14,SKUs!$C$6:$C$1997,0)),"") -> M | I14: =IFERROR(INDEX(SKUs!#REF!,MATCH(B14,SKUs!$C$6:$C$1997,0)),"") | J14: =SUMIFS(SKUs!$I$6:$I$1997,SKUs!$C$6:$C$1997,B14) -> 0 | K14: =IFERROR(I14*J14,0) -> 0 | L14: =COUNTIF(SKUs!$C$6:$C$1997,B14) -> 1 | U14: =SUM(M14:R14) -> 0 | V14: =IF(B14="","",J14) -> 0
A15: 8 | B15: A.01.0776.001.G | C15: =IF(B15="","",IFERROR(IF(TRIM(MID(SUBSTITUTE(B15,".",REPT(" ",50)),51,50))="01","Masculino",IF(TRIM(MID(SUBSTITUTE(B15,".",REPT(" ",50)),51,50))="02","Feminino",IF(TRIM(MID(SUBSTITUTE(B15,".",REPT(" ",50)),51,50))="03","Outros","—"))),"—")) -> Masculino | D15: =IFERROR(INDEX(SKUs!$E$6:$E$1997,MATCH(B15,SKUs!$C$6:$C$1997,0)),"") -> CAMISETA | E15: =IFERROR(VLOOKUP(D15,Configurações!$N$5:$O$46,2,FALSE()),"OUTROS") -> VESTUÁRIO | F15: =IFERROR(INDEX(SKUs!$F$6:$F$1997,MATCH(B15,SKUs!$C$6:$C$1997,0)),"") -> CAMISETA COPA MASC. | G15: =IFERROR(INDEX(SKUs!$G$6:$G$1997,MATCH(B15,SKUs!$C$6:$C$1997,0)),"") -> AZUL | H15: =IFERROR(INDEX(SKUs!$H$6:$H$1997,MATCH(B15,SKUs!$C$6:$C$1997,0)),"") -> GG | I15: =IFERROR(INDEX(SKUs!#REF!,MATCH(B15,SKUs!$C$6:$C$1997,0)),"") | J15: =SUMIFS(SKUs!$I$6:$I$1997,SKUs!$C$6:$C$1997,B15) -> 0 | K15: =IFERROR(I15*J15,0) -> 0 | L15: =COUNTIF(SKUs!$C$6:$C$1997,B15) -> 1 | U15: =SUM(M15:R15) -> 0 | V15: =IF(B15="","",J15) -> 0
A16: 9 | B16: A.01.0776.001.2G | C16: =IF(B16="","",IFERROR(IF(TRIM(MID(SUBSTITUTE(B16,".",REPT(" ",50)),51,50))="01","Masculino",IF(TRIM(MID(SUBSTITUTE(B16,".",REPT(" ",50)),51,50))="02","Feminino",IF(TRIM(MID(SUBSTITUTE(B16,".",REPT(" ",50)),51,50))="03","Outros","—"))),"—")) -> Masculino | D16: =IFERROR(INDEX(SKUs!$E$6:$E$1997,MATCH(B16,SKUs!$C$6:$C$1997,0)),"") -> CAMISETA | E16: =IFERROR(VLOOKUP(D16,Configurações!$N$5:$O$46,2,FALSE()),"OUTROS") -> VESTUÁRIO | F16: =IFERROR(INDEX(SKUs!$F$6:$F$1997,MATCH(B16,SKUs!$C$6:$C$1997,0)),"") -> CAMISETA COPA MASC. | G16: =IFERROR(INDEX(SKUs!$G$6:$G$1997,MATCH(B16,SKUs!$C$6:$C$1997,0)),"") -> AZUL | H16: =IFERROR(INDEX(SKUs!$H$6:$H$1997,MATCH(B16,SKUs!$C$6:$C$1997,0)),"") -> G | I16: =IFERROR(INDEX(SKUs!#REF!,MATCH(B16,SKUs!$C$6:$C$1997,0)),"") | J16: =SUMIFS(SKUs!$I$6:$I$1997,SKUs!$C$6:$C$1997,B16) -> 0 | K16: =IFERROR(I16*J16,0) -> 0 | L16: =COUNTIF(SKUs!$C$6:$C$1997,B16) -> 1 | U16: =SUM(M16:R16) -> 0 | V16: =IF(B16="","",J16) -> 0
A17: 10 | B17: A.01.0776.001.3G | C17: =IF(B17="","",IFERROR(IF(TRIM(MID(SUBSTITUTE(B17,".",REPT(" ",50)),51,50))="01","Masculino",IF(TRIM(MID(SUBSTITUTE(B17,".",REPT(" ",50)),51,50))="02","Feminino",IF(TRIM(MID(SUBSTITUTE(B17,".",REPT(" ",50)),51,50))="03","Outros","—"))),"—")) -> Masculino | D17: =IFERROR(INDEX(SKUs!$E$6:$E$1997,MATCH(B17,SKUs!$C$6:$C$1997,0)),"") -> CAMISETA | E17: =IFERROR(VLOOKUP(D17,Configurações!$N$5:$O$46,2,FALSE()),"OUTROS") -> VESTUÁRIO | F17: =IFERROR(INDEX(SKUs!$F$6:$F$1997,MATCH(B17,SKUs!$C$6:$C$1997,0)),"") -> CAMISETA COPA MASC. | G17: =IFERROR(INDEX(SKUs!$G$6:$G$1997,MATCH(B17,SKUs!$C$6:$C$1997,0)),"") -> AZUL | H17: =IFERROR(INDEX(SKUs!$H$6:$H$1997,MATCH(B17,SKUs!$C$6:$C$1997,0)),"") -> XG | I17: =IFERROR(INDEX(SKUs!#REF!,MATCH(B17,SKUs!$C$6:$C$1997,0)),"") | J17: =SUMIFS(SKUs!$I$6:$I$1997,SKUs!$C$6:$C$1997,B17) -> 0 | K17: =IFERROR(I17*J17,0) -> 0 | L17: =COUNTIF(SKUs!$C$6:$C$1997,B17) -> 1 | U17: =SUM(M17:R17) -> 0 | V17: =IF(B17="","",J17) -> 0
A18: 11 | B18: A.01.0776.001.4G | C18: =IF(B18="","",IFERROR(IF(TRIM(MID(SUBSTITUTE(B18,".",REPT(" ",50)),51,50))="01","Masculino",IF(TRIM(MID(SUBSTITUTE(B18,".",REPT(" ",50)),51,50))="02","Feminino",IF(TRIM(MID(SUBSTITUTE(B18,".",REPT(" ",50)),51,50))="03","Outros","—"))),"—")) -> Masculino | D18: =IFERROR(INDEX(SKUs!$E$6:$E$1997,MATCH(B18,SKUs!$C$6:$C$1997,0)),"") -> CAMISETA | E18: =IFERROR(VLOOKUP(D18,Configurações!$N$5:$O$46,2,FALSE()),"OUTROS") -> VESTUÁRIO | F18: =IFERROR(INDEX(SKUs!$F$6:$F$1997,MATCH(B18,SKUs!$C$6:$C$1997,0)),"") -> CAMISETA COPA MASC. | G18: =IFERROR(INDEX(SKUs!$G$6:$G$1997,MATCH(B18,SKUs!$C$6:$C$1997,0)),"") -> AZUL | H18: =IFERROR(INDEX(SKUs!$H$6:$H$1997,MATCH(B18,SKUs!$C$6:$C$1997,0)),"") -> 4G | I18: =IFERROR(INDEX(SKUs!#REF!,MATCH(B18,SKUs!$C$6:$C$1997,0)),"") | J18: =SUMIFS(SKUs!$I$6:$I$1997,SKUs!$C$6:$C$1997,B18) -> 0 | K18: =IFERROR(I18*J18,0) -> 0 | L18: =COUNTIF(SKUs!$C$6:$C$1997,B18) -> 1 | U18: =SUM(M18:R18) -> 0 | V18: =IF(B18="","",J18) -> 0
A19: 12 | B19: A.01.0778.009.P | C19: =IF(B19="","",IFERROR(IF(TRIM(MID(SUBSTITUTE(B19,".",REPT(" ",50)),51,50))="01","Masculino",IF(TRIM(MID(SUBSTITUTE(B19,".",REPT(" ",50)),51,50))="02","Feminino",IF(TRIM(MID(SUBSTITUTE(B19,".",REPT(" ",50)),51,50))="03","Outros","—"))),"—")) -> Masculino | D19: =IFERROR(INDEX(SKUs!$E$6:$E$1997,MATCH(B19,SKUs!$C$6:$C$1997,0)),"") -> CAMISETA | E19: =IFERROR(VLOOKUP(D19,Configurações!$N$5:$O$46,2,FALSE()),"OUTROS") -> VESTUÁRIO | F19: =IFERROR(INDEX(SKUs!$F$6:$F$1997,MATCH(B19,SKUs!$C$6:$C$1997,0)),"") -> CAMISETA COPA MASC. | G19: =IFERROR(INDEX(SKUs!$G$6:$G$1997,MATCH(B19,SKUs!$C$6:$C$1997,0)),"") -> AMARELA | H19: =IFERROR(INDEX(SKUs!$H$6:$H$1997,MATCH(B19,SKUs!$C$6:$C$1997,0)),"") -> P | I19: =IFERROR(INDEX(SKUs!#REF!,MATCH(B19,SKUs!$C$6:$C$1997,0)),"") | J19: =SUMIFS(SKUs!$I$6:$I$1997,SKUs!$C$6:$C$1997,B19) -> 0 | K19: =IFERROR(I19*J19,0) -> 0 | L19: =COUNTIF(SKUs!$C$6:$C$1997,B19) -> 1 | U19: =SUM(M19:R19) -> 0 | V19: =IF(B19="","",J19) -> 0
... A37: 30 | B37: A.01.0768.011.G | C37: =IF(B37="","",IFERROR(IF(TRIM(MID(SUBSTITUTE(B37,".",REPT(" ",50)),51,50))="01","Masculino",IF(TRIM(MID(SUBSTITUTE(B37,".",REPT(" ",50)),51,50))="02","Feminino",IF(TRIM(MID(SUBSTITUTE(B37,".",REPT(" ",50)),51,50))="03","Outros","—"))),"—")) -> Masculino | D37: =IFERROR(INDEX(SKUs!$E$6:$E$1997,MATCH(B37,SKUs!$C$6:$C$1997,0)),"") -> JAQUETA | E37: =IFERROR(VLOOKUP(D37,Configurações!$N$5:$O$46,2,FALSE()),"OUTROS") -> VESTUÁRIO | F37: =IFERROR(INDEX(SKUs!$F$6:$F$1997,MATCH(B37,SKUs!$C$6:$C$1997,0)),"") -> JAQUETA COPA MASC. | G37: =IFERROR(INDEX(SKUs!$G$6:$G$1997,MATCH(B37,SKUs!$C$6:$C$1997,0)),"") -> VERDE | H37: =IFERROR(INDEX(SKUs!$H$6:$H$1997,MATCH(B37,SKUs!$C$6:$C$1997,0)),"") -> G | I37: =IFERROR(INDEX(SKUs!#REF!,MATCH(B37,SKUs!$C$6:$C$1997,0)),"") | J37: =SUMIFS(SKUs!$I$6:$I$1997,SKUs!$C$6:$C$1997,B37) -> 10 | K37: =IFERROR(I37*J37,0) -> 0 | L37: =COUNTIF(SKUs!$C$6:$C$1997,B37) -> 1 | U37: =SUM(M37:R37) -> 0 | V37: =IF(B37="","",J37) -> 10
A38: 31 | B38: A.01.0768.011.GG | C38: =IF(B38="","",IFERROR(IF(TRIM(MID(SUBSTITUTE(B38,".",REPT(" ",50)),51,50))="01","Masculino",IF(TRIM(MID(SUBSTITUTE(B38,".",REPT(" ",50)),51,50))="02","Feminino",IF(TRIM(MID(SUBSTITUTE(B38,".",REPT(" ",50)),51,50))="03","Outros","—"))),"—")) -> Masculino | D38: =IFERROR(INDEX(SKUs!$E$6:$E$1997,MATCH(B38,SKUs!$C$6:$C$1997,0)),"") -> JAQUETA | E38: =IFERROR(VLOOKUP(D38,Configurações!$N$5:$O$46,2,FALSE()),"OUTROS") -> VESTUÁRIO | F38: =IFERROR(INDEX(SKUs!$F$6:$F$1997,MATCH(B38,SKUs!$C$6:$C$1997,0)),"") -> JAQUETA COPA MASC. | G38: =IFERROR(INDEX(SKUs!$G$6:$G$1997,MATCH(B38,SKUs!$C$6:$C$1997,0)),"") -> VERDE | H38: =IFERROR(INDEX(SKUs!$H$6:$H$1997,MATCH(B38,SKUs!$C$6:$C$1997,0)),"") -> GG | I38: =IFERROR(INDEX(SKUs!#REF!,MATCH(B38,SKUs!$C$6:$C$1997,0)),"") | J38: =SUMIFS(SKUs!$I$6:$I$1997,SKUs!$C$6:$C$1997,B38) -> 0 | K38: =IFERROR(I38*J38,0) -> 0 | L38: =COUNTIF(SKUs!$C$6:$C$1997,B38) -> 2 | M38: 10 | U38: =SUM(M38:R38) -> 10 | V38: =IF(B38="","",J38) -> 0
A39: 32 | B39: A.01.0768.011.XG | C39: =IF(B39="","",IFERROR(IF(TRIM(MID(SUBSTITUTE(B39,".",REPT(" ",50)),51,50))="01","Masculino",IF(TRIM(MID(SUBSTITUTE(B39,".",REPT(" ",50)),51,50))="02","Feminino",IF(TRIM(MID(SUBSTITUTE(B39,".",REPT(" ",50)),51,50))="03","Outros","—"))),"—")) -> Masculino | D39: =IFERROR(INDEX(SKUs!$E$6:$E$1997,MATCH(B39,SKUs!$C$6:$C$1997,0)),"") -> JAQUETA | E39: =IFERROR(VLOOKUP(D39,Configurações!$N$5:$O$46,2,FALSE()),"OUTROS") -> VESTUÁRIO | F39: =IFERROR(INDEX(SKUs!$F$6:$F$1997,MATCH(B39,SKUs!$C$6:$C$1997,0)),"") -> JAQUETA COPA MASC. | G39: =IFERROR(INDEX(SKUs!$G$6:$G$1997,MATCH(B39,SKUs!$C$6:$C$1997,0)),"") -> VERDE | H39: =IFERROR(INDEX(SKUs!$H$6:$H$1997,MATCH(B39,SKUs!$C$6:$C$1997,0)),"") -> XG | I39: =IFERROR(INDEX(SKUs!#REF!,MATCH(B39,SKUs!$C$6:$C$1997,0)),"") | J39: =SUMIFS(SKUs!$I$6:$I$1997,SKUs!$C$6:$C$1997,B39) -> 0 | K39: =IFERROR(I39*J39,0) -> 0 | L39: =COUNTIF(SKUs!$C$6:$C$1997,B39) -> 1 | M39: 10 | U39: =SUM(M39:R39) -> 10 | V39: =IF(B39="","",J39) -> 0
A40: 33 | B40: A.01.0772.001.P | C40: =IF(B40="","",IFERROR(IF(TRIM(MID(SUBSTITUTE(B40,".",REPT(" ",50)),51,50))="01","Masculino",IF(TRIM(MID(SUBSTITUTE(B40,".",REPT(" ",50)),51,50))="02","Feminino",IF(TRIM(MID(SUBSTITUTE(B40,".",REPT(" ",50)),51,50))="03","Outros","—"))),"—")) -> Masculino | D40: =IFERROR(INDEX(SKUs!$E$6:$E$1997,MATCH(B40,SKUs!$C$6:$C$1997,0)),"") -> JAQUETA | E40: =IFERROR(VLOOKUP(D40,Configurações!$N$5:$O$46,2,FALSE()),"OUTROS") -> VESTUÁRIO | F40: =IFERROR(INDEX(SKUs!$F$6:$F$1997,MATCH(B40,SKUs!$C$6:$C$1997,0)),"") -> JAQUETA COPA MASC. | G40: =IFERROR(INDEX(SKUs!$G$6:$G$1997,MATCH(B40,SKUs!$C$6:$C$1997,0)),"") -> AZUL | H40: =IFERROR(INDEX(SKUs!$H$6:$H$1997,MATCH(B40,SKUs!$C$6:$C$1997,0)),"") -> P | I40: =IFERROR(INDEX(SKUs!#REF!,MATCH(B40,SKUs!$C$6:$C$1997,0)),"") | J40: =SUMIFS(SKUs!$I$6:$I$1997,SKUs!$C$6:$C$1997,B40) -> 10 | K40: =IFERROR(I40*J40,0) -> 0 | L40: =COUNTIF(SKUs!$C$6:$C$1997,B40) -> 1 | U40: =SUM(M40:R40) -> 0 | V40: =IF(B40="","",J40) -> 10
A41: 34 | B41: A.01.0772.001.M | C41: =IF(B41="","",IFERROR(IF(TRIM(MID(SUBSTITUTE(B41,".",REPT(" ",50)),51,50))="01","Masculino",IF(TRIM(MID(SUBSTITUTE(B41,".",REPT(" ",50)),51,50))="02","Feminino",IF(TRIM(MID(SUBSTITUTE(B41,".",REPT(" ",50)),51,50))="03","Outros","—"))),"—")) -> Masculino | D41: =IFERROR(INDEX(SKUs!$E$6:$E$1997,MATCH(B41,SKUs!$C$6:$C$1997,0)),"") -> JAQUETA | E41: =IFERROR(VLOOKUP(D41,Configurações!$N$5:$O$46,2,FALSE()),"OUTROS") -> VESTUÁRIO | F41: =IFERROR(INDEX(SKUs!$F$6:$F$1997,MATCH(B41,SKUs!$C$6:$C$1997,0)),"") -> JAQUETA COPA MASC. | G41: =IFERROR(INDEX(SKUs!$G$6:$G$1997,MATCH(B41,SKUs!$C$6:$C$1997,0)),"") -> AZUL | H41: =IFERROR(INDEX(SKUs!$H$6:$H$1997,MATCH(B41,SKUs!$C$6:$C$1997,0)),"") -> M | I41: =IFERROR(INDEX(SKUs!#REF!,MATCH(B41,SKUs!$C$6:$C$1997,0)),"") | J41: =SUMIFS(SKUs!$I$6:$I$1997,SKUs!$C$6:$C$1997,B41) -> 10 | K41: =IFERROR(I41*J41,0) -> 0 | L41: =COUNTIF(SKUs!$C$6:$C$1997,B41) -> 1 | U41: =SUM(M41:R41) -> 0 | V41: =IF(B41="","",J41) -> 10
A42: 35 | B42: A.01.0772.001.G | C42: =IF(B42="","",IFERROR(IF(TRIM(MID(SUBSTITUTE(B42,".",REPT(" ",50)),51,50))="01","Masculino",IF(TRIM(MID(SUBSTITUTE(B42,".",REPT(" ",50)),51,50))="02","Feminino",IF(TRIM(MID(SUBSTITUTE(B42,".",REPT(" ",50)),51,50))="03","Outros","—"))),"—")) -> Masculino | D42: =IFERROR(INDEX(SKUs!$E$6:$E$1997,MATCH(B42,SKUs!$C$6:$C$1997,0)),"") -> JAQUETA | E42: =IFERROR(VLOOKUP(D42,Configurações!$N$5:$O$46,2,FALSE()),"OUTROS") -> VESTUÁRIO | F42: =IFERROR(INDEX(SKUs!$F$6:$F$1997,MATCH(B42,SKUs!$C$6:$C$1997,0)),"") -> JAQUETA COPA MASC. | G42: =IFERROR(INDEX(SKUs!$G$6:$G$1997,MATCH(B42,SKUs!$C$6:$C$1997,0)),"") -> AZUL | H42: =IFERROR(INDEX(SKUs!$H$6:$H$1997,MATCH(B42,SKUs!$C$6:$C$1997,0)),"") -> G | I42: =IFERROR(INDEX(SKUs!#REF!,MATCH(B42,SKUs!$C$6:$C$1997,0)),"") | J42: =SUMIFS(SKUs!$I$6:$I$1997,SKUs!$C$6:$C$1997,B42) -> 9 | K42: =IFERROR(I42*J42,0) -> 0 | L42: =COUNTIF(SKUs!$C$6:$C$1997,B42) -> 2 | U42: =SUM(M42:R42) -> 0 | V42: =IF(B42="","",J42) -> 9
A43: 36 | B43: A.01.0772.001.GG | C43: =IF(B43="","",IFERROR(IF(TRIM(MID(SUBSTITUTE(B43,".",REPT(" ",50)),51,50))="01","Masculino",IF(TRIM(MID(SUBSTITUTE(B43,".",REPT(" ",50)),51,50))="02","Feminino",IF(TRIM(MID(SUBSTITUTE(B43,".",REPT(" ",50)),51,50))="03","Outros","—"))),"—")) -> Masculino | D43: =IFERROR(INDEX(SKUs!$E$6:$E$1997,MATCH(B43,SKUs!$C$6:$C$1997,0)),"") -> JAQUETA | E43: =IFERROR(VLOOKUP(D43,Configurações!$N$5:$O$46,2,FALSE()),"OUTROS") -> VESTUÁRIO | F43: =IFERROR(INDEX(SKUs!$F$6:$F$1997,MATCH(B43,SKUs!$C$6:$C$1997,0)),"") -> JAQUETA COPA MASC. | G43: =IFERROR(INDEX(SKUs!$G$6:$G$1997,MATCH(B43,SKUs!$C$6:$C$1997,0)),"") -> AZUL | H43: =IFERROR(INDEX(SKUs!$H$6:$H$1997,MATCH(B43,SKUs!$C$6:$C$1997,0)),"") -> GG | I43: =IFERROR(INDEX(SKUs!#REF!,MATCH(B43,SKUs!$C$6:$C$1997,0)),"") | J43: =SUMIFS(SKUs!$I$6:$I$1997,SKUs!$C$6:$C$1997,B43) -> 9 | K43: =IFERROR(I43*J43,0) -> 0 | L43: =COUNTIF(SKUs!$C$6:$C$1997,B43) -> 1 | U43: =SUM(M43:R43) -> 0 | V43: =IF(B43="","",J43) -> 9
A44: 37 | B44: A.01.0772.001.XG | C44: =IF(B44="","",IFERROR(IF(TRIM(MID(SUBSTITUTE(B44,".",REPT(" ",50)),51,50))="01","Masculino",IF(TRIM(MID(SUBSTITUTE(B44,".",REPT(" ",50)),51,50))="02","Feminino",IF(TRIM(MID(SUBSTITUTE(B44,".",REPT(" ",50)),51,50))="03","Outros","—"))),"—")) -> Masculino | D44: =IFERROR(INDEX(SKUs!$E$6:$E$1997,MATCH(B44,SKUs!$C$6:$C$1997,0)),"") -> JAQUETA | E44: =IFERROR(VLOOKUP(D44,Configurações!$N$5:$O$46,2,FALSE()),"OUTROS") -> VESTUÁRIO | F44: =IFERROR(INDEX(SKUs!$F$6:$F$1997,MATCH(B44,SKUs!$C$6:$C$1997,0)),"") -> JAQUETA COPA MASC. | G44: =IFERROR(INDEX(SKUs!$G$6:$G$1997,MATCH(B44,SKUs!$C$6:$C$1997,0)),"") -> AZUL | H44: =IFERROR(INDEX(SKUs!$H$6:$H$1997,MATCH(B44,SKUs!$C$6:$C$1997,0)),"") -> XG | I44: =IFERROR(INDEX(SKUs!#REF!,MATCH(B44,SKUs!$C$6:$C$1997,0)),"") | J44: =SUMIFS(SKUs!$I$6:$I$1997,SKUs!$C$6:$C$1997,B44) -> 11 | K44: =IFERROR(I44*J44,0) -> 0 | L44: =COUNTIF(SKUs!$C$6:$C$1997,B44) -> 1 | U44: =SUM(M44:R44) -> 0 | V44: =IF(B44="","",J44) -> 11
A45: 38 | B45: A.01.0766.003.P | C45: =IF(B45="","",IFERROR(IF(TRIM(MID(SUBSTITUTE(B45,".",REPT(" ",50)),51,50))="01","Masculino",IF(TRIM(MID(SUBSTITUTE(B45,".",REPT(" ",50)),51,50))="02","Feminino",IF(TRIM(MID(SUBSTITUTE(B45,".",REPT(" ",50)),51,50))="03","Outros","—"))),"—")) -> Masculino | D45: =IFERROR(INDEX(SKUs!$E$6:$E$1997,MATCH(B45,SKUs!$C$6:$C$1997,0)),"") -> JAQUETA | E45: =IFERROR(VLOOKUP(D45,Configurações!$N$5:$O$46,2,FALSE()),"OUTROS") -> VESTUÁRIO | F45: =IFERROR(INDEX(SKUs!$F$6:$F$1997,MATCH(B45,SKUs!$C$6:$C$1997,0)),"") -> JAQUETA COPA MASC. | G45: =IFERROR(INDEX(SKUs!$G$6:$G$1997,MATCH(B45,SKUs!$C$6:$C$1997,0)),"") -> BRANCA | H45: =IFERROR(INDEX(SKUs!$H$6:$H$1997,MATCH(B45,SKUs!$C$6:$C$1997,0)),"") -> P | I45: =IFERROR(INDEX(SKUs!#REF!,MATCH(B45,SKUs!$C$6:$C$1997,0)),"") | J45: =SUMIFS(SKUs!$I$6:$I$1997,SKUs!$C$6:$C$1997,B45) -> 10 | K45: =IFERROR(I45*J45,0) -> 0 | L45: =COUNTIF(SKUs!$C$6:$C$1997,B45) -> 2 | U45: =SUM(M45:R45) -> 0 | V45: =IF(B45="","",J45) -> 10
A46: 39 | B46: A.01.0766.003.M | C46: =IF(B46="","",IFERROR(IF(TRIM(MID(SUBSTITUTE(B46,".",REPT(" ",50)),51,50))="01","Masculino",IF(TRIM(MID(SUBSTITUTE(B46,".",REPT(" ",50)),51,50))="02","Feminino",IF(TRIM(MID(SUBSTITUTE(B46,".",REPT(" ",50)),51,50))="03","Outros","—"))),"—")) -> Masculino | D46: =IFERROR(INDEX(SKUs!$E$6:$E$1997,MATCH(B46,SKUs!$C$6:$C$1997,0)),"") -> JAQUETA | E46: =IFERROR(VLOOKUP(D46,Configurações!$N$5:$O$46,2,FALSE()),"OUTROS") -> VESTUÁRIO | F46: =IFERROR(INDEX(SKUs!$F$6:$F$1997,MATCH(B46,SKUs!$C$6:$C$1997,0)),"") -> JAQUETA COPA MASC. | G46: =IFERROR(INDEX(SKUs!$G$6:$G$1997,MATCH(B46,SKUs!$C$6:$C$1997,0)),"") -> BRANCA | H46: =IFERROR(INDEX(SKUs!$H$6:$H$1997,MATCH(B46,SKUs!$C$6:$C$1997,0)),"") -> M | I46: =IFERROR(INDEX(SKUs!#REF!,MATCH(B46,SKUs!$C$6:$C$1997,0)),"") | J46: =SUMIFS(SKUs!$I$6:$I$1997,SKUs!$C$6:$C$1997,B46) -> 8 | K46: =IFERROR(I46*J46,0) -> 0 | L46: =COUNTIF(SKUs!$C$6:$C$1997,B46) -> 1 | U46: =SUM(M46:R46) -> 0 | V46: =IF(B46="","",J46) -> 8
A47: 40 | B47: A.01.0766.003.G | C47: =IF(B47="","",IFERROR(IF(TRIM(MID(SUBSTITUTE(B47,".",REPT(" ",50)),51,50))="01","Masculino",IF(TRIM(MID(SUBSTITUTE(B47,".",REPT(" ",50)),51,50))="02","Feminino",IF(TRIM(MID(SUBSTITUTE(B47,".",REPT(" ",50)),51,50))="03","Outros","—"))),"—")) -> Masculino | D47: =IFERROR(INDEX(SKUs!$E$6:$E$1997,MATCH(B47,SKUs!$C$6:$C$1997,0)),"") -> JAQUETA | E47: =IFERROR(VLOOKUP(D47,Configurações!$N$5:$O$46,2,FALSE()),"OUTROS") -> VESTUÁRIO | F47: =IFERROR(INDEX(SKUs!$F$6:$F$1997,MATCH(B47,SKUs!$C$6:$C$1997,0)),"") -> JAQUETA COPA MASC. | G47: =IFERROR(INDEX(SKUs!$G$6:$G$1997,MATCH(B47,SKUs!$C$6:$C$1997,0)),"") -> BRANCA | H47: =IFERROR(INDEX(SKUs!$H$6:$H$1997,MATCH(B47,SKUs!$C$6:$C$1997,0)),"") -> G | I47: =IFERROR(INDEX(SKUs!#REF!,MATCH(B47,SKUs!$C$6:$C$1997,0)),"") | J47: =SUMIFS(SKUs!$I$6:$I$1997,SKUs!$C$6:$C$1997,B47) -> 11 | K47: =IFERROR(I47*J47,0) -> 0 | L47: =COUNTIF(SKUs!$C$6:$C$1997,B47) -> 1 | U47: =SUM(M47:R47) -> 0 | V47: =IF(B47="","",J47) -> 11
A48: 41 | B48: A.01.0766.003.GG | C48: =IF(B48="","",IFERROR(IF(TRIM(MID(SUBSTITUTE(B48,".",REPT(" ",50)),51,50))="01","Masculino",IF(TRIM(MID(SUBSTITUTE(B48,".",REPT(" ",50)),51,50))="02","Feminino",IF(TRIM(MID(SUBSTITUTE(B48,".",REPT(" ",50)),51,50))="03","Outros","—"))),"—")) -> Masculino | D48: =IFERROR(INDEX(SKUs!$E$6:$E$1997,MATCH(B48,SKUs!$C$6:$C$1997,0)),"") -> JAQUETA | E48: =IFERROR(VLOOKUP(D48,Configurações!$N$5:$O$46,2,FALSE()),"OUTROS") -> VESTUÁRIO | F48: =IFERROR(INDEX(SKUs!$F$6:$F$1997,MATCH(B48,SKUs!$C$6:$C$1997,0)),"") -> JAQUETA COPA MASC. | G48: =IFERROR(INDEX(SKUs!$G$6:$G$1997,MATCH(B48,SKUs!$C$6:$C$1997,0)),"") -> BRANCA | H48: =IFERROR(INDEX(SKUs!$H$6:$H$1997,MATCH(B48,SKUs!$C$6:$C$1997,0)),"") -> GG | I48: =IFERROR(INDEX(SKUs!#REF!,MATCH(B48,SKUs!$C$6:$C$1997,0)),"") | J48: =SUMIFS(SKUs!$I$6:$I$1997,SKUs!$C$6:$C$1997,B48) -> 9 | K48: =IFERROR(I48*J48,0) -> 0 | L48: =COUNTIF(SKUs!$C$6:$C$1997,B48) -> 1 | U48: =SUM(M48:R48) -> 0 | V48: =IF(B48="","",J48) -> 9
A49: 42 | B49: A.01.0766.003.XG | C49: =IF(B49="","",IFERROR(IF(TRIM(MID(SUBSTITUTE(B49,".",REPT(" ",50)),51,50))="01","Masculino",IF(TRIM(MID(SUBSTITUTE(B49,".",REPT(" ",50)),51,50))="02","Feminino",IF(TRIM(MID(SUBSTITUTE(B49,".",REPT(" ",50)),51,50))="03","Outros","—"))),"—")) -> Masculino | D49: =IFERROR(INDEX(SKUs!$E$6:$E$1997,MATCH(B49,SKUs!$C$6:$C$1997,0)),"") -> JAQUETA | E49: =IFERROR(VLOOKUP(D49,Configurações!$N$5:$O$46,2,FALSE()),"OUTROS") -> VESTUÁRIO | F49: =IFERROR(INDEX(SKUs!$F$6:$F$1997,MATCH(B49,SKUs!$C$6:$C$1997,0)),"") -> JAQUETA COPA MASC. | G49: =IFERROR(INDEX(SKUs!$G$6:$G$1997,MATCH(B49,SKUs!$C$6:$C$1997,0)),"") -> BRANCA | H49: =IFERROR(INDEX(SKUs!$H$6:$H$1997,MATCH(B49,SKUs!$C$6:$C$1997,0)),"") -> XG | I49: =IFERROR(INDEX(SKUs!#REF!,MATCH(B49,SKUs!$C$6:$C$1997,0)),"") | J49: =SUMIFS(SKUs!$I$6:$I$1997,SKUs!$C$6:$C$1997,B49) -> 8 | K49: =IFERROR(I49*J49,0) -> 0 | L49: =COUNTIF(SKUs!$C$6:$C$1997,B49) -> 1 | U49: =SUM(M49:R49) -> 0 | V49: =IF(B49="","",J49) -> 8
A50: 43 | B50: A.01.0774.003.P | C50: =IF(B50="","",IFERROR(IF(TRIM(MID(SUBSTITUTE(B50,".",REPT(" ",50)),51,50))="01","Masculino",IF(TRIM(MID(SUBSTITUTE(B50,".",REPT(" ",50)),51,50))="02","Feminino",IF(TRIM(MID(SUBSTITUTE(B50,".",REPT(" ",50)),51,50))="03","Outros","—"))),"—")) -> Masculino | D50: =IFERROR(INDEX(SKUs!$E$6:$E$1997,MATCH(B50,SKUs!$C$6:$C$1997,0)),"") -> CAMISETA | E50: =IFERROR(VLOOKUP(D50,Configurações!$N$5:$O$46,2,FALSE()),"OUTROS") -> VESTUÁRIO | F50: =IFERROR(INDEX(SKUs!$F$6:$F$1997,MATCH(B50,SKUs!$C$6:$C$1997,0)),"") -> CAMISETA COPA MASC. | G50: =IFERROR(INDEX(SKUs!$G$6:$G$1997,MATCH(B50,SKUs!$C$6:$C$1997,0)),"") -> BRANCA | H50: =IFERROR(INDEX(SKUs!$H$6:$H$1997,MATCH(B50,SKUs!$C$6:$C$1997,0)),"") -> P | I50: =IFERROR(INDEX(SKUs!#REF!,MATCH(B50,SKUs!$C$6:$C$1997,0)),"") | J50: =SUMIFS(SKUs!$I$6:$I$1997,SKUs!$C$6:$C$1997,B50) -> 0 | K50: =IFERROR(I50*J50,0) -> 0 | L50: =COUNTIF(SKUs!$C$6:$C$1997,B50) -> 2 | M50: 14 | U50: =SUM(M50:R50) -> 14 | V50: =IF(B50="","",J50) -> 0
A51: 44 | B51: A.01.0774.003.M | C51: =IF(B51="","",IFERROR(IF(TRIM(MID(SUBSTITUTE(B51,".",REPT(" ",50)),51,50))="01","Masculino",IF(TRIM(MID(SUBSTITUTE(B51,".",REPT(" ",50)),51,50))="02","Feminino",IF(TRIM(MID(SUBSTITUTE(B51,".",REPT(" ",50)),51,50))="03","Outros","—"))),"—")) -> Masculino | D51: =IFERROR(INDEX(SKUs!$E$6:$E$1997,MATCH(B51,SKUs!$C$6:$C$1997,0)),"") -> CAMISETA | E51: =IFERROR(VLOOKUP(D51,Configurações!$N$5:$O$46,2,FALSE()),"OUTROS") -> VESTUÁRIO | F51: =IFERROR(INDEX(SKUs!$F$6:$F$1997,MATCH(B51,SKUs!$C$6:$C$1997,0)),"") -> CAMISETA COPA MASC. | G51: =IFERROR(INDEX(SKUs!$G$6:$G$1997,MATCH(B51,SKUs!$C$6:$C$1997,0)),"") -> BRANCA | H51: =IFERROR(INDEX(SKUs!$H$6:$H$1997,MATCH(B51,SKUs!$C$6:$C$1997,0)),"") -> M | I51: =IFERROR(INDEX(SKUs!#REF!,MATCH(B51,SKUs!$C$6:$C$1997,0)),"") | J51: =SUMIFS(SKUs!$I$6:$I$1997,SKUs!$C$6:$C$1997,B51) -> 0 | K51: =IFERROR(I51*J51,0) -> 0 | L51: =COUNTIF(SKUs!$C$6:$C$1997,B51) -> 2 | M51: 15 | U51: =SUM(M51:R51) -> 15 | V51: =IF(B51="","",J51) -> 0
A52: 45 | B52: A.01.0774.003.G | C52: =IF(B52="","",IFERROR(IF(TRIM(MID(SUBSTITUTE(B52,".",REPT(" ",50)),51,50))="01","Masculino",IF(TRIM(MID(SUBSTITUTE(B52,".",REPT(" ",50)),51,50))="02","Feminino",IF(TRIM(MID(SUBSTITUTE(B52,".",REPT(" ",50)),51,50))="03","Outros","—"))),"—")) -> Masculino | D52: =IFERROR(INDEX(SKUs!$E$6:$E$1997,MATCH(B52,SKUs!$C$6:$C$1997,0)),"") -> CAMISETA | E52: =IFERROR(VLOOKUP(D52,Configurações!$N$5:$O$46,2,FALSE()),"OUTROS") -> VESTUÁRIO | F52: =IFERROR(INDEX(SKUs!$F$6:$F$1997,MATCH(B52,SKUs!$C$6:$C$1997,0)),"") -> CAMISETA COPA MASC. | G52: =IFERROR(INDEX(SKUs!$G$6:$G$1997,MATCH(B52,SKUs!$C$6:$C$1997,0)),"") -> BRANCA | H52: =IFERROR(INDEX(SKUs!$H$6:$H$1997,MATCH(B52,SKUs!$C$6:$C$1997,0)),"") -> G | I52: =IFERROR(INDEX(SKUs!#REF!,MATCH(B52,SKUs!$C$6:$C$1997,0)),"") | J52: =SUMIFS(SKUs!$I$6:$I$1997,SKUs!$C$6:$C$1997,B52) -> 0 | K52: =IFERROR(I52*J52,0) -> 0 | L52: =COUNTIF(SKUs!$C$6:$C$1997,B52) -> 2 | M52: 15 | U52: =SUM(M52:R52) -> 15 | V52: =IF(B52="","",J52) -> 0
A53: 46 | B53: A.01.0774.003.2G | C53: =IF(B53="","",IFERROR(IF(TRIM(MID(SUBSTITUTE(B53,".",REPT(" ",50)),51,50))="01","Masculino",IF(TRIM(MID(SUBSTITUTE(B53,".",REPT(" ",50)),51,50))="02","Feminino",IF(TRIM(MID(SUBSTITUTE(B53,".",REPT(" ",50)),51,50))="03","Outros","—"))),"—")) -> Masculino | D53: =IFERROR(INDEX(SKUs!$E$6:$E$1997,MATCH(B53,SKUs!$C$6:$C$1997,0)),"") -> CAMISETA | E53: =IFERROR(VLOOKUP(D53,Configurações!$N$5:$O$46,2,FALSE()),"OUTROS") -> VESTUÁRIO | F53: =IFERROR(INDEX(SKUs!$F$6:$F$1997,MATCH(B53,SKUs!$C$6:$C$1997,0)),"") -> CAMISETA COPA MASC. | G53: =IFERROR(INDEX(SKUs!$G$6:$G$1997,MATCH(B53,SKUs!$C$6:$C$1997,0)),"") -> BRANCA | H53: =IFERROR(INDEX(SKUs!$H$6:$H$1997,MATCH(B53,SKUs!$C$6:$C$1997,0)),"") -> GG | I53: =IFERROR(INDEX(SKUs!#REF!,MATCH(B53,SKUs!$C$6:$C$1997,0)),"") | J53: =SUMIFS(SKUs!$I$6:$I$1997,SKUs!$C$6:$C$1997,B53) -> 0 | K53: =IFERROR(I53*J53,0) -> 0 | L53: =COUNTIF(SKUs!$C$6:$C$1997,B53) -> 2 | M53: 15 | U53: =SUM(M53:R53) -> 15 | V53: =IF(B53="","",J53) -> 0
A54: 47 | B54: A.01.0774.003.3G | C54: =IF(B54="","",IFERROR(IF(TRIM(MID(SUBSTITUTE(B54,".",REPT(" ",50)),51,50))="01","Masculino",IF(TRIM(MID(SUBSTITUTE(B54,".",REPT(" ",50)),51,50))="02","Feminino",IF(TRIM(MID(SUBSTITUTE(B54,".",REPT(" ",50)),51,50))="03","Outros","—"))),"—")) -> Masculino | D54: =IFERROR(INDEX(SKUs!$E$6:$E$1997,MATCH(B54,SKUs!$C$6:$C$1997,0)),"") -> CAMISETA | E54: =IFERROR(VLOOKUP(D54,Configurações!$N$5:$O$46,2,FALSE()),"OUTROS") -> VESTUÁRIO | F54: =IFERROR(INDEX(SKUs!$F$6:$F$1997,MATCH(B54,SKUs!$C$6:$C$1997,0)),"") -> CAMISETA COPA MASC. | G54: =IFERROR(INDEX(SKUs!$G$6:$G$1997,MATCH(B54,SKUs!$C$6:$C$1997,0)),"") -> BRANCA | H54: =IFERROR(INDEX(SKUs!$H$6:$H$1997,MATCH(B54,SKUs!$C$6:$C$1997,0)),"") -> XG | I54: =IFERROR(INDEX(SKUs!#REF!,MATCH(B54,SKUs!$C$6:$C$1997,0)),"") | J54: =SUMIFS(SKUs!$I$6:$I$1997,SKUs!$C$6:$C$1997,B54) -> 0 | K54: =IFERROR(I54*J54,0) -> 0 | L54: =COUNTIF(SKUs!$C$6:$C$1997,B54) -> 2 | M54: 12 | U54: =SUM(M54:R54) -> 12 | V54: =IF(B54="","",J54) -> 0
A55: 48 | B55: A.01.0774.003.4G | C55: =IF(B55="","",IFERROR(IF(TRIM(MID(SUBSTITUTE(B55,".",REPT(" ",50)),51,50))="01","Masculino",IF(TRIM(MID(SUBSTITUTE(B55,".",REPT(" ",50)),51,50))="02","Feminino",IF(TRIM(MID(SUBSTITUTE(B55,".",REPT(" ",50)),51,50))="03","Outros","—"))),"—")) -> Masculino | D55: =IFERROR(INDEX(SKUs!$E$6:$E$1997,MATCH(B55,SKUs!$C$6:$C$1997,0)),"") -> CAMISETA | E55: =IFERROR(VLOOKUP(D55,Configurações!$N$5:$O$46,2,FALSE()),"OUTROS") -> VESTUÁRIO | F55: =IFERROR(INDEX(SKUs!$F$6:$F$1997,MATCH(B55,SKUs!$C$6:$C$1997,0)),"") -> CAMISETA COPA MASC. | G55: =IFERROR(INDEX(SKUs!$G$6:$G$1997,MATCH(B55,SKUs!$C$6:$C$1997,0)),"") -> BRANCA | H55: =IFERROR(INDEX(SKUs!$H$6:$H$1997,MATCH(B55,SKUs!$C$6:$C$1997,0)),"") -> 4G | I55: =IFERROR(INDEX(SKUs!#REF!,MATCH(B55,SKUs!$C$6:$C$1997,0)),"") | J55: =SUMIFS(SKUs!$I$6:$I$1997,SKUs!$C$6:$C$1997,B55) -> 0 | K55: =IFERROR(I55*J55,0) -> 0 | L55: =COUNTIF(SKUs!$C$6:$C$1997,B55) -> 2 | M55: 5 | U55: =SUM(M55:R55) -> 5 | V55: =IF(B55="","",J55) -> 0
A56: 49 | B56: A.01.0709.004.PP | C56: =IF(B56="","",IFERROR(IF(TRIM(MID(SUBSTITUTE(B56,".",REPT(" ",50)),51,50))="01","Masculino",IF(TRIM(MID(SUBSTITUTE(B56,".",REPT(" ",50)),51,50))="02","Feminino",IF(TRIM(MID(SUBSTITUTE(B56,".",REPT(" ",50)),51,50))="03","Outros","—"))),"—")) -> Masculino | D56: =IFERROR(INDEX(SKUs!$E$6:$E$1997,MATCH(B56,SKUs!$C$6:$C$1997,0)),"") -> POLO | E56: =IFERROR(VLOOKUP(D56,Configurações!$N$5:$O$46,2,FALSE()),"OUTROS") -> VESTUÁRIO | F56: =IFERROR(INDEX(SKUs!$F$6:$F$1997,MATCH(B56,SKUs!$C$6:$C$1997,0)),"") -> POLO PIQUET MASC. | G56: =IFERROR(INDEX(SKUs!$G$6:$G$1997,MATCH(B56,SKUs!$C$6:$C$1997,0)),"") -> CINZA | H56: =IFERROR(INDEX(SKUs!$H$6:$H$1997,MATCH(B56,SKUs!$C$6:$C$1997,0)),"") -> PP | I56: =IFERROR(INDEX(SKUs!#REF!,MATCH(B56,SKUs!$C$6:$C$1997,0)),"") | J56: =SUMIFS(SKUs!$I$6:$I$1997,SKUs!$C$6:$C$1997,B56) -> 0 | K56: =IFERROR(I56*J56,0) -> 0 | L56: =COUNTIF(SKUs!$C$6:$C$1997,B56) -> 3 | M56: 27 | U56: =SUM(M56:R56) -> 27 | V56: =IF(B56="","",J56) -> 0
A57: 50 | B57: A.01.0709.004.P | C57: =IF(B57="","",IFERROR(IF(TRIM(MID(SUBSTITUTE(B57,".",REPT(" ",50)),51,50))="01","Masculino",IF(TRIM(MID(SUBSTITUTE(B57,".",REPT(" ",50)),51,50))="02","Feminino",IF(TRIM(MID(SUBSTITUTE(B57,".",REPT(" ",50)),51,50))="03","Outros","—"))),"—")) -> Masculino | D57: =IFERROR(INDEX(SKUs!$E$6:$E$1997,MATCH(B57,SKUs!$C$6:$C$1997,0)),"") -> POLO | E57: =IFERROR(VLOOKUP(D57,Configurações!$N$5:$O$46,2,FALSE()),"OUTROS") -> VESTUÁRIO | F57: =IFERROR(INDEX(SKUs!$F$6:$F$1997,MATCH(B57,SKUs!$C$6:$C$1997,0)),"") -> POLO PIQUET MASC. | G57: =IFERROR(INDEX(SKUs!$G$6:$G$1997,MATCH(B57,SKUs!$C$6:$C$1997,0)),"") -> CINZA | H57: =IFERROR(INDEX(SKUs!$H$6:$H$1997,MATCH(B57,SKUs!$C$6:$C$1997,0)),"") -> P | I57: =IFERROR(INDEX(SKUs!#REF!,MATCH(B57,SKUs!$C$6:$C$1997,0)),"") | J57: =SUMIFS(SKUs!$I$6:$I$1997,SKUs!$C$6:$C$1997,B57) -> 56 | K57: =IFERROR(I57*J57,0) -> 0 | L57: =COUNTIF(SKUs!$C$6:$C$1997,B57) -> 2 | U57: =SUM(M57:R57) -> 0 | V57: =IF(B57="","",J57) -> 56
A58: 51 | B58: A.01.0709.004.M | C58: =IF(B58="","",IFERROR(IF(TRIM(MID(SUBSTITUTE(B58,".",REPT(" ",50)),51,50))="01","Masculino",IF(TRIM(MID(SUBSTITUTE(B58,".",REPT(" ",50)),51,50))="02","Feminino",IF(TRIM(MID(SUBSTITUTE(B58,".",REPT(" ",50)),51,50))="03","Outros","—"))),"—")) -> Masculino | D58: =IFERROR(INDEX(SKUs!$E$6:$E$1997,MATCH(B58,SKUs!$C$6:$C$1997,0)),"") -> POLO | E58: =IFERROR(VLOOKUP(D58,Configurações!$N$5:$O$46,2,FALSE()),"OUTROS") -> VESTUÁRIO | F58: =IFERROR(INDEX(SKUs!$F$6:$F$1997,MATCH(B58,SKUs!$C$6:$C$1997,0)),"") -> POLO PIQUET MASC. | G58: =IFERROR(INDEX(SKUs!$G$6:$G$1997,MATCH(B58,SKUs!$C$6:$C$1997,0)),"") -> CINZA | H58: =IFERROR(INDEX(SKUs!$H$6:$H$1997,MATCH(B58,SKUs!$C$6:$C$1997,0)),"") -> M | I58: =IFERROR(INDEX(SKUs!#REF!,MATCH(B58,SKUs!$C$6:$C$1997,0)),"") | J58: =SUMIFS(SKUs!$I$6:$I$1997,SKUs!$C$6:$C$1997,B58) -> 130 | K58: =IFERROR(I58*J58,0) -> 0 | L58: =COUNTIF(SKUs!$C$6:$C$1997,B58) -> 3 | U58: =SUM(M58:R58) -> 0 | V58: =IF(B58="","",J58) -> 130
A59: 52 | B59: A.01.0709.004.G | C59: =IF(B59="","",IFERROR(IF(TRIM(MID(SUBSTITUTE(B59,".",REPT(" ",50)),51,50))="01","Masculino",IF(TRIM(MID(SUBSTITUTE(B59,".",REPT(" ",50)),51,50))="02","Feminino",IF(TRIM(MID(SUBSTITUTE(B59,".",REPT(" ",50)),51,50))="03","Outros","—"))),"—")) -> Masculino | D59: =IFERROR(INDEX(SKUs!$E$6:$E$1997,MATCH(B59,SKUs!$C$6:$C$1997,0)),"") -> POLO | E59: =IFERROR(VLOOKUP(D59,Configurações!$N$5:$O$46,2,FALSE()),"OUTROS") -> VESTUÁRIO | F59: =IFERROR(INDEX(SKUs!$F$6:$F$1997,MATCH(B59,SKUs!$C$6:$C$1997,0)),"") -> POLO PIQUET MASC. | G59: =IFERROR(INDEX(SKUs!$G$6:$G$1997,MATCH(B59,SKUs!$C$6:$C$1997,0)),"") -> CINZA | H59: =IFERROR(INDEX(SKUs!$H$6:$H$1997,MATCH(B59,SKUs!$C$6:$C$1997,0)),"") -> G | I59: =IFERROR(INDEX(SKUs!#REF!,MATCH(B59,SKUs!$C$6:$C$1997,0)),"") | J59: =SUMIFS(SKUs!$I$6:$I$1997,SKUs!$C$6:$C$1997,B59) -> 79 | K59: =IFERROR(I59*J59,0) -> 0 | L59: =COUNTIF(SKUs!$C$6:$C$1997,B59) -> 3 | U59: =SUM(M59:R59) -> 0 | V59: =IF(B59="","",J59) -> 79
A60: 53 | B60: A.01.0709.004.GG | C60: =IF(B60="","",IFERROR(IF(TRIM(MID(SUBSTITUTE(B60,".",REPT(" ",50)),51,50))="01","Masculino",IF(TRIM(MID(SUBSTITUTE(B60,".",REPT(" ",50)),51,50))="02","Feminino",IF(TRIM(MID(SUBSTITUTE(B60,".",REPT(" ",50)),51,50))="03","Outros","—"))),"—")) -> Masculino | D60: =IFERROR(INDEX(SKUs!$E$6:$E$1997,MATCH(B60,SKUs!$C$6:$C$1997,0)),"") -> POLO | E60: =IFERROR(VLOOKUP(D60,Configurações!$N$5:$O$46,2,FALSE()),"OUTROS") -> VESTUÁRIO | F60: =IFERROR(INDEX(SKUs!$F$6:$F$1997,MATCH(B60,SKUs!$C$6:$C$1997,0)),"") -> POLO PIQUET MASC. | G60: =IFERROR(INDEX(SKUs!$G$6:$G$1997,MATCH(B60,SKUs!$C$6:$C$1997,0)),"") -> CINZA | H60: =IFERROR(INDEX(SKUs!$H$6:$H$1997,MATCH(B60,SKUs!$C$6:$C$1997,0)),"") -> GG | I60: =IFERROR(INDEX(SKUs!#REF!,MATCH(B60,SKUs!$C$6:$C$1997,0)),"") | J60: =SUMIFS(SKUs!$I$6:$I$1997,SKUs!$C$6:$C$1997,B60) -> 0 | K60: =IFERROR(I60*J60,0) -> 0 | L60: =COUNTIF(SKUs!$C$6:$C$1997,B60) -> 2 | M60: 25 | U60: =SUM(M60:R60) -> 25 | V60: =IF(B60="","",J60) -> 0
A61: 54 | B61: A.01.0709.004.XG | C61: =IF(B61="","",IFERROR(IF(TRIM(MID(SUBSTITUTE(B61,".",REPT(" ",50)),51,50))="01","Masculino",IF(TRIM(MID(SUBSTITUTE(B61,".",REPT(" ",50)),51,50))="02","Feminino",IF(TRIM(MID(SUBSTITUTE(B61,".",REPT(" ",50)),51,50))="03","Outros","—"))),"—")) -> Masculino | D61: =IFERROR(INDEX(SKUs!$E$6:$E$1997,MATCH(B61,SKUs!$C$6:$C$1997,0)),"") -> POLO | E61: =IFERROR(VLOOKUP(D61,Configurações!$N$5:$O$46,2,FALSE()),"OUTROS") -> VESTUÁRIO | F61: =IFERROR(INDEX(SKUs!$F$6:$F$1997,MATCH(B61,SKUs!$C$6:$C$1997,0)),"") -> POLO PIQUET MASC. | G61: =IFERROR(INDEX(SKUs!$G$6:$G$1997,MATCH(B61,SKUs!$C$6:$C$1997,0)),"") -> CINZA | H61: =IFERROR(INDEX(SKUs!$H$6:$H$1997,MATCH(B61,SKUs!$C$6:$C$1997,0)),"") -> XG | I61: =IFERROR(INDEX(SKUs!#REF!,MATCH(B61,SKUs!$C$6:$C$1997,0)),"") | J61: =SUMIFS(SKUs!$I$6:$I$1997,SKUs!$C$6:$C$1997,B61) -> 0 | K61: =IFERROR(I61*J61,0) -> 0 | L61: =COUNTIF(SKUs!$C$6:$C$1997,B61) -> 1 | M61: 8 | U61: =SUM(M61:R61) -> 8 | V61: =IF(B61="","",J61) -> 0
A62: 55 | B62: A.01.0703.002.PP | C62: =IF(B62="","",IFERROR(IF(TRIM(MID(SUBSTITUTE(B62,".",REPT(" ",50)),51,50))="01","Masculino",IF(TRIM(MID(SUBSTITUTE(B62,".",REPT(" ",50)),51,50))="02","Feminino",IF(TRIM(MID(SUBSTITUTE(B62,".",REPT(" ",50)),51,50))="03","Outros","—"))),"—")) -> Masculino | D62: =IFERROR(INDEX(SKUs!$E$6:$E$1997,MATCH(B62,SKUs!$C$6:$C$1997,0)),"") -> POLO | E62: =IFERROR(VLOOKUP(D62,Configurações!$N$5:$O$46,2,FALSE()),"OUTROS") -> VESTUÁRIO | F62: =IFERROR(INDEX(SKUs!$F$6:$F$1997,MATCH(B62,SKUs!$C$6:$C$1997,0)),"") -> POLO PIQUET MASC. | G62: =IFERROR(INDEX(SKUs!$G$6:$G$1997,MATCH(B62,SKUs!$C$6:$C$1997,0)),"") -> MARINHO-RISCOS | H62: =IFERROR(INDEX(SKUs!$H$6:$H$1997,MATCH(B62,SKUs!$C$6:$C$1997,0)),"") -> PP | I62: =IFERROR(INDEX(SKUs!#REF!,MATCH(B62,SKUs!$C$6:$C$1997,0)),"") | J62: =SUMIFS(SKUs!$I$6:$I$1997,SKUs!$C$6:$C$1997,B62) -> 0 | K62: =IFERROR(I62*J62,0) -> 0 | L62: =COUNTIF(SKUs!$C$6:$C$1997,B62) -> 1 | M62: 5 | U62: =SUM(M62:R62) -> 5 | V62: =IF(B62="","",J62) -> 0
A63: 56 | B63: A.01.0703.002.P | C63: =IF(B63="","",IFERROR(IF(TRIM(MID(SUBSTITUTE(B63,".",REPT(" ",50)),51,50))="01","Masculino",IF(TRIM(MID(SUBSTITUTE(B63,".",REPT(" ",50)),51,50))="02","Feminino",IF(TRIM(MID(SUBSTITUTE(B63,".",REPT(" ",50)),51,50))="03","Outros","—"))),"—")) -> Masculino | D63: =IFERROR(INDEX(SKUs!$E$6:$E$1997,MATCH(B63,SKUs!$C$6:$C$1997,0)),"") -> POLO | E63: =IFERROR(VLOOKUP(D63,Configurações!$N$5:$O$46,2,FALSE()),"OUTROS") -> VESTUÁRIO | F63: =IFERROR(INDEX(SKUs!$F$6:$F$1997,MATCH(B63,SKUs!$C$6:$C$1997,0)),"") -> POLO PIQUET MASC. | G63: =IFERROR(INDEX(SKUs!$G$6:$G$1997,MATCH(B63,SKUs!$C$6:$C$1997,0)),"") -> MARINHO-RISCOS | H63: =IFERROR(INDEX(SKUs!$H$6:$H$1997,MATCH(B63,SKUs!$C$6:$C$1997,0)),"") -> P | I63: =IFERROR(INDEX(SKUs!#REF!,MATCH(B63,SKUs!$C$6:$C$1997,0)),"") | J63: =SUMIFS(SKUs!$I$6:$I$1997,SKUs!$C$6:$C$1997,B63) -> 67 | K63: =IFERROR(I63*J63,0) -> 0 | L63: =COUNTIF(SKUs!$C$6:$C$1997,B63) -> 2 | U63: =SUM(M63:R63) -> 0 | V63: =IF(B63="","",J63) -> 67
A64: 57 | B64: A.01.0703.002.M | C64: =IF(B64="","",IFERROR(IF(TRIM(MID(SUBSTITUTE(B64,".",REPT(" ",50)),51,50))="01","Masculino",IF(TRIM(MID(SUBSTITUTE(B64,".",REPT(" ",50)),51,50))="02","Feminino",IF(TRIM(MID(SUBSTITUTE(B64,".",REPT(" ",50)),51,50))="03","Outros","—"))),"—")) -> Masculino | D64: =IFERROR(INDEX(SKUs!$E$6:$E$1997,MATCH(B64,SKUs!$C$6:$C$1997,0)),"") -> POLO | E64: =IFERROR(VLOOKUP(D64,Configurações!$N$5:$O$46,2,FALSE()),"OUTROS") -> VESTUÁRIO | F64: =IFERROR(INDEX(SKUs!$F$6:$F$1997,MATCH(B64,SKUs!$C$6:$C$1997,0)),"") -> POLO PIQUET MASC. | G64: =IFERROR(INDEX(SKUs!$G$6:$G$1997,MATCH(B64,SKUs!$C$6:$C$1997,0)),"") -> MARINHO-RISCOS | H64: =IFERROR(INDEX(SKUs!$H$6:$H$1997,MATCH(B64,SKUs!$C$6:$C$1997,0)),"") -> M | I64: =IFERROR(INDEX(SKUs!#REF!,MATCH(B64,SKUs!$C$6:$C$1997,0)),"") | J64: =SUMIFS(SKUs!$I$6:$I$1997,SKUs!$C$6:$C$1997,B64) -> 208 | K64: =IFERROR(I64*J64,0) -> 0 | L64: =COUNTIF(SKUs!$C$6:$C$1997,B64) -> 5 | U64: =SUM(M64:R64) -> 0 | V64: =IF(B64="","",J64) -> 208
A65: 58 | B65: A.01.0703.002.G | C65: =IF(B65="","",IFERROR(IF(TRIM(MID(SUBSTITUTE(B65,".",REPT(" ",50)),51,50))="01","Masculino",IF(TRIM(MID(SUBSTITUTE(B65,".",REPT(" ",50)),51,50))="02","Feminino",IF(TRIM(MID(SUBSTITUTE(B65,".",REPT(" ",50)),51,50))="03","Outros","—"))),"—")) -> Masculino | D65: =IFERROR(INDEX(SKUs!$E$6:$E$1997,MATCH(B65,SKUs!$C$6:$C$1997,0)),"") -> POLO | E65: =IFERROR(VLOOKUP(D65,Configurações!$N$5:$O$46,2,FALSE()),"OUTROS") -> VESTUÁRIO | F65: =IFERROR(INDEX(SKUs!$F$6:$F$1997,MATCH(B65,SKUs!$C$6:$C$1997,0)),"") -> POLO PIQUET MASC. | G65: =IFERROR(INDEX(SKUs!$G$6:$G$1997,MATCH(B65,SKUs!$C$6:$C$1997,0)),"") -> MARINHO-RISCOS | H65: =IFERROR(INDEX(SKUs!$H$6:$H$1997,MATCH(B65,SKUs!$C$6:$C$1997,0)),"") -> G | I65: =IFERROR(INDEX(SKUs!#REF!,MATCH(B65,SKUs!$C$6:$C$1997,0)),"") | J65: =SUMIFS(SKUs!$I$6:$I$1997,SKUs!$C$6:$C$1997,B65) -> 51 | K65: =IFERROR(I65*J65,0) -> 0 | L65: =COUNTIF(SKUs!$C$6:$C$1997,B65) -> 3 | U65: =SUM(M65:R65) -> 0 | V65: =IF(B65="","",J65) -> 51
A66: 59 | B66: A.01.0703.002.GG | C66: =IF(B66="","",IFERROR(IF(TRIM(MID(SUBSTITUTE(B66,".",REPT(" ",50)),51,50))="01","Masculino",IF(TRIM(MID(SUBSTITUTE(B66,".",REPT(" ",50)),51,50))="02","Feminino",IF(TRIM(MID(SUBSTITUTE(B66,".",REPT(" ",50)),51,50))="03","Outros","—"))),"—")) -> Masculino | D66: =IFERROR(INDEX(SKUs!$E$6:$E$1997,MATCH(B66,SKUs!$C$6:$C$1997,0)),"") -> POLO | E66: =IFERROR(VLOOKUP(D66,Configurações!$N$5:$O$46,2,FALSE()),"OUTROS") -> VESTUÁRIO | F66: =IFERROR(INDEX(SKUs!$F$6:$F$1997,MATCH(B66,SKUs!$C$6:$C$1997,0)),"") -> POLO PIQUET MASC. | G66: =IFERROR(INDEX(SKUs!$G$6:$G$1997,MATCH(B66,SKUs!$C$6:$C$1997,0)),"") -> MARINHO-RISCOS | H66: =IFERROR(INDEX(SKUs!$H$6:$H$1997,MATCH(B66,SKUs!$C$6:$C$1997,0)),"") -> GG | I66: =IFERROR(INDEX(SKUs!#REF!,MATCH(B66,SKUs!$C$6:$C$1997,0)),"") | J66: =SUMIFS(SKUs!$I$6:$I$1997,SKUs!$C$6:$C$1997,B66) -> 0 | K66: =IFERROR(I66*J66,0) -> 0 | L66: =COUNTIF(SKUs!$C$6:$C$1997,B66) -> 3 | M66: 29 | U66: =SUM(M66:R66) -> 29 | V66: =IF(B66="","",J66) -> 0
A67: 60 | B67: A.01.0703.002.XG | C67: =IF(B67="","",IFERROR(IF(TRIM(MID(SUBSTITUTE(B67,".",REPT(" ",50)),51,50))="01","Masculino",IF(TRIM(MID(SUBSTITUTE(B67,".",REPT(" ",50)),51,50))="02","Feminino",IF(TRIM(MID(SUBSTITUTE(B67,".",REPT(" ",50)),51,50))="03","Outros","—"))),"—")) -> Masculino | D67: =IFERROR(INDEX(SKUs!$E$6:$E$1997,MATCH(B67,SKUs!$C$6:$C$1997,0)),"") -> POLO | E67: =IFERROR(VLOOKUP(D67,Configurações!$N$5:$O$46,2,FALSE()),"OUTROS") -> VESTUÁRIO | F67: =IFERROR(INDEX(SKUs!$F$6:$F$1997,MATCH(B67,SKUs!$C$6:$C$1997,0)),"") -> POLO PIQUET MASC. | G67: =IFERROR(INDEX(SKUs!$G$6:$G$1997,MATCH(B67,SKUs!$C$6:$C$1997,0)),"") -> MARINHO-RISCOS | H67: =IFERROR(INDEX(SKUs!$H$6:$H$1997,MATCH(B67,SKUs!$C$6:$C$1997,0)),"") -> XG | I67: =IFERROR(INDEX(SKUs!#REF!,MATCH(B67,SKUs!$C$6:$C$1997,0)),"") | J67: =SUMIFS(SKUs!$I$6:$I$1997,SKUs!$C$6:$C$1997,B67) -> 0 | K67: =IFERROR(I67*J67,0) -> 0 | L67: =COUNTIF(SKUs!$C$6:$C$1997,B67) -> 2 | M67: 35 | U67: =SUM(M67:R67) -> 35 | V67: =IF(B67="","",J67) -> 0
A68: 61 | B68: A.01.0711.004.PP | C68: =IF(B68="","",IFERROR(IF(TRIM(MID(SUBSTITUTE(B68,".",REPT(" ",50)),51,50))="01","Masculino",IF(TRIM(MID(SUBSTITUTE(B68,".",REPT(" ",50)),51,50))="02","Feminino",IF(TRIM(MID(SUBSTITUTE(B68,".",REPT(" ",50)),51,50))="03","Outros","—"))),"—")) -> Masculino | D68: =IFERROR(INDEX(SKUs!$E$6:$E$1997,MATCH(B68,SKUs!$C$6:$C$1997,0)),"") -> POLO | E68: =IFERROR(VLOOKUP(D68,Configurações!$N$5:$O$46,2,FALSE()),"OUTROS") -> VESTUÁRIO | F68: =IFERROR(INDEX(SKUs!$F$6:$F$1997,MATCH(B68,SKUs!$C$6:$C$1997,0)),"") -> POLO PIQUET MASC. | G68: =IFERROR(INDEX(SKUs!$G$6:$G$1997,MATCH(B68,SKUs!$C$6:$C$1997,0)),"") -> BRANCA | H68: =IFERROR(INDEX(SKUs!$H$6:$H$1997,MATCH(B68,SKUs!$C$6:$C$1997,0)),"") -> PP | I68: =IFERROR(INDEX(SKUs!#REF!,MATCH(B68,SKUs!$C$6:$C$1997,0)),"") | J68: =SUMIFS(SKUs!$I$6:$I$1997,SKUs!$C$6:$C$1997,B68) -> 0 | K68: =IFERROR(I68*J68,0) -> 0 | L68: =COUNTIF(SKUs!$C$6:$C$1997,B68) -> 1 | M68: 5 | U68: =SUM(M68:R68) -> 5 | V68: =IF(B68="","",J68) -> 0
A69: 62 | B69: A.01.0711.004.P | C69: =IF(B69="","",IFERROR(IF(TRIM(MID(SUBSTITUTE(B69,".",REPT(" ",50)),51,50))="01","Masculino",IF(TRIM(MID(SUBSTITUTE(B69,".",REPT(" ",50)),51,50))="02","Feminino",IF(TRIM(MID(SUBSTITUTE(B69,".",REPT(" ",50)),51,50))="03","Outros","—"))),"—")) -> Masculino | D69: =IFERROR(INDEX(SKUs!$E$6:$E$1997,MATCH(B69,SKUs!$C$6:$C$1997,0)),"") -> POLO | E69: =IFERROR(VLOOKUP(D69,Configurações!$N$5:$O$46,2,FALSE()),"OUTROS") -> VESTUÁRIO | F69: =IFERROR(INDEX(SKUs!$F$6:$F$1997,MATCH(B69,SKUs!$C$6:$C$1997,0)),"") -> POLO PIQUET MASC. | G69: =IFERROR(INDEX(SKUs!$G$6:$G$1997,MATCH(B69,SKUs!$C$6:$C$1997,0)),"") -> BRANCA | H69: =IFERROR(INDEX(SKUs!$H$6:$H$1997,MATCH(B69,SKUs!$C$6:$C$1997,0)),"") -> P | I69: =IFERROR(INDEX(SKUs!#REF!,MATCH(B69,SKUs!$C$6:$C$1997,0)),"") | J69: =SUMIFS(SKUs!$I$6:$I$1997,SKUs!$C$6:$C$1997,B69) -> 0 | K69: =IFERROR(I69*J69,0) -> 0 | L69: =COUNTIF(SKUs!$C$6:$C$1997,B69) -> 1 | M69: 10 | U69: =SUM(M69:R69) -> 10 | V69: =IF(B69="","",J69) -> 0
A70: 63 | B70: A.01.0711.004.M | C70: =IF(B70="","",IFERROR(IF(TRIM(MID(SUBSTITUTE(B70,".",REPT(" ",50)),51,50))="01","Masculino",IF(TRIM(MID(SUBSTITUTE(B70,".",REPT(" ",50)),51,50))="02","Feminino",IF(TRIM(MID(SUBSTITUTE(B70,".",REPT(" ",50)),51,50))="03","Outros","—"))),"—")) -> Masculino | D70: =IFERROR(INDEX(SKUs!$E$6:$E$1997,MATCH(B70,SKUs!$C$6:$C$1997,0)),"") -> POLO | E70: =IFERROR(VLOOKUP(D70,Configurações!$N$5:$O$46,2,FALSE()),"OUTROS") -> VESTUÁRIO | F70: =IFERROR(INDEX(SKUs!$F$6:$F$1997,MATCH(B70,SKUs!$C$6:$C$1997,0)),"") -> POLO PIQUET MASC. | G70: =IFERROR(INDEX(SKUs!$G$6:$G$1997,MATCH(B70,SKUs!$C$6:$C$1997,0)),"") -> BRANCA | H70: =IFERROR(INDEX(SKUs!$H$6:$H$1997,MATCH(B70,SKUs!$C$6:$C$1997,0)),"") -> M | I70: =IFERROR(INDEX(SKUs!#REF!,MATCH(B70,SKUs!$C$6:$C$1997,0)),"") | J70: =SUMIFS(SKUs!$I$6:$I$1997,SKUs!$C$6:$C$1997,B70) -> 0 | K70: =IFERROR(I70*J70,0) -> 0 | L70: =COUNTIF(SKUs!$C$6:$C$1997,B70) -> 1 | M70: 28 | U70: =SUM(M70:R70) -> 28 | V70: =IF(B70="","",J70) -> 0
A71: 64 | B71: A.01.0711.004.G | C71: =IF(B71="","",IFERROR(IF(TRIM(MID(SUBSTITUTE(B71,".",REPT(" ",50)),51,50))="01","Masculino",IF(TRIM(MID(SUBSTITUTE(B71,".",REPT(" ",50)),51,50))="02","Feminino",IF(TRIM(MID(SUBSTITUTE(B71,".",REPT(" ",50)),51,50))="03","Outros","—"))),"—")) -> Masculino | D71: =IFERROR(INDEX(SKUs!$E$6:$E$1997,MATCH(B71,SKUs!$C$6:$C$1997,0)),"") -> POLO | E71: =IFERROR(VLOOKUP(D71,Configurações!$N$5:$O$46,2,FALSE()),"OUTROS") -> VESTUÁRIO | F71: =IFERROR(INDEX(SKUs!$F$6:$F$1997,MATCH(B71,SKUs!$C$6:$C$1997,0)),"") -> POLO PIQUET MASC. | G71: =IFERROR(INDEX(SKUs!$G$6:$G$1997,MATCH(B71,SKUs!$C$6:$C$1997,0)),"") -> BRANCA | H71: =IFERROR(INDEX(SKUs!$H$6:$H$1997,MATCH(B71,SKUs!$C$6:$C$1997,0)),"") -> G | I71: =IFERROR(INDEX(SKUs!#REF!,MATCH(B71,SKUs!$C$6:$C$1997,0)),"") | J71: =SUMIFS(SKUs!$I$6:$I$1997,SKUs!$C$6:$C$1997,B71) -> 0 | K71: =IFERROR(I71*J71,0) -> 0 | L71: =COUNTIF(SKUs!$C$6:$C$1997,B71) -> 1 | M71: 15 | U71: =SUM(M71:R71) -> 15 | V71: =IF(B71="","",J71) -> 0
A72: 65 | B72: A.01.0711.004.GG | C72: =IF(B72="","",IFERROR(IF(TRIM(MID(SUBSTITUTE(B72,".",REPT(" ",50)),51,50))="01","Masculino",IF(TRIM(MID(SUBSTITUTE(B72,".",REPT(" ",50)),51,50))="02","Feminino",IF(TRIM(MID(SUBSTITUTE(B72,".",REPT(" ",50)),51,50))="03","Outros","—"))),"—")) -> Masculino | D72: =IFERROR(INDEX(SKUs!$E$6:$E$1997,MATCH(B72,SKUs!$C$6:$C$1997,0)),"") -> POLO | E72: =IFERROR(VLOOKUP(D72,Configurações!$N$5:$O$46,2,FALSE()),"OUTROS") -> VESTUÁRIO | F72: =IFERROR(INDEX(SKUs!$F$6:$F$1997,MATCH(B72,SKUs!$C$6:$C$1997,0)),"") -> POLO PIQUET MASC. | G72: =IFERROR(INDEX(SKUs!$G$6:$G$1997,MATCH(B72,SKUs!$C$6:$C$1997,0)),"") -> BRANCA | H72: =IFERROR(INDEX(SKUs!$H$6:$H$1997,MATCH(B72,SKUs!$C$6:$C$1997,0)),"") -> GG | I72: =IFERROR(INDEX(SKUs!#REF!,MATCH(B72,SKUs!$C$6:$C$1997,0)),"") | J72: =SUMIFS(SKUs!$I$6:$I$1997,SKUs!$C$6:$C$1997,B72) -> 0 | K72: =IFERROR(I72*J72,0) -> 0 | L72: =COUNTIF(SKUs!$C$6:$C$1997,B72) -> 1 | M72: 10 | U72: =SUM(M72:R72) -> 10 | V72: =IF(B72="","",J72) -> 0
A73: 66 | B73: A.01.0711.004.XG | C73: =IF(B73="","",IFERROR(IF(TRIM(MID(SUBSTITUTE(B73,".",REPT(" ",50)),51,50))="01","Masculino",IF(TRIM(MID(SUBSTITUTE(B73,".",REPT(" ",50)),51,50))="02","Feminino",IF(TRIM(MID(SUBSTITUTE(B73,".",REPT(" ",50)),51,50))="03","Outros","—"))),"—")) -> Masculino | D73: =IFERROR(INDEX(SKUs!$E$6:$E$1997,MATCH(B73,SKUs!$C$6:$C$1997,0)),"") -> POLO | E73: =IFERROR(VLOOKUP(D73,Configurações!$N$5:$O$46,2,FALSE()),"OUTROS") -> VESTUÁRIO | F73: =IFERROR(INDEX(SKUs!$F$6:$F$1997,MATCH(B73,SKUs!$C$6:$C$1997,0)),"") -> POLO PIQUET MASC. | G73: =IFERROR(INDEX(SKUs!$G$6:$G$1997,MATCH(B73,SKUs!$C$6:$C$1997,0)),"") -> BRANCA | H73: =IFERROR(INDEX(SKUs!$H$6:$H$1997,MATCH(B73,SKUs!$C$6:$C$1997,0)),"") -> XG | I73: =IFERROR(INDEX(SKUs!#REF!,MATCH(B73,SKUs!$C$6:$C$1997,0)),"") | J73: =SUMIFS(SKUs!$I$6:$I$1997,SKUs!$C$6:$C$1997,B73) -> 0 | K73: =IFERROR(I73*J73,0) -> 0 | L73: =COUNTIF(SKUs!$C$6:$C$1997,B73) -> 1 | M73: 8 | U73: =SUM(M73:R73) -> 8 | V73: =IF(B73="","",J73) -> 0
A74: 67 | B74: A.01.0705.017.PP | C74: =IF(B74="","",IFERROR(IF(TRIM(MID(SUBSTITUTE(B74,".",REPT(" ",50)),51,50))="01","Masculino",IF(TRIM(MID(SUBSTITUTE(B74,".",REPT(" ",50)),51,50))="02","Feminino",IF(TRIM(MID(SUBSTITUTE(B74,".",REPT(" ",50)),51,50))="03","Outros","—"))),"—")) -> Masculino | D74: =IFERROR(INDEX(SKUs!$E$6:$E$1997,MATCH(B74,SKUs!$C$6:$C$1997,0)),"") -> POLO | E74: =IFERROR(VLOOKUP(D74,Configurações!$N$5:$O$46,2,FALSE()),"OUTROS") -> VESTUÁRIO | F74: =IFERROR(INDEX(SKUs!$F$6:$F$1997,MATCH(B74,SKUs!$C$6:$C$1997,0)),"") -> POLO PIQUET MASC. | G74: =IFERROR(INDEX(SKUs!$G$6:$G$1997,MATCH(B74,SKUs!$C$6:$C$1997,0)),"") -> INDIGO | H74: =IFERROR(INDEX(SKUs!$H$6:$H$1997,MATCH(B74,SKUs!$C$6:$C$1997,0)),"") -> PP | I74: =IFERROR(INDEX(SKUs!#REF!,MATCH(B74,SKUs!$C$6:$C$1997,0)),"") | J74: =SUMIFS(SKUs!$I$6:$I$1997,SKUs!$C$6:$C$1997,B74) -> 0 | K74: =IFERROR(I74*J74,0) -> 0 | L74: =COUNTIF(SKUs!$C$6:$C$1997,B74) -> 1 | M74: 5 | U74: =SUM(M74:R74) -> 5 | V74: =IF(B74="","",J74) -> 0
A75: 68 | B75: A.01.0705.017.P | C75: =IF(B75="","",IFERROR(IF(TRIM(MID(SUBSTITUTE(B75,".",REPT(" ",50)),51,50))="01","Masculino",IF(TRIM(MID(SUBSTITUTE(B75,".",REPT(" ",50)),51,50))="02","Feminino",IF(TRIM(MID(SUBSTITUTE(B75,".",REPT(" ",50)),51,50))="03","Outros","—"))),"—")) -> Masculino | D75: =IFERROR(INDEX(SKUs!$E$6:$E$1997,MATCH(B75,SKUs!$C$6:$C$1997,0)),"") -> POLO | E75: =IFERROR(VLOOKUP(D75,Configurações!$N$5:$O$46,2,FALSE()),"OUTROS") -> VESTUÁRIO | F75: =IFERROR(INDEX(SKUs!$F$6:$F$1997,MATCH(B75,SKUs!$C$6:$C$1997,0)),"") -> POLO PIQUET MASC. | G75: =IFERROR(INDEX(SKUs!$G$6:$G$1997,MATCH(B75,SKUs!$C$6:$C$1997,0)),"") -> INDIGO | H75: =IFERROR(INDEX(SKUs!$H$6:$H$1997,MATCH(B75,SKUs!$C$6:$C$1997,0)),"") -> P | I75: =IFERROR(INDEX(SKUs!#REF!,MATCH(B75,SKUs!$C$6:$C$1997,0)),"") | J75: =SUMIFS(SKUs!$I$6:$I$1997,SKUs!$C$6:$C$1997,B75) -> 0 | K75: =IFERROR(I75*J75,0) -> 0 | L75: =COUNTIF(SKUs!$C$6:$C$1997,B75) -> 2 | M75: 37 | U75: =SUM(M75:R75) -> 37 | V75: =IF(B75="","",J75) -> 0
A76: 69 | B76: A.01.0705.017.M | C76: =IF(B76="","",IFERROR(IF(TRIM(MID(SUBSTITUTE(B76,".",REPT(" ",50)),51,50))="01","Masculino",IF(TRIM(MID(SUBSTITUTE(B76,".",REPT(" ",50)),51,50))="02","Feminino",IF(TRIM(MID(SUBSTITUTE(B76,".",REPT(" ",50)),51,50))="03","Outros","—"))),"—")) -> Masculino | D76: =IFERROR(INDEX(SKUs!$E$6:$E$1997,MATCH(B76,SKUs!$C$6:$C$1997,0)),"") -> POLO | E76: =IFERROR(VLOOKUP(D76,Configurações!$N$5:$O$46,2,FALSE()),"OUTROS") -> VESTUÁRIO | F76: =IFERROR(INDEX(SKUs!$F$6:$F$1997,MATCH(B76,SKUs!$C$6:$C$1997,0)),"") -> POLO PIQUET MASC. | G76: =IFERROR(INDEX(SKUs!$G$6:$G$1997,MATCH(B76,SKUs!$C$6:$C$1997,0)),"") -> INDIGO | H76: =IFERROR(INDEX(SKUs!$H$6:$H$1997,MATCH(B76,SKUs!$C$6:$C$1997,0)),"") -> M | I76: =IFERROR(INDEX(SKUs!#REF!,MATCH(B76,SKUs!$C$6:$C$1997,0)),"") | J76: =SUMIFS(SKUs!$I$6:$I$1997,SKUs!$C$6:$C$1997,B76) -> 54 | K76: =IFERROR(I76*J76,0) -> 0 | L76: =COUNTIF(SKUs!$C$6:$C$1997,B76) -> 2 | U76: =SUM(M76:R76) -> 0 | V76: =IF(B76="","",J76) -> 54
A77: 70 | B77: A.01.0705.017.G | C77: =IF(B77="","",IFERROR(IF(TRIM(MID(SUBSTITUTE(B77,".",REPT(" ",50)),51,50))="01","Masculino",IF(TRIM(MID(SUBSTITUTE(B77,".",REPT(" ",50)),51,50))="02","Feminino",IF(TRIM(MID(SUBSTITUTE(B77,".",REPT(" ",50)),51,50))="03","Outros","—"))),"—")) -> Masculino | D77: =IFERROR(INDEX(SKUs!$E$6:$E$1997,MATCH(B77,SKUs!$C$6:$C$1997,0)),"") -> POLO | E77: =IFERROR(VLOOKUP(D77,Configurações!$N$5:$O$46,2,FALSE()),"OUTROS") -> VESTUÁRIO | F77: =IFERROR(INDEX(SKUs!$F$6:$F$1997,MATCH(B77,SKUs!$C$6:$C$1997,0)),"") -> POLO PIQUET MASC. | G77: =IFERROR(INDEX(SKUs!$G$6:$G$1997,MATCH(B77,SKUs!$C$6:$C$1997,0)),"") -> INDIGO | H77: =IFERROR(INDEX(SKUs!$H$6:$H$1997,MATCH(B77,SKUs!$C$6:$C$1997,0)),"") -> G | I77: =IFERROR(INDEX(SKUs!#REF!,MATCH(B77,SKUs!$C$6:$C$1997,0)),"") | J77: =SUMIFS(SKUs!$I$6:$I$1997,SKUs!$C$6:$C$1997,B77) -> 18 | K77: =IFERROR(I77*J77,0) -> 0 | L77: =COUNTIF(SKUs!$C$6:$C$1997,B77) -> 1 | U77: =SUM(M77:R77) -> 0 | V77: =IF(B77="","",J77) -> 18
A78: 71 | B78: A.01.0705.017.GG | C78: =IF(B78="","",IFERROR(IF(TRIM(MID(SUBSTITUTE(B78,".",REPT(" ",50)),51,50))="01","Masculino",IF(TRIM(MID(SUBSTITUTE(B78,".",REPT(" ",50)),51,50))="02","Feminino",IF(TRIM(MID(SUBSTITUTE(B78,".",REPT(" ",50)),51,50))="03","Outros","—"))),"—")) -> Masculino | D78: =IFERROR(INDEX(SKUs!$E$6:$E$1997,MATCH(B78,SKUs!$C$6:$C$1997,0)),"") -> POLO | E78: =IFERROR(VLOOKUP(D78,Configurações!$N$5:$O$46,2,FALSE()),"OUTROS") -> VESTUÁRIO | F78: =IFERROR(INDEX(SKUs!$F$6:$F$1997,MATCH(B78,SKUs!$C$6:$C$1997,0)),"") -> POLO PIQUET MASC. | G78: =IFERROR(INDEX(SKUs!$G$6:$G$1997,MATCH(B78,SKUs!$C$6:$C$1997,0)),"") -> INDIGO | H78: =IFERROR(INDEX(SKUs!$H$6:$H$1997,MATCH(B78,SKUs!$C$6:$C$1997,0)),"") -> GG | I78: =IFERROR(INDEX(SKUs!#REF!,MATCH(B78,SKUs!$C$6:$C$1997,0)),"") | J78: =SUMIFS(SKUs!$I$6:$I$1997,SKUs!$C$6:$C$1997,B78) -> 0 | K78: =IFERROR(I78*J78,0) -> 0 | L78: =COUNTIF(SKUs!$C$6:$C$1997,B78) -> 1 | M78: 1 | U78: =SUM(M78:R78) -> 1 | V78: =IF(B78="","",J78) -> 0
A79: 72 | B79: A.01.0705.017.XG | C79: =IF(B79="","",IFERROR(IF(TRIM(MID(SUBSTITUTE(B79,".",REPT(" ",50)),51,50))="01","Masculino",IF(TRIM(MID(SUBSTITUTE(B79,".",REPT(" ",50)),51,50))="02","Feminino",IF(TRIM(MID(SUBSTITUTE(B79,".",REPT(" ",50)),51,50))="03","Outros","—"))),"—")) -> Masculino | D79: =IFERROR(INDEX(SKUs!$E$6:$E$1997,MATCH(B79,SKUs!$C$6:$C$1997,0)),"") -> POLO | E79: =IFERROR(VLOOKUP(D79,Configurações!$N$5:$O$46,2,FALSE()),"OUTROS") -> VESTUÁRIO | F79: =IFERROR(INDEX(SKUs!$F$6:$F$1997,MATCH(B79,SKUs!$C$6:$C$1997,0)),"") -> POLO PIQUET MASC. | G79: =IFERROR(INDEX(SKUs!$G$6:$G$1997,MATCH(B79,SKUs!$C$6:$C$1997,0)),"") -> INDIGO | H79: =IFERROR(INDEX(SKUs!$H$6:$H$1997,MATCH(B79,SKUs!$C$6:$C$1997,0)),"") -> XG | I79: =IFERROR(INDEX(SKUs!#REF!,MATCH(B79,SKUs!$C$6:$C$1997,0)),"") | J79: =SUMIFS(SKUs!$I$6:$I$1997,SKUs!$C$6:$C$1997,B79) -> 0 | K79: =IFERROR(I79*J79,0) -> 0 | L79: =COUNTIF(SKUs!$C$6:$C$1997,B79) -> 1 | M79: 8 | U79: =SUM(M79:R79) -> 8 | V79: =IF(B79="","",J79) -> 0
A80: 73 | B80: A.01.0706.015.PP | C80: =IF(B80="","",IFERROR(IF(TRIM(MID(SUBSTITUTE(B80,".",REPT(" ",50)),51,50))="01","Masculino",IF(TRIM(MID(SUBSTITUTE(B80,".",REPT(" ",50)),51,50))="02","Feminino",IF(TRIM(MID(SUBSTITUTE(B80,".",REPT(" ",50)),51,50))="03","Outros","—"))),"—")) -> Masculino | D80: =IFERROR(INDEX(SKUs!$E$6:$E$1997,MATCH(B80,SKUs!$C$6:$C$1997,0)),"") -> POLO | E80: =IFERROR(VLOOKUP(D80,Configurações!$N$5:$O$46,2,FALSE()),"OUTROS") -> VESTUÁRIO | F80: =IFERROR(INDEX(SKUs!$F$6:$F$1997,MATCH(B80,SKUs!$C$6:$C$1997,0)),"") -> POLO PIMA MASC. | G80: =IFERROR(INDEX(SKUs!$G$6:$G$1997,MATCH(B80,SKUs!$C$6:$C$1997,0)),"") -> MESCLA - AZUL | H80: =IFERROR(INDEX(SKUs!$H$6:$H$1997,MATCH(B80,SKUs!$C$6:$C$1997,0)),"") -> PP | I80: =IFERROR(INDEX(SKUs!#REF!,MATCH(B80,SKUs!$C$6:$C$1997,0)),"") | J80: =SUMIFS(SKUs!$I$6:$I$1997,SKUs!$C$6:$C$1997,B80) -> 0 | K80: =IFERROR(I80*J80,0) -> 0 | L80: =COUNTIF(SKUs!$C$6:$C$1997,B80) -> 1 | M80: 5 | U80: =SUM(M80:R80) -> 5 | V80: =IF(B80="","",J80) -> 0
A81: 74 | B81: A.01.0706.015.P | C81: =IF(B81="","",IFERROR(IF(TRIM(MID(SUBSTITUTE(B81,".",REPT(" ",50)),51,50))="01","Masculino",IF(TRIM(MID(SUBSTITUTE(B81,".",REPT(" ",50)),51,50))="02","Feminino",IF(TRIM(MID(SUBSTITUTE(B81,".",REPT(" ",50)),51,50))="03","Outros","—"))),"—")) -> Masculino | D81: =IFERROR(INDEX(SKUs!$E$6:$E$1997,MATCH(B81,SKUs!$C$6:$C$1997,0)),"") -> POLO | E81: =IFERROR(VLOOKUP(D81,Configurações!$N$5:$O$46,2,FALSE()),"OUTROS") -> VESTUÁRIO | F81: =IFERROR(INDEX(SKUs!$F$6:$F$1997,MATCH(B81,SKUs!$C$6:$C$1997,0)),"") -> POLO PIMA MASC. | G81: =IFERROR(INDEX(SKUs!$G$6:$G$1997,MATCH(B81,SKUs!$C$6:$C$1997,0)),"") -> MESCLA - AZUL | H81: =IFERROR(INDEX(SKUs!$H$6:$H$1997,MATCH(B81,SKUs!$C$6:$C$1997,0)),"") -> P | I81: =IFERROR(INDEX(SKUs!#REF!,MATCH(B81,SKUs!$C$6:$C$1997,0)),"") | J81: =SUMIFS(SKUs!$I$6:$I$1997,SKUs!$C$6:$C$1997,B81) -> 0 | K81: =IFERROR(I81*J81,0) -> 0 | L81: =COUNTIF(SKUs!$C$6:$C$1997,B81) -> 1 | M81: 14 | U81: =SUM(M81:R81) -> 14 | V81: =IF(B81="","",J81) -> 0
A82: 75 | B82: A.01.0706.015.M | C82: =IF(B82="","",IFERROR(IF(TRIM(MID(SUBSTITUTE(B82,".",REPT(" ",50)),51,50))="01","Masculino",IF(TRIM(MID(SUBSTITUTE(B82,".",REPT(" ",50)),51,50))="02","Feminino",IF(TRIM(MID(SUBSTITUTE(B82,".",REPT(" ",50)),51,50))="03","Outros","—"))),"—")) -> Masculino | D82: =IFERROR(INDEX(SKUs!$E$6:$E$1997,MATCH(B82,SKUs!$C$6:$C$1997,0)),"") -> POLO | E82: =IFERROR(VLOOKUP(D82,Configurações!$N$5:$O$46,2,FALSE()),"OUTROS") -> VESTUÁRIO | F82: =IFERROR(INDEX(SKUs!$F$6:$F$1997,MATCH(B82,SKUs!$C$6:$C$1997,0)),"") -> POLO PIMA MASC. | G82: =IFERROR(INDEX(SKUs!$G$6:$G$1997,MATCH(B82,SKUs!$C$6:$C$1997,0)),"") -> MESCLA - AZUL | H82: =IFERROR(INDEX(SKUs!$H$6:$H$1997,MATCH(B82,SKUs!$C$6:$C$1997,0)),"") -> M | I82: =IFERROR(INDEX(SKUs!#REF!,MATCH(B82,SKUs!$C$6:$C$1997,0)),"") | J82: =SUMIFS(SKUs!$I$6:$I$1997,SKUs!$C$6:$C$1997,B82) -> 0 | K82: =IFERROR(I82*J82,0) -> 0 | L82: =COUNTIF(SKUs!$C$6:$C$1997,B82) -> 1 | M82: 24 | U82: =SUM(M82:R82) -> 24 | V82: =IF(B82="","",J82) -> 0
A83: 76 | B83: A.01.0706.015.G | C83: =IF(B83="","",IFERROR(IF(TRIM(MID(SUBSTITUTE(B83,".",REPT(" ",50)),51,50))="01","Masculino",IF(TRIM(MID(SUBSTITUTE(B83,".",REPT(" ",50)),51,50))="02","Feminino",IF(TRIM(MID(SUBSTITUTE(B83,".",REPT(" ",50)),51,50))="03","Outros","—"))),"—")) -> Masculino | D83: =IFERROR(INDEX(SKUs!$E$6:$E$1997,MATCH(B83,SKUs!$C$6:$C$1997,0)),"") -> POLO | E83: =IFERROR(VLOOKUP(D83,Configurações!$N$5:$O$46,2,FALSE()),"OUTROS") -> VESTUÁRIO | F83: =IFERROR(INDEX(SKUs!$F$6:$F$1997,MATCH(B83,SKUs!$C$6:$C$1997,0)),"") -> POLO PIMA MASC. | G83: =IFERROR(INDEX(SKUs!$G$6:$G$1997,MATCH(B83,SKUs!$C$6:$C$1997,0)),"") -> MESCLA - AZUL | H83: =IFERROR(INDEX(SKUs!$H$6:$H$1997,MATCH(B83,SKUs!$C$6:$C$1997,0)),"") -> G | I83: =IFERROR(INDEX(SKUs!#REF!,MATCH(B83,SKUs!$C$6:$C$1997,0)),"") | J83: =SUMIFS(SKUs!$I$6:$I$1997,SKUs!$C$6:$C$1997,B83) -> 0 | K83: =IFERROR(I83*J83,0) -> 0 | L83: =COUNTIF(SKUs!$C$6:$C$1997,B83) -> 1 | M83: 4 | U83: =SUM(M83:R83) -> 4 | V83: =IF(B83="","",J83) -> 0
A84: 77 | B84: A.01.0706.015.GG | C84: =IF(B84="","",IFERROR(IF(TRIM(MID(SUBSTITUTE(B84,".",REPT(" ",50)),51,50))="01","Masculino",IF(TRIM(MID(SUBSTITUTE(B84,".",REPT(" ",50)),51,50))="02","Feminino",IF(TRIM(MID(SUBSTITUTE(B84,".",REPT(" ",50)),51,50))="03","Outros","—"))),"—")) -> Masculino | D84: =IFERROR(INDEX(SKUs!$E$6:$E$1997,MATCH(B84,SKUs!$C$6:$C$1997,0)),"") -> POLO | E84: =IFERROR(VLOOKUP(D84,Configurações!$N$5:$O$46,2,FALSE()),"OUTROS") -> VESTUÁRIO | F84: =IFERROR(INDEX(SKUs!$F$6:$F$1997,MATCH(B84,SKUs!$C$6:$C$1997,0)),"") -> POLO PIMA MASC. | G84: =IFERROR(INDEX(SKUs!$G$6:$G$1997,MATCH(B84,SKUs!$C$6:$C$1997,0)),"") -> MESCLA - AZUL | H84: =IFERROR(INDEX(SKUs!$H$6:$H$1997,MATCH(B84,SKUs!$C$6:$C$1997,0)),"") -> GG | I84: =IFERROR(INDEX(SKUs!#REF!,MATCH(B84,SKUs!$C$6:$C$1997,0)),"") | J84: =SUMIFS(SKUs!$I$6:$I$1997,SKUs!$C$6:$C$1997,B84) -> 0 | K84: =IFERROR(I84*J84,0) -> 0 | L84: =COUNTIF(SKUs!$C$6:$C$1997,B84) -> 1 | M84: 13 | U84: =SUM(M84:R84) -> 13 | V84: =IF(B84="","",J84) -> 0
A85: 78 | B85: A.01.0706.015.XG | C85: =IF(B85="","",IFERROR(IF(TRIM(MID(SUBSTITUTE(B85,".",REPT(" ",50)),51,50))="01","Masculino",IF(TRIM(MID(SUBSTITUTE(B85,".",REPT(" ",50)),51,50))="02","Feminino",IF(TRIM(MID(SUBSTITUTE(B85,".",REPT(" ",50)),51,50))="03","Outros","—"))),"—")) -> Masculino | D85: =IFERROR(INDEX(SKUs!$E$6:$E$1997,MATCH(B85,SKUs!$C$6:$C$1997,0)),"") -> POLO | E85: =IFERROR(VLOOKUP(D85,Configurações!$N$5:$O$46,2,FALSE()),"OUTROS") -> VESTUÁRIO | F85: =IFERROR(INDEX(SKUs!$F$6:$F$1997,MATCH(B85,SKUs!$C$6:$C$1997,0)),"") -> POLO PIMA MASC. | G85: =IFERROR(INDEX(SKUs!$G$6:$G$1997,MATCH(B85,SKUs!$C$6:$C$1997,0)),"") -> MESCLA - AZUL | H85: =IFERROR(INDEX(SKUs!$H$6:$H$1997,MATCH(B85,SKUs!$C$6:$C$1997,0)),"") -> XG | I85: =IFERROR(INDEX(SKUs!#REF!,MATCH(B85,SKUs!$C$6:$C$1997,0)),"") | J85: =SUMIFS(SKUs!$I$6:$I$1997,SKUs!$C$6:$C$1997,B85) -> 0 | K85: =IFERROR(I85*J85,0) -> 0 | L85: =COUNTIF(SKUs!$C$6:$C$1997,B85) -> 1 | M85: 7 | U85: =SUM(M85:R85) -> 7 | V85: =IF(B85="","",J85) -> 0
A86: 79 | B86: A.01.0713.005.PP | C86: =IF(B86="","",IFERROR(IF(TRIM(MID(SUBSTITUTE(B86,".",REPT(" ",50)),51,50))="01","Masculino",IF(TRIM(MID(SUBSTITUTE(B86,".",REPT(" ",50)),51,50))="02","Feminino",IF(TRIM(MID(SUBSTITUTE(B86,".",REPT(" ",50)),51,50))="03","Outros","—"))),"—")) -> Masculino | D86: =IFERROR(INDEX(SKUs!$E$6:$E$1997,MATCH(B86,SKUs!$C$6:$C$1997,0)),"") -> POLO | E86: =IFERROR(VLOOKUP(D86,Configurações!$N$5:$O$46,2,FALSE()),"OUTROS") -> VESTUÁRIO | F86: =IFERROR(INDEX(SKUs!$F$6:$F$1997,MATCH(B86,SKUs!$C$6:$C$1997,0)),"") -> POLO COTTON MASC. | G86: =IFERROR(INDEX(SKUs!$G$6:$G$1997,MATCH(B86,SKUs!$C$6:$C$1997,0)),"") -> PRETA | H86: =IFERROR(INDEX(SKUs!$H$6:$H$1997,MATCH(B86,SKUs!$C$6:$C$1997,0)),"") -> PP | I86: =IFERROR(INDEX(SKUs!#REF!,MATCH(B86,SKUs!$C$6:$C$1997,0)),"") | J86: =SUMIFS(SKUs!$I$6:$I$1997,SKUs!$C$6:$C$1997,B86) -> 0 | K86: =IFERROR(I86*J86,0) -> 0 | L86: =COUNTIF(SKUs!$C$6:$C$1997,B86) -> 1 | M86: 5 | U86: =SUM(M86:R86) -> 5 | V86: =IF(B86="","",J86) -> 0
A87: 80 | B87: A.01.0713.005.P | C87: =IF(B87="","",IFERROR(IF(TRIM(MID(SUBSTITUTE(B87,".",REPT(" ",50)),51,50))="01","Masculino",IF(TRIM(MID(SUBSTITUTE(B87,".",REPT(" ",50)),51,50))="02","Feminino",IF(TRIM(MID(SUBSTITUTE(B87,".",REPT(" ",50)),51,50))="03","Outros","—"))),"—")) -> Masculino | D87: =IFERROR(INDEX(SKUs!$E$6:$E$1997,MATCH(B87,SKUs!$C$6:$C$1997,0)),"") -> POLO | E87: =IFERROR(VLOOKUP(D87,Configurações!$N$5:$O$46,2,FALSE()),"OUTROS") -> VESTUÁRIO | F87: =IFERROR(INDEX(SKUs!$F$6:$F$1997,MATCH(B87,SKUs!$C$6:$C$1997,0)),"") -> POLO COTTON MASC. | G87: =IFERROR(INDEX(SKUs!$G$6:$G$1997,MATCH(B87,SKUs!$C$6:$C$1997,0)),"") -> PRETA | H87: =IFERROR(INDEX(SKUs!$H$6:$H$1997,MATCH(B87,SKUs!$C$6:$C$1997,0)),"") -> P | I87: =IFERROR(INDEX(SKUs!#REF!,MATCH(B87,SKUs!$C$6:$C$1997,0)),"") | J87: =SUMIFS(SKUs!$I$6:$I$1997,SKUs!$C$6:$C$1997,B87) -> 71 | K87: =IFERROR(I87*J87,0) -> 0 | L87: =COUNTIF(SKUs!$C$6:$C$1997,B87) -> 4 | U87: =SUM(M87:R87) -> 0 | V87: =IF(B87="","",J87) -> 71
A88: 81 | B88: A.01.0713.005.M | C88: =IF(B88="","",IFERROR(IF(TRIM(MID(SUBSTITUTE(B88,".",REPT(" ",50)),51,50))="01","Masculino",IF(TRIM(MID(SUBSTITUTE(B88,".",REPT(" ",50)),51,50))="02","Feminino",IF(TRIM(MID(SUBSTITUTE(B88,".",REPT(" ",50)),51,50))="03","Outros","—"))),"—")) -> Masculino | D88: =IFERROR(INDEX(SKUs!$E$6:$E$1997,MATCH(B88,SKUs!$C$6:$C$1997,0)),"") -> POLO | E88: =IFERROR(VLOOKUP(D88,Configurações!$N$5:$O$46,2,FALSE()),"OUTROS") -> VESTUÁRIO | F88: =IFERROR(INDEX(SKUs!$F$6:$F$1997,MATCH(B88,SKUs!$C$6:$C$1997,0)),"") -> POLO COTTON MASC. | G88: =IFERROR(INDEX(SKUs!$G$6:$G$1997,MATCH(B88,SKUs!$C$6:$C$1997,0)),"") -> PRETA | H88: =IFERROR(INDEX(SKUs!$H$6:$H$1997,MATCH(B88,SKUs!$C$6:$C$1997,0)),"") -> M | I88: =IFERROR(INDEX(SKUs!#REF!,MATCH(B88,SKUs!$C$6:$C$1997,0)),"") | J88: =SUMIFS(SKUs!$I$6:$I$1997,SKUs!$C$6:$C$1997,B88) -> 216 | K88: =IFERROR(I88*J88,0) -> 0 | L88: =COUNTIF(SKUs!$C$6:$C$1997,B88) -> 7 | U88: =SUM(M88:R88) -> 0 | V88: =IF(B88="","",J88) -> 216
A89: 82 | B89: A.01.0713.005.G | C89: =IF(B89="","",IFERROR(IF(TRIM(MID(SUBSTITUTE(B89,".",REPT(" ",50)),51,50))="01","Masculino",IF(TRIM(MID(SUBSTITUTE(B89,".",REPT(" ",50)),51,50))="02","Feminino",IF(TRIM(MID(SUBSTITUTE(B89,".",REPT(" ",50)),51,50))="03","Outros","—"))),"—")) -> Masculino | D89: =IFERROR(INDEX(SKUs!$E$6:$E$1997,MATCH(B89,SKUs!$C$6:$C$1997,0)),"") -> POLO | E89: =IFERROR(VLOOKUP(D89,Configurações!$N$5:$O$46,2,FALSE()),"OUTROS") -> VESTUÁRIO | F89: =IFERROR(INDEX(SKUs!$F$6:$F$1997,MATCH(B89,SKUs!$C$6:$C$1997,0)),"") -> POLO COTTON MASC. | G89: =IFERROR(INDEX(SKUs!$G$6:$G$1997,MATCH(B89,SKUs!$C$6:$C$1997,0)),"") -> PRETA | H89: =IFERROR(INDEX(SKUs!$H$6:$H$1997,MATCH(B89,SKUs!$C$6:$C$1997,0)),"") -> G | I89: =IFERROR(INDEX(SKUs!#REF!,MATCH(B89,SKUs!$C$6:$C$1997,0)),"") | J89: =SUMIFS(SKUs!$I$6:$I$1997,SKUs!$C$6:$C$1997,B89) -> 85 | K89: =IFERROR(I89*J89,0) -> 0 | L89: =COUNTIF(SKUs!$C$6:$C$1997,B89) -> 4 | U89: =SUM(M89:R89) -> 0 | V89: =IF(B89="","",J89) -> 85
A90: 83 | B90: A.01.0713.005.GG | C90: =IF(B90="","",IFERROR(IF(TRIM(MID(SUBSTITUTE(B90,".",REPT(" ",50)),51,50))="01","Masculino",IF(TRIM(MID(SUBSTITUTE(B90,".",REPT(" ",50)),51,50))="02","Feminino",IF(TRIM(MID(SUBSTITUTE(B90,".",REPT(" ",50)),51,50))="03","Outros","—"))),"—")) -> Masculino | D90: =IFERROR(INDEX(SKUs!$E$6:$E$1997,MATCH(B90,SKUs!$C$6:$C$1997,0)),"") -> POLO | E90: =IFERROR(VLOOKUP(D90,Configurações!$N$5:$O$46,2,FALSE()),"OUTROS") -> VESTUÁRIO | F90: =IFERROR(INDEX(SKUs!$F$6:$F$1997,MATCH(B90,SKUs!$C$6:$C$1997,0)),"") -> POLO COTTON MASC. | G90: =IFERROR(INDEX(SKUs!$G$6:$G$1997,MATCH(B90,SKUs!$C$6:$C$1997,0)),"") -> PRETA | H90: =IFERROR(INDEX(SKUs!$H$6:$H$1997,MATCH(B90,SKUs!$C$6:$C$1997,0)),"") -> GG | I90: =IFERROR(INDEX(SKUs!#REF!,MATCH(B90,SKUs!$C$6:$C$1997,0)),"") | J90: =SUMIFS(SKUs!$I$6:$I$1997,SKUs!$C$6:$C$1997,B90) -> 0 | K90: =IFERROR(I90*J90,0) -> 0 | L90: =COUNTIF(SKUs!$C$6:$C$1997,B90) -> 3 | M90: 21 | U90: =SUM(M90:R90) -> 21 | V90: =IF(B90="","",J90) -> 0
A91: 84 | B91: A.01.0713.005.XG | C91: =IF(B91="","",IFERROR(IF(TRIM(MID(SUBSTITUTE(B91,".",REPT(" ",50)),51,50))="01","Masculino",IF(TRIM(MID(SUBSTITUTE(B91,".",REPT(" ",50)),51,50))="02","Feminino",IF(TRIM(MID(SUBSTITUTE(B91,".",REPT(" ",50)),51,50))="03","Outros","—"))),"—")) -> Masculino | D91: =IFERROR(INDEX(SKUs!$E$6:$E$1997,MATCH(B91,SKUs!$C$6:$C$1997,0)),"") -> POLO | E91: =IFERROR(VLOOKUP(D91,Configurações!$N$5:$O$46,2,FALSE()),"OUTROS") -> VESTUÁRIO | F91: =IFERROR(INDEX(SKUs!$F$6:$F$1997,MATCH(B91,SKUs!$C$6:$C$1997,0)),"") -> POLO COTTON MASC. | G91: =IFERROR(INDEX(SKUs!$G$6:$G$1997,MATCH(B91,SKUs!$C$6:$C$1997,0)),"") -> PRETA | H91: =IFERROR(INDEX(SKUs!$H$6:$H$1997,MATCH(B91,SKUs!$C$6:$C$1997,0)),"") -> XG | I91: =IFERROR(INDEX(SKUs!#REF!,MATCH(B91,SKUs!$C$6:$C$1997,0)),"") | J91: =SUMIFS(SKUs!$I$6:$I$1997,SKUs!$C$6:$C$1997,B91) -> 0 | K91: =IFERROR(I91*J91,0) -> 0 | L91: =COUNTIF(SKUs!$C$6:$C$1997,B91) -> 3 | M91: 33 | U91: =SUM(M91:R91) -> 33 | V91: =IF(B91="","",J91) -> 0
A92: 85 | B92: A.01.0695.005.PP | C92: =IF(B92="","",IFERROR(IF(TRIM(MID(SUBSTITUTE(B92,".",REPT(" ",50)),51,50))="01","Masculino",IF(TRIM(MID(SUBSTITUTE(B92,".",REPT(" ",50)),51,50))="02","Feminino",IF(TRIM(MID(SUBSTITUTE(B92,".",REPT(" ",50)),51,50))="03","Outros","—"))),"—")) -> Masculino | D92: =IFERROR(INDEX(SKUs!$E$6:$E$1997,MATCH(B92,SKUs!$C$6:$C$1997,0)),"") -> POLO | E92: =IFERROR(VLOOKUP(D92,Configurações!$N$5:$O$46,2,FALSE()),"OUTROS") -> VESTUÁRIO | F92: =IFERROR(INDEX(SKUs!$F$6:$F$1997,MATCH(B92,SKUs!$C$6:$C$1997,0)),"") -> POLO PIMA MASC. | G92: =IFERROR(INDEX(SKUs!$G$6:$G$1997,MATCH(B92,SKUs!$C$6:$C$1997,0)),"") -> PRETA | H92: =IFERROR(INDEX(SKUs!$H$6:$H$1997,MATCH(B92,SKUs!$C$6:$C$1997,0)),"") -> PP | I92: =IFERROR(INDEX(SKUs!#REF!,MATCH(B92,SKUs!$C$6:$C$1997,0)),"") | J92: =SUMIFS(SKUs!$I$6:$I$1997,SKUs!$C$6:$C$1997,B92) -> 0 | K92: =IFERROR(I92*J92,0) -> 0 | L92: =COUNTIF(SKUs!$C$6:$C$1997,B92) -> 1 | M92: 5 | U92: =SUM(M92:R92) -> 5 | V92: =IF(B92="","",J92) -> 0
A93: 86 | B93: A.01.0695.005.P | C93: =IF(B93="","",IFERROR(IF(TRIM(MID(SUBSTITUTE(B93,".",REPT(" ",50)),51,50))="01","Masculino",IF(TRIM(MID(SUBSTITUTE(B93,".",REPT(" ",50)),51,50))="02","Feminino",IF(TRIM(MID(SUBSTITUTE(B93,".",REPT(" ",50)),51,50))="03","Outros","—"))),"—")) -> Masculino | D93: =IFERROR(INDEX(SKUs!$E$6:$E$1997,MATCH(B93,SKUs!$C$6:$C$1997,0)),"") -> POLO | E93: =IFERROR(VLOOKUP(D93,Configurações!$N$5:$O$46,2,FALSE()),"OUTROS") -> VESTUÁRIO | F93: =IFERROR(INDEX(SKUs!$F$6:$F$1997,MATCH(B93,SKUs!$C$6:$C$1997,0)),"") -> POLO PIMA MASC. | G93: =IFERROR(INDEX(SKUs!$G$6:$G$1997,MATCH(B93,SKUs!$C$6:$C$1997,0)),"") -> PRETA | H93: =IFERROR(INDEX(SKUs!$H$6:$H$1997,MATCH(B93,SKUs!$C$6:$C$1997,0)),"") -> P | I93: =IFERROR(INDEX(SKUs!#REF!,MATCH(B93,SKUs!$C$6:$C$1997,0)),"") | J93: =SUMIFS(SKUs!$I$6:$I$1997,SKUs!$C$6:$C$1997,B93) -> 0 | K93: =IFERROR(I93*J93,0) -> 0 | L93: =COUNTIF(SKUs!$C$6:$C$1997,B93) -> 1 | M93: 4 | U93: =SUM(M93:R93) -> 4 | V93: =IF(B93="","",J93) -> 0
A94: 87 | B94: A.01.0695.005.M | C94: =IF(B94="","",IFERROR(IF(TRIM(MID(SUBSTITUTE(B94,".",REPT(" ",50)),51,50))="01","Masculino",IF(TRIM(MID(SUBSTITUTE(B94,".",REPT(" ",50)),51,50))="02","Feminino",IF(TRIM(MID(SUBSTITUTE(B94,".",REPT(" ",50)),51,50))="03","Outros","—"))),"—")) -> Masculino | D94: =IFERROR(INDEX(SKUs!$E$6:$E$1997,MATCH(B94,SKUs!$C$6:$C$1997,0)),"") -> POLO | E94: =IFERROR(VLOOKUP(D94,Configurações!$N$5:$O$46,2,FALSE()),"OUTROS") -> VESTUÁRIO | F94: =IFERROR(INDEX(SKUs!$F$6:$F$1997,MATCH(B94,SKUs!$C$6:$C$1997,0)),"") -> POLO PIMA MASC. | G94: =IFERROR(INDEX(SKUs!$G$6:$G$1997,MATCH(B94,SKUs!$C$6:$C$1997,0)),"") -> PRETA | H94: =IFERROR(INDEX(SKUs!$H$6:$H$1997,MATCH(B94,SKUs!$C$6:$C$1997,0)),"") -> M | I94: =IFERROR(INDEX(SKUs!#REF!,MATCH(B94,SKUs!$C$6:$C$1997,0)),"") | J94: =SUMIFS(SKUs!$I$6:$I$1997,SKUs!$C$6:$C$1997,B94) -> 0 | K94: =IFERROR(I94*J94,0) -> 0 | L94: =COUNTIF(SKUs!$C$6:$C$1997,B94) -> 1 | M94: 9 | U94: =SUM(M94:R94) -> 9 | V94: =IF(B94="","",J94) -> 0
A95: 88 | B95: A.01.0695.005.G | C95: =IF(B95="","",IFERROR(IF(TRIM(MID(SUBSTITUTE(B95,".",REPT(" ",50)),51,50))="01","Masculino",IF(TRIM(MID(SUBSTITUTE(B95,".",REPT(" ",50)),51,50))="02","Feminino",IF(TRIM(MID(SUBSTITUTE(B95,".",REPT(" ",50)),51,50))="03","Outros","—"))),"—")) -> Masculino | D95: =IFERROR(INDEX(SKUs!$E$6:$E$1997,MATCH(B95,SKUs!$C$6:$C$1997,0)),"") -> POLO | E95: =IFERROR(VLOOKUP(D95,Configurações!$N$5:$O$46,2,FALSE()),"OUTROS") -> VESTUÁRIO | F95: =IFERROR(INDEX(SKUs!$F$6:$F$1997,MATCH(B95,SKUs!$C$6:$C$1997,0)),"") -> POLO PIMA MASC. | G95: =IFERROR(INDEX(SKUs!$G$6:$G$1997,MATCH(B95,SKUs!$C$6:$C$1997,0)),"") -> PRETA | H95: =IFERROR(INDEX(SKUs!$H$6:$H$1997,MATCH(B95,SKUs!$C$6:$C$1997,0)),"") -> G | I95: =IFERROR(INDEX(SKUs!#REF!,MATCH(B95,SKUs!$C$6:$C$1997,0)),"") | J95: =SUMIFS(SKUs!$I$6:$I$1997,SKUs!$C$6:$C$1997,B95) -> 0 | K95: =IFERROR(I95*J95,0) -> 0 | L95: =COUNTIF(SKUs!$C$6:$C$1997,B95) -> 1 | M95: 10 | U95: =SUM(M95:R95) -> 10 | V95: =IF(B95="","",J95) -> 0
A96: 89 | B96: A.01.0695.005.GG | C96: =IF(B96="","",IFERROR(IF(TRIM(MID(SUBSTITUTE(B96,".",REPT(" ",50)),51,50))="01","Masculino",IF(TRIM(MID(SUBSTITUTE(B96,".",REPT(" ",50)),51,50))="02","Feminino",IF(TRIM(MID(SUBSTITUTE(B96,".",REPT(" ",50)),51,50))="03","Outros","—"))),"—")) -> Masculino | D96: =IFERROR(INDEX(SKUs!$E$6:$E$1997,MATCH(B96,SKUs!$C$6:$C$1997,0)),"") -> POLO | E96: =IFERROR(VLOOKUP(D96,Configurações!$N$5:$O$46,2,FALSE()),"OUTROS") -> VESTUÁRIO | F96: =IFERROR(INDEX(SKUs!$F$6:$F$1997,MATCH(B96,SKUs!$C$6:$C$1997,0)),"") -> POLO PIMA MASC. | G96: =IFERROR(INDEX(SKUs!$G$6:$G$1997,MATCH(B96,SKUs!$C$6:$C$1997,0)),"") -> PRETA | H96: =IFERROR(INDEX(SKUs!$H$6:$H$1997,MATCH(B96,SKUs!$C$6:$C$1997,0)),"") -> GG | I96: =IFERROR(INDEX(SKUs!#REF!,MATCH(B96,SKUs!$C$6:$C$1997,0)),"") | J96: =SUMIFS(SKUs!$I$6:$I$1997,SKUs!$C$6:$C$1997,B96) -> 0 | K96: =IFERROR(I96*J96,0) -> 0 | L96: =COUNTIF(SKUs!$C$6:$C$1997,B96) -> 1 | M96: 10 | U96: =SUM(M96:R96) -> 10 | V96: =IF(B96="","",J96) -> 0
A97: 90 | B97: A.01.0695.005.XG | C97: =IF(B97="","",IFERROR(IF(TRIM(MID(SUBSTITUTE(B97,".",REPT(" ",50)),51,50))="01","Masculino",IF(TRIM(MID(SUBSTITUTE(B97,".",REPT(" ",50)),51,50))="02","Feminino",IF(TRIM(MID(SUBSTITUTE(B97,".",REPT(" ",50)),51,50))="03","Outros","—"))),"—")) -> Masculino | D97: =IFERROR(INDEX(SKUs!$E$6:$E$1997,MATCH(B97,SKUs!$C$6:$C$1997,0)),"") -> POLO | E97: =IFERROR(VLOOKUP(D97,Configurações!$N$5:$O$46,2,FALSE()),"OUTROS") -> VESTUÁRIO | F97: =IFERROR(INDEX(SKUs!$F$6:$F$1997,MATCH(B97,SKUs!$C$6:$C$1997,0)),"") -> POLO PIMA MASC. | G97: =IFERROR(INDEX(SKUs!$G$6:$G$1997,MATCH(B97,SKUs!$C$6:$C$1997,0)),"") -> PRETA | H97: =IFERROR(INDEX(SKUs!$H$6:$H$1997,MATCH(B97,SKUs!$C$6:$C$1997,0)),"") -> XG | I97: =IFERROR(INDEX(SKUs!#REF!,MATCH(B97,SKUs!$C$6:$C$1997,0)),"") | J97: =SUMIFS(SKUs!$I$6:$I$1997,SKUs!$C$6:$C$1997,B97) -> 0 | K97: =IFERROR(I97*J97,0) -> 0 | L97: =COUNTIF(SKUs!$C$6:$C$1997,B97) -> 1 | M97: 3 | U97: =SUM(M97:R97) -> 3 | V97: =IF(B97="","",J97) -> 0
A98: 91 | B98: A.01.0780.011.P | C98: =IF(B98="","",IFERROR(IF(TRIM(MID(SUBSTITUTE(B98,".",REPT(" ",50)),51,50))="01","Masculino",IF(TRIM(MID(SUBSTITUTE(B98,".",REPT(" ",50)),51,50))="02","Feminino",IF(TRIM(MID(SUBSTITUTE(B98,".",REPT(" ",50)),51,50))="03","Outros","—"))),"—")) -> Masculino | D98: =IFERROR(INDEX(SKUs!$E$6:$E$1997,MATCH(B98,SKUs!$C$6:$C$1997,0)),"") -> CAMISETA | E98: =IFERROR(VLOOKUP(D98,Configurações!$N$5:$O$46,2,FALSE()),"OUTROS") -> VESTUÁRIO | F98: =IFERROR(INDEX(SKUs!$F$6:$F$1997,MATCH(B98,SKUs!$C$6:$C$1997,0)),"") -> CAMISETA COPA MASC. | G98: =IFERROR(INDEX(SKUs!$G$6:$G$1997,MATCH(B98,SKUs!$C$6:$C$1997,0)),"") -> VERDE | H98: =IFERROR(INDEX(SKUs!$H$6:$H$1997,MATCH(B98,SKUs!$C$6:$C$1997,0)),"") -> P | I98: =IFERROR(INDEX(SKUs!#REF!,MATCH(B98,SKUs!$C$6:$C$1997,0)),"") | J98: =SUMIFS(SKUs!$I$6:$I$1997,SKUs!$C$6:$C$1997,B98) -> 0 | K98: =IFERROR(I98*J98,0) -> 0 | L98: =COUNTIF(SKUs!$C$6:$C$1997,B98) -> 1 | U98: =SUM(M98:R98) -> 0 | V98: =IF(B98="","",J98) -> 0
A99: 92 | B99: A.01.0780.011.M | C99: =IF(B99="","",IFERROR(IF(TRIM(MID(SUBSTITUTE(B99,".",REPT(" ",50)),51,50))="01","Masculino",IF(TRIM(MID(SUBSTITUTE(B99,".",REPT(" ",50)),51,50))="02","Feminino",IF(TRIM(MID(SUBSTITUTE(B99,".",REPT(" ",50)),51,50))="03","Outros","—"))),"—")) -> Masculino | D99: =IFERROR(INDEX(SKUs!$E$6:$E$1997,MATCH(B99,SKUs!$C$6:$C$1997,0)),"") -> CAMISETA | E99: =IFERROR(VLOOKUP(D99,Configurações!$N$5:$O$46,2,FALSE()),"OUTROS") -> VESTUÁRIO | F99: =IFERROR(INDEX(SKUs!$F$6:$F$1997,MATCH(B99,SKUs!$C$6:$C$1997,0)),"") -> CAMISETA COPA MASC. | G99: =IFERROR(INDEX(SKUs!$G$6:$G$1997,MATCH(B99,SKUs!$C$6:$C$1997,0)),"") -> VERDE | H99: =IFERROR(INDEX(SKUs!$H$6:$H$1997,MATCH(B99,SKUs!$C$6:$C$1997,0)),"") -> M | I99: =IFERROR(INDEX(SKUs!#REF!,MATCH(B99,SKUs!$C$6:$C$1997,0)),"") | J99: =SUMIFS(SKUs!$I$6:$I$1997,SKUs!$C$6:$C$1997,B99) -> 0 | K99: =IFERROR(I99*J99,0) -> 0 | L99: =COUNTIF(SKUs!$C$6:$C$1997,B99) -> 1 | U99: =SUM(M99:R99) -> 0 | V99: =IF(B99="","",J99) -> 0
A100: 93 | B100: A.01.0780.011.G | C100: =IF(B100="","",IFERROR(IF(TRIM(MID(SUBSTITUTE(B100,".",REPT(" ",50)),51,50))="01","Masculino",IF(TRIM(MID(SUBSTITUTE(B100,".",REPT(" ",50)),51,50))="02","Feminino",IF(TRIM(MID(SUBSTITUTE(B100,".",REPT(" ",50)),51,50))="03","Outros","—"))),"—")) -> Masculino | D100: =IFERROR(INDEX(SKUs!$E$6:$E$1997,MATCH(B100,SKUs!$C$6:$C$1997,0)),"") -> CAMISETA | E100: =IFERROR(VLOOKUP(D100,Configurações!$N$5:$O$46,2,FALSE()),"OUTROS") -> VESTUÁRIO | F100: =IFERROR(INDEX(SKUs!$F$6:$F$1997,MATCH(B100,SKUs!$C$6:$C$1997,0)),"") -> CAMISETA COPA MASC. | G100: =IFERROR(INDEX(SKUs!$G$6:$G$1997,MATCH(B100,SKUs!$C$6:$C$1997,0)),"") -> VERDE | H100: =IFERROR(INDEX(SKUs!$H$6:$H$1997,MATCH(B100,SKUs!$C$6:$C$1997,0)),"") -> G | I100: =IFERROR(INDEX(SKUs!#REF!,MATCH(B100,SKUs!$C$6:$C$1997,0)),"") | J100: =SUMIFS(SKUs!$I$6:$I$1997,SKUs!$C$6:$C$1997,B100) -> 0 | K100: =IFERROR(I100*J100,0) -> 0 | L100: =COUNTIF(SKUs!$C$6:$C$1997,B100) -> 1 | U100: =SUM(M100:R100) -> 0 | V100: =IF(B100="","",J100) -> 0
A101: 94 | B101: A.01.0780.011.GG | C101: =IF(B101="","",IFERROR(IF(TRIM(MID(SUBSTITUTE(B101,".",REPT(" ",50)),51,50))="01","Masculino",IF(TRIM(MID(SUBSTITUTE(B101,".",REPT(" ",50)),51,50))="02","Feminino",IF(TRIM(MID(SUBSTITUTE(B101,".",REPT(" ",50)),51,50))="03","Outros","—"))),"—")) -> Masculino | D101: =IFERROR(INDEX(SKUs!$E$6:$E$1997,MATCH(B101,SKUs!$C$6:$C$1997,0)),"") -> CAMISETA | E101: =IFERROR(VLOOKUP(D101,Configurações!$N$5:$O$46,2,FALSE()),"OUTROS") -> VESTUÁRIO | F101: =IFERROR(INDEX(SKUs!$F$6:$F$1997,MATCH(B101,SKUs!$C$6:$C$1997,0)),"") -> CAMISETA COPA MASC. | G101: =IFERROR(INDEX(SKUs!$G$6:$G$1997,MATCH(B101,SKUs!$C$6:$C$1997,0)),"") -> VERDE | H101: =IFERROR(INDEX(SKUs!$H$6:$H$1997,MATCH(B101,SKUs!$C$6:$C$1997,0)),"") -> GG | I101: =IFERROR(INDEX(SKUs!#REF!,MATCH(B101,SKUs!$C$6:$C$1997,0)),"") | J101: =SUMIFS(SKUs!$I$6:$I$1997,SKUs!$C$6:$C$1997,B101) -> 0 | K101: =IFERROR(I101*J101,0) -> 0 | L101: =COUNTIF(SKUs!$C$6:$C$1997,B101) -> 1 | U101: =SUM(M101:R101) -> 0 | V101: =IF(B101="","",J101) -> 0
A102: 95 | B102: A.01.0780.011.XG | C102: =IF(B102="","",IFERROR(IF(TRIM(MID(SUBSTITUTE(B102,".",REPT(" ",50)),51,50))="01","Masculino",IF(TRIM(MID(SUBSTITUTE(B102,".",REPT(" ",50)),51,50))="02","Feminino",IF(TRIM(MID(SUBSTITUTE(B102,".",REPT(" ",50)),51,50))="03","Outros","—"))),"—")) -> Masculino | D102: =IFERROR(INDEX(SKUs!$E$6:$E$1997,MATCH(B102,SKUs!$C$6:$C$1997,0)),"") -> CAMISETA | E102: =IFERROR(VLOOKUP(D102,Configurações!$N$5:$O$46,2,FALSE()),"OUTROS") -> VESTUÁRIO | F102: =IFERROR(INDEX(SKUs!$F$6:$F$1997,MATCH(B102,SKUs!$C$6:$C$1997,0)),"") -> CAMISETA COPA MASC. | G102: =IFERROR(INDEX(SKUs!$G$6:$G$1997,MATCH(B102,SKUs!$C$6:$C$1997,0)),"") -> VERDE | H102: =IFERROR(INDEX(SKUs!$H$6:$H$1997,MATCH(B102,SKUs!$C$6:$C$1997,0)),"") -> XG | I102: =IFERROR(INDEX(SKUs!#REF!,MATCH(B102,SKUs!$C$6:$C$1997,0)),"") | J102: =SUMIFS(SKUs!$I$6:$I$1997,SKUs!$C$6:$C$1997,B102) -> 0 | K102: =IFERROR(I102*J102,0) -> 0 | L102: =COUNTIF(SKUs!$C$6:$C$1997,B102) -> 1 | U102: =SUM(M102:R102) -> 0 | V102: =IF(B102="","",J102) -> 0
A103: 96 | B103: A.01.0780.011.XGG | C103: =IF(B103="","",IFERROR(IF(TRIM(MID(SUBSTITUTE(B103,".",REPT(" ",50)),51,50))="01","Masculino",IF(TRIM(MID(SUBSTITUTE(B103,".",REPT(" ",50)),51,50))="02","Feminino",IF(TRIM(MID(SUBSTITUTE(B103,".",REPT(" ",50)),51,50))="03","Outros","—"))),"—")) -> Masculino | D103: =IFERROR(INDEX(SKUs!$E$6:$E$1997,MATCH(B103,SKUs!$C$6:$C$1997,0)),"") -> CAMISETA | E103: =IFERROR(VLOOKUP(D103,Configurações!$N$5:$O$46,2,FALSE()),"OUTROS") -> VESTUÁRIO | F103: =IFERROR(INDEX(SKUs!$F$6:$F$1997,MATCH(B103,SKUs!$C$6:$C$1997,0)),"") -> CAMISETA COPA MASC. | G103: =IFERROR(INDEX(SKUs!$G$6:$G$1997,MATCH(B103,SKUs!$C$6:$C$1997,0)),"") -> VERDE | H103: =IFERROR(INDEX(SKUs!$H$6:$H$1997,MATCH(B103,SKUs!$C$6:$C$1997,0)),"") -> 4G | I103: =IFERROR(INDEX(SKUs!#REF!,MATCH(B103,SKUs!$C$6:$C$1997,0)),"") | J103: =SUMIFS(SKUs!$I$6:$I$1997,SKUs!$C$6:$C$1997,B103) -> 0 | K103: =IFERROR(I103*J103,0) -> 0 | L103: =COUNTIF(SKUs!$C$6:$C$1997,B103) -> 1 | U103: =SUM(M103:R103) -> 0 | V103: =IF(B103="","",J103) -> 0
A104: 97 | B104: A.02.0702.002.PP | C104: =IF(B104="","",IFERROR(IF(TRIM(MID(SUBSTITUTE(B104,".",REPT(" ",50)),51,50))="01","Masculino",IF(TRIM(MID(SUBSTITUTE(B104,".",REPT(" ",50)),51,50))="02","Feminino",IF(TRIM(MID(SUBSTITUTE(B104,".",REPT(" ",50)),51,50))="03","Outros","—"))),"—")) -> Feminino | D104: =IFERROR(INDEX(SKUs!$E$6:$E$1997,MATCH(B104,SKUs!$C$6:$C$1997,0)),"") -> POLO | E104: =IFERROR(VLOOKUP(D104,Configurações!$N$5:$O$46,2,FALSE()),"OUTROS") -> VESTUÁRIO | F104: =IFERROR(INDEX(SKUs!$F$6:$F$1997,MATCH(B104,SKUs!$C$6:$C$1997,0)),"") -> POLO PIQUET FEM. | G104: =IFERROR(INDEX(SKUs!$G$6:$G$1997,MATCH(B104,SKUs!$C$6:$C$1997,0)),"") -> MARINHO-RISCOS | H104: =IFERROR(INDEX(SKUs!$H$6:$H$1997,MATCH(B104,SKUs!$C$6:$C$1997,0)),"") -> PP | I104: =IFERROR(INDEX(SKUs!#REF!,MATCH(B104,SKUs!$C$6:$C$1997,0)),"") | J104: =SUMIFS(SKUs!$I$6:$I$1997,SKUs!$C$6:$C$1997,B104) -> 0 | K104: =IFERROR(I104*J104,0) -> 0 | L104: =COUNTIF(SKUs!$C$6:$C$1997,B104) -> 1 | M104: 10 | U104: =SUM(M104:R104) -> 10 | V104: =IF(B104="","",J104) -> 0
A105: 98 | B105: A.02.0702.002.P | C105: =IF(B105="","",IFERROR(IF(TRIM(MID(SUBSTITUTE(B105,".",REPT(" ",50)),51,50))="01","Masculino",IF(TRIM(MID(SUBSTITUTE(B105,".",REPT(" ",50)),51,50))="02","Feminino",IF(TRIM(MID(SUBSTITUTE(B105,".",REPT(" ",50)),51,50))="03","Outros","—"))),"—")) -> Feminino | D105: =IFERROR(INDEX(SKUs!$E$6:$E$1997,MATCH(B105,SKUs!$C$6:$C$1997,0)),"") -> POLO | E105: =IFERROR(VLOOKUP(D105,Configurações!$N$5:$O$46,2,FALSE()),"OUTROS") -> VESTUÁRIO | F105: =IFERROR(INDEX(SKUs!$F$6:$F$1997,MATCH(B105,SKUs!$C$6:$C$1997,0)),"") -> POLO PIQUET FEM. | G105: =IFERROR(INDEX(SKUs!$G$6:$G$1997,MATCH(B105,SKUs!$C$6:$C$1997,0)),"") -> MARINHO-RISCOS | H105: =IFERROR(INDEX(SKUs!$H$6:$H$1997,MATCH(B105,SKUs!$C$6:$C$1997,0)),"") -> P | I105: =IFERROR(INDEX(SKUs!#REF!,MATCH(B105,SKUs!$C$6:$C$1997,0)),"") | J105: =SUMIFS(SKUs!$I$6:$I$1997,SKUs!$C$6:$C$1997,B105) -> 0 | K105: =IFERROR(I105*J105,0) -> 0 | L105: =COUNTIF(SKUs!$C$6:$C$1997,B105) -> 1 | M105: 13 | U105: =SUM(M105:R105) -> 13 | V105: =IF(B105="","",J105) -> 0
A106: 99 | B106: A.02.0702.002.M | C106: =IF(B106="","",IFERROR(IF(TRIM(MID(SUBSTITUTE(B106,".",REPT(" ",50)),51,50))="01","Masculino",IF(TRIM(MID(SUBSTITUTE(B106,".",REPT(" ",50)),51,50))="02","Feminino",IF(TRIM(MID(SUBSTITUTE(B106,".",REPT(" ",50)),51,50))="03","Outros","—"))),"—")) -> Feminino | D106: =IFERROR(INDEX(SKUs!$E$6:$E$1997,MATCH(B106,SKUs!$C$6:$C$1997,0)),"") -> POLO | E106: =IFERROR(VLOOKUP(D106,Configurações!$N$5:$O$46,2,FALSE()),"OUTROS") -> VESTUÁRIO | F106: =IFERROR(INDEX(SKUs!$F$6:$F$1997,MATCH(B106,SKUs!$C$6:$C$1997,0)),"") -> POLO PIQUET FEM. | G106: =IFERROR(INDEX(SKUs!$G$6:$G$1997,MATCH(B106,SKUs!$C$6:$C$1997,0)),"") -> MARINHO-RISCOS | H106: =IFERROR(INDEX(SKUs!$H$6:$H$1997,MATCH(B106,SKUs!$C$6:$C$1997,0)),"") -> M | I106: =IFERROR(INDEX(SKUs!#REF!,MATCH(B106,SKUs!$C$6:$C$1997,0)),"") | J106: =SUMIFS(SKUs!$I$6:$I$1997,SKUs!$C$6:$C$1997,B106) -> 0 | K106: =IFERROR(I106*J106,0) -> 0 | L106: =COUNTIF(SKUs!$C$6:$C$1997,B106) -> 1 | M106: 15 | U106: =SUM(M106:R106) -> 15 | V106: =IF(B106="","",J106) -> 0
A107: 100 | B107: A.02.0702.002.G | C107: =IF(B107="","",IFERROR(IF(TRIM(MID(SUBSTITUTE(B107,".",REPT(" ",50)),51,50))="01","Masculino",IF(TRIM(MID(SUBSTITUTE(B107,".",REPT(" ",50)),51,50))="02","Feminino",IF(TRIM(MID(SUBSTITUTE(B107,".",REPT(" ",50)),51,50))="03","Outros","—"))),"—")) -> Feminino | D107: =IFERROR(INDEX(SKUs!$E$6:$E$1997,MATCH(B107,SKUs!$C$6:$C$1997,0)),"") -> POLO | E107: =IFERROR(VLOOKUP(D107,Configurações!$N$5:$O$46,2,FALSE()),"OUTROS") -> VESTUÁRIO | F107: =IFERROR(INDEX(SKUs!$F$6:$F$1997,MATCH(B107,SKUs!$C$6:$C$1997,0)),"") -> POLO PIQUET FEM. | G107: =IFERROR(INDEX(SKUs!$G$6:$G$1997,MATCH(B107,SKUs!$C$6:$C$1997,0)),"") -> MARINHO-RISCOS | H107: =IFERROR(INDEX(SKUs!$H$6:$H$1997,MATCH(B107,SKUs!$C$6:$C$1997,0)),"") -> G | I107: =IFERROR(INDEX(SKUs!#REF!,MATCH(B107,SKUs!$C$6:$C$1997,0)),"") | J107: =SUMIFS(SKUs!$I$6:$I$1997,SKUs!$C$6:$C$1997,B107) -> 0 | K107: =IFERROR(I107*J107,0) -> 0 | L107: =COUNTIF(SKUs!$C$6:$C$1997,B107) -> 1 | M107: 9 | U107: =SUM(M107:R107) -> 9 | V107: =IF(B107="","",J107) -> 0
A108: 101 | B108: A.02.0702.002.GG | C108: =IF(B108="","",IFERROR(IF(TRIM(MID(SUBSTITUTE(B108,".",REPT(" ",50)),51,50))="01","Masculino",IF(TRIM(MID(SUBSTITUTE(B108,".",REPT(" ",50)),51,50))="02","Feminino",IF(TRIM(MID(SUBSTITUTE(B108,".",REPT(" ",50)),51,50))="03","Outros","—"))),"—")) -> Feminino | D108: =IFERROR(INDEX(SKUs!$E$6:$E$1997,MATCH(B108,SKUs!$C$6:$C$1997,0)),"") -> POLO | E108: =IFERROR(VLOOKUP(D108,Configurações!$N$5:$O$46,2,FALSE()),"OUTROS") -> VESTUÁRIO | F108: =IFERROR(INDEX(SKUs!$F$6:$F$1997,MATCH(B108,SKUs!$C$6:$C$1997,0)),"") -> POLO PIQUET FEM. | G108: =IFERROR(INDEX(SKUs!$G$6:$G$1997,MATCH(B108,SKUs!$C$6:$C$1997,0)),"") -> MARINHO-RISCOS | H108: =IFERROR(INDEX(SKUs!$H$6:$H$1997,MATCH(B108,SKUs!$C$6:$C$1997,0)),"") -> GG | I108: =IFERROR(INDEX(SKUs!#REF!,MATCH(B108,SKUs!$C$6:$C$1997,0)),"") | J108: =SUMIFS(SKUs!$I$6:$I$1997,SKUs!$C$6:$C$1997,B108) -> 0 | K108: =IFERROR(I108*J108,0) -> 0 | L108: =COUNTIF(SKUs!$C$6:$C$1997,B108) -> 1 | M108: 5 | U108: =SUM(M108:R108) -> 5 | V108: =IF(B108="","",J108) -> 0
A109: 102 | B109: A.02.0702.002.XG | C109: =IF(B109="","",IFERROR(IF(TRIM(MID(SUBSTITUTE(B109,".",REPT(" ",50)),51,50))="01","Masculino",IF(TRIM(MID(SUBSTITUTE(B109,".",REPT(" ",50)),51,50))="02","Feminino",IF(TRIM(MID(SUBSTITUTE(B109,".",REPT(" ",50)),51,50))="03","Outros","—"))),"—")) -> Feminino | D109: =IFERROR(INDEX(SKUs!$E$6:$E$1997,MATCH(B109,SKUs!$C$6:$C$1997,0)),"") -> POLO | E109: =IFERROR(VLOOKUP(D109,Configurações!$N$5:$O$46,2,FALSE()),"OUTROS") -> VESTUÁRIO | F109: =IFERROR(INDEX(SKUs!$F$6:$F$1997,MATCH(B109,SKUs!$C$6:$C$1997,0)),"") -> POLO PIQUET FEM. | G109: =IFERROR(INDEX(SKUs!$G$6:$G$1997,MATCH(B109,SKUs!$C$6:$C$1997,0)),"") -> MARINHO-RISCOS | H109: =IFERROR(INDEX(SKUs!$H$6:$H$1997,MATCH(B109,SKUs!$C$6:$C$1997,0)),"") -> XG | I109: =IFERROR(INDEX(SKUs!#REF!,MATCH(B109,SKUs!$C$6:$C$1997,0)),"") | J109: =SUMIFS(SKUs!$I$6:$I$1997,SKUs!$C$6:$C$1997,B109) -> 0 | K109: =IFERROR(I109*J109,0) -> 0 | L109: =COUNTIF(SKUs!$C$6:$C$1997,B109) -> 1 | M109: 5 | U109: =SUM(M109:R109) -> 5 | V109: =IF(B109="","",J109) -> 0
A110: 103 | B110: A.02.0707.015.PP | C110: =IF(B110="","",IFERROR(IF(TRIM(MID(SUBSTITUTE(B110,".",REPT(" ",50)),51,50))="01","Masculino",IF(TRIM(MID(SUBSTITUTE(B110,".",REPT(" ",50)),51,50))="02","Feminino",IF(TRIM(MID(SUBSTITUTE(B110,".",REPT(" ",50)),51,50))="03","Outros","—"))),"—")) -> Feminino | D110: =IFERROR(INDEX(SKUs!$E$6:$E$1997,MATCH(B110,SKUs!$C$6:$C$1997,0)),"") -> POLO | E110: =IFERROR(VLOOKUP(D110,Configurações!$N$5:$O$46,2,FALSE()),"OUTROS") -> VESTUÁRIO | F110: =IFERROR(INDEX(SKUs!$F$6:$F$1997,MATCH(B110,SKUs!$C$6:$C$1997,0)),"") -> POLO PIMA FEM. | G110: =IFERROR(INDEX(SKUs!$G$6:$G$1997,MATCH(B110,SKUs!$C$6:$C$1997,0)),"") -> MESCLA - AZUL | H110: =IFERROR(INDEX(SKUs!$H$6:$H$1997,MATCH(B110,SKUs!$C$6:$C$1997,0)),"") -> PP | I110: =IFERROR(INDEX(SKUs!#REF!,MATCH(B110,SKUs!$C$6:$C$1997,0)),"") | J110: =SUMIFS(SKUs!$I$6:$I$1997,SKUs!$C$6:$C$1997,B110) -> 0 | K110: =IFERROR(I110*J110,0) -> 0 | L110: =COUNTIF(SKUs!$C$6:$C$1997,B110) -> 1 | M110: 8 | U110: =SUM(M110:R110) -> 8 | V110: =IF(B110="","",J110) -> 0
A111: 104 | B111: A.02.0707.015.P | C111: =IF(B111="","",IFERROR(IF(TRIM(MID(SUBSTITUTE(B111,".",REPT(" ",50)),51,50))="01","Masculino",IF(TRIM(MID(SUBSTITUTE(B111,".",REPT(" ",50)),51,50))="02","Feminino",IF(TRIM(MID(SUBSTITUTE(B111,".",REPT(" ",50)),51,50))="03","Outros","—"))),"—")) -> Feminino | D111: =IFERROR(INDEX(SKUs!$E$6:$E$1997,MATCH(B111,SKUs!$C$6:$C$1997,0)),"") -> POLO | E111: =IFERROR(VLOOKUP(D111,Configurações!$N$5:$O$46,2,FALSE()),"OUTROS") -> VESTUÁRIO | F111: =IFERROR(INDEX(SKUs!$F$6:$F$1997,MATCH(B111,SKUs!$C$6:$C$1997,0)),"") -> POLO PIMA FEM. | G111: =IFERROR(INDEX(SKUs!$G$6:$G$1997,MATCH(B111,SKUs!$C$6:$C$1997,0)),"") -> MESCLA - AZUL | H111: =IFERROR(INDEX(SKUs!$H$6:$H$1997,MATCH(B111,SKUs!$C$6:$C$1997,0)),"") -> PP | I111: =IFERROR(INDEX(SKUs!#REF!,MATCH(B111,SKUs!$C$6:$C$1997,0)),"") | J111: =SUMIFS(SKUs!$I$6:$I$1997,SKUs!$C$6:$C$1997,B111) -> 0 | K111: =IFERROR(I111*J111,0) -> 0 | L111: =COUNTIF(SKUs!$C$6:$C$1997,B111) -> 1 | M111: 11 | U111: =SUM(M111:R111) -> 11 | V111: =IF(B111="","",J111) -> 0
A112: 105 | B112: A.02.0707.015.M | C112: =IF(B112="","",IFERROR(IF(TRIM(MID(SUBSTITUTE(B112,".",REPT(" ",50)),51,50))="01","Masculino",IF(TRIM(MID(SUBSTITUTE(B112,".",REPT(" ",50)),51,50))="02","Feminino",IF(TRIM(MID(SUBSTITUTE(B112,".",REPT(" ",50)),51,50))="03","Outros","—"))),"—")) -> Feminino | D112: =IFERROR(INDEX(SKUs!$E$6:$E$1997,MATCH(B112,SKUs!$C$6:$C$1997,0)),"") -> POLO | E112: =IFERROR(VLOOKUP(D112,Configurações!$N$5:$O$46,2,FALSE()),"OUTROS") -> VESTUÁRIO | F112: =IFERROR(INDEX(SKUs!$F$6:$F$1997,MATCH(B112,SKUs!$C$6:$C$1997,0)),"") -> POLO PIMA FEM. | G112: =IFERROR(INDEX(SKUs!$G$6:$G$1997,MATCH(B112,SKUs!$C$6:$C$1997,0)),"") -> MESCLA - AZUL | H112: =IFERROR(INDEX(SKUs!$H$6:$H$1997,MATCH(B112,SKUs!$C$6:$C$1997,0)),"") -> M | I112: =IFERROR(INDEX(SKUs!#REF!,MATCH(B112,SKUs!$C$6:$C$1997,0)),"") | J112: =SUMIFS(SKUs!$I$6:$I$1997,SKUs!$C$6:$C$1997,B112) -> 0 | K112: =IFERROR(I112*J112,0) -> 0 | L112: =COUNTIF(SKUs!$C$6:$C$1997,B112) -> 1 | M112: 14 | U112: =SUM(M112:R112) -> 14 | V112: =IF(B112="","",J112) -> 0
A113: 106 | B113: A.02.0707.015.G | C113: =IF(B113="","",IFERROR(IF(TRIM(MID(SUBSTITUTE(B113,".",REPT(" ",50)),51,50))="01","Masculino",IF(TRIM(MID(SUBSTITUTE(B113,".",REPT(" ",50)),51,50))="02","Feminino",IF(TRIM(MID(SUBSTITUTE(B113,".",REPT(" ",50)),51,50))="03","Outros","—"))),"—")) -> Feminino | D113: =IFERROR(INDEX(SKUs!$E$6:$E$1997,MATCH(B113,SKUs!$C$6:$C$1997,0)),"") -> POLO | E113: =IFERROR(VLOOKUP(D113,Configurações!$N$5:$O$46,2,FALSE()),"OUTROS") -> VESTUÁRIO | F113: =IFERROR(INDEX(SKUs!$F$6:$F$1997,MATCH(B113,SKUs!$C$6:$C$1997,0)),"") -> POLO PIMA FEM. | G113: =IFERROR(INDEX(SKUs!$G$6:$G$1997,MATCH(B113,SKUs!$C$6:$C$1997,0)),"") -> MESCLA - AZUL | H113: =IFERROR(INDEX(SKUs!$H$6:$H$1997,MATCH(B113,SKUs!$C$6:$C$1997,0)),"") -> G | I113: =IFERROR(INDEX(SKUs!#REF!,MATCH(B113,SKUs!$C$6:$C$1997,0)),"") | J113: =SUMIFS(SKUs!$I$6:$I$1997,SKUs!$C$6:$C$1997,B113) -> 0 | K113: =IFERROR(I113*J113,0) -> 0 | L113: =COUNTIF(SKUs!$C$6:$C$1997,B113) -> 1 | M113: 11 | U113: =SUM(M113:R113) -> 11 | V113: =IF(B113="","",J113) -> 0
A114: 107 | B114: A.02.0707.015.GG | C114: =IF(B114="","",IFERROR(IF(TRIM(MID(SUBSTITUTE(B114,".",REPT(" ",50)),51,50))="01","Masculino",IF(TRIM(MID(SUBSTITUTE(B114,".",REPT(" ",50)),51,50))="02","Feminino",IF(TRIM(MID(SUBSTITUTE(B114,".",REPT(" ",50)),51,50))="03","Outros","—"))),"—")) -> Feminino | D114: =IFERROR(INDEX(SKUs!$E$6:$E$1997,MATCH(B114,SKUs!$C$6:$C$1997,0)),"") -> POLO | E114: =IFERROR(VLOOKUP(D114,Configurações!$N$5:$O$46,2,FALSE()),"OUTROS") -> VESTUÁRIO | F114: =IFERROR(INDEX(SKUs!$F$6:$F$1997,MATCH(B114,SKUs!$C$6:$C$1997,0)),"") -> POLO PIMA FEM. | G114: =IFERROR(INDEX(SKUs!$G$6:$G$1997,MATCH(B114,SKUs!$C$6:$C$1997,0)),"") -> MESCLA - AZUL | H114: =IFERROR(INDEX(SKUs!$H$6:$H$1997,MATCH(B114,SKUs!$C$6:$C$1997,0)),"") -> GG | I114: =IFERROR(INDEX(SKUs!#REF!,MATCH(B114,SKUs!$C$6:$C$1997,0)),"") | J114: =SUMIFS(SKUs!$I$6:$I$1997,SKUs!$C$6:$C$1997,B114) -> 0 | K114: =IFERROR(I114*J114,0) -> 0 | L114: =COUNTIF(SKUs!$C$6:$C$1997,B114) -> 1 | M114: 6 | U114: =SUM(M114:R114) -> 6 | V114: =IF(B114="","",J114) -> 0
A115: 108 | B115: A.02.0707.015.XG | C115: =IF(B115="","",IFERROR(IF(TRIM(MID(SUBSTITUTE(B115,".",REPT(" ",50)),51,50))="01","Masculino",IF(TRIM(MID(SUBSTITUTE(B115,".",REPT(" ",50)),51,50))="02","Feminino",IF(TRIM(MID(SUBSTITUTE(B115,".",REPT(" ",50)),51,50))="03","Outros","—"))),"—")) -> Feminino | D115: =IFERROR(INDEX(SKUs!$E$6:$E$1997,MATCH(B115,SKUs!$C$6:$C$1997,0)),"") -> POLO | E115: =IFERROR(VLOOKUP(D115,Configurações!$N$5:$O$46,2,FALSE()),"OUTROS") -> VESTUÁRIO | F115: =IFERROR(INDEX(SKUs!$F$6:$F$1997,MATCH(B115,SKUs!$C$6:$C$1997,0)),"") -> POLO PIMA FEM. | G115: =IFERROR(INDEX(SKUs!$G$6:$G$1997,MATCH(B115,SKUs!$C$6:$C$1997,0)),"") -> MESCLA - AZUL | H115: =IFERROR(INDEX(SKUs!$H$6:$H$1997,MATCH(B115,SKUs!$C$6:$C$1997,0)),"") -> XG | I115: =IFERROR(INDEX(SKUs!#REF!,MATCH(B115,SKUs!$C$6:$C$1997,0)),"") | J115: =SUMIFS(SKUs!$I$6:$I$1997,SKUs!$C$6:$C$1997,B115) -> 0 | K115: =IFERROR(I115*J115,0) -> 0 | L115: =COUNTIF(SKUs!$C$6:$C$1997,B115) -> 1 | M115: 4 | U115: =SUM(M115:R115) -> 4 | V115: =IF(B115="","",J115) -> 0
... A138: 131 | B138: A.02.0710.004.XG | C138: =IF(B138="","",IFERROR(IF(TRIM(MID(SUBSTITUTE(B138,".",REPT(" ",50)),51,50))="01","Masculino",IF(TRIM(MID(SUBSTITUTE(B138,".",REPT(" ",50)),51,50))="02","Feminino",IF(TRIM(MID(SUBSTITUTE(B138,".",REPT(" ",50)),51,50))="03","Outros","—"))),"—")) -> Feminino | D138: =IFERROR(INDEX(SKUs!$E$6:$E$1997,MATCH(B138,SKUs!$C$6:$C$1997,0)),"") -> POLO | E138: =IFERROR(VLOOKUP(D138,Configurações!$N$5:$O$46,2,FALSE()),"OUTROS") -> VESTUÁRIO | F138: =IFERROR(INDEX(SKUs!$F$6:$F$1997,MATCH(B138,SKUs!$C$6:$C$1997,0)),"") -> POLO PIQUET FEM. | G138: =IFERROR(INDEX(SKUs!$G$6:$G$1997,MATCH(B138,SKUs!$C$6:$C$1997,0)),"") -> BRANCA | H138: =IFERROR(INDEX(SKUs!$H$6:$H$1997,MATCH(B138,SKUs!$C$6:$C$1997,0)),"") -> XG | I138: =IFERROR(INDEX(SKUs!#REF!,MATCH(B138,SKUs!$C$6:$C$1997,0)),"") | J138: =SUMIFS(SKUs!$I$6:$I$1997,SKUs!$C$6:$C$1997,B138) -> 0 | K138: =IFERROR(I138*J138,0) -> 0 | L138: =COUNTIF(SKUs!$C$6:$C$1997,B138) -> 1 | M138: 5 | U138: =SUM(M138:R138) -> 5 | V138: =IF(B138="","",J138) -> 0
A139: 132 | B139: A.01.0683.004.G | C139: =IF(B139="","",IFERROR(IF(TRIM(MID(SUBSTITUTE(B139,".",REPT(" ",50)),51,50))="01","Masculino",IF(TRIM(MID(SUBSTITUTE(B139,".",REPT(" ",50)),51,50))="02","Feminino",IF(TRIM(MID(SUBSTITUTE(B139,".",REPT(" ",50)),51,50))="03","Outros","—"))),"—")) -> Masculino | D139: =IFERROR(INDEX(SKUs!$E$6:$E$1997,MATCH(B139,SKUs!$C$6:$C$1997,0)),"") -> JAQUETA | E139: =IFERROR(VLOOKUP(D139,Configurações!$N$5:$O$46,2,FALSE()),"OUTROS") -> VESTUÁRIO | F139: =IFERROR(INDEX(SKUs!$F$6:$F$1997,MATCH(B139,SKUs!$C$6:$C$1997,0)),"") -> JAQUETA CAPUZ EMBUTIDO | G139: =IFERROR(INDEX(SKUs!$G$6:$G$1997,MATCH(B139,SKUs!$C$6:$C$1997,0)),"") -> AZUL | H139: =IFERROR(INDEX(SKUs!$H$6:$H$1997,MATCH(B139,SKUs!$C$6:$C$1997,0)),"") -> G | I139: =IFERROR(INDEX(SKUs!#REF!,MATCH(B139,SKUs!$C$6:$C$1997,0)),"") | J139: =SUMIFS(SKUs!$I$6:$I$1997,SKUs!$C$6:$C$1997,B139) -> 16 | K139: =IFERROR(I139*J139,0) -> 0 | L139: =COUNTIF(SKUs!$C$6:$C$1997,B139) -> 4 | U139: =SUM(M139:R139) -> 0 | V139: =IF(B139="","",J139) -> 16
A140: 133 | B140: A.01.0683.004.GG | C140: =IF(B140="","",IFERROR(IF(TRIM(MID(SUBSTITUTE(B140,".",REPT(" ",50)),51,50))="01","Masculino",IF(TRIM(MID(SUBSTITUTE(B140,".",REPT(" ",50)),51,50))="02","Feminino",IF(TRIM(MID(SUBSTITUTE(B140,".",REPT(" ",50)),51,50))="03","Outros","—"))),"—")) -> Masculino | D140: =IFERROR(INDEX(SKUs!$E$6:$E$1997,MATCH(B140,SKUs!$C$6:$C$1997,0)),"") -> JAQUETA | E140: =IFERROR(VLOOKUP(D140,Configurações!$N$5:$O$46,2,FALSE()),"OUTROS") -> VESTUÁRIO | F140: =IFERROR(INDEX(SKUs!$F$6:$F$1997,MATCH(B140,SKUs!$C$6:$C$1997,0)),"") -> JAQUETA CAPUZ EMBUTIDO | G140: =IFERROR(INDEX(SKUs!$G$6:$G$1997,MATCH(B140,SKUs!$C$6:$C$1997,0)),"") -> AZUL | H140: =IFERROR(INDEX(SKUs!$H$6:$H$1997,MATCH(B140,SKUs!$C$6:$C$1997,0)),"") -> GG | I140: =IFERROR(INDEX(SKUs!#REF!,MATCH(B140,SKUs!$C$6:$C$1997,0)),"") | J140: =SUMIFS(SKUs!$I$6:$I$1997,SKUs!$C$6:$C$1997,B140) -> 8 | K140: =IFERROR(I140*J140,0) -> 0 | L140: =COUNTIF(SKUs!$C$6:$C$1997,B140) -> 4 | U140: =SUM(M140:R140) -> 0 | V140: =IF(B140="","",J140) -> 8
A141: 134 | B141: A.02.0773.001.P | C141: =IF(B141="","",IFERROR(IF(TRIM(MID(SUBSTITUTE(B141,".",REPT(" ",50)),51,50))="01","Masculino",IF(TRIM(MID(SUBSTITUTE(B141,".",REPT(" ",50)),51,50))="02","Feminino",IF(TRIM(MID(SUBSTITUTE(B141,".",REPT(" ",50)),51,50))="03","Outros","—"))),"—")) -> Feminino | D141: =IFERROR(INDEX(SKUs!$E$6:$E$1997,MATCH(B141,SKUs!$C$6:$C$1997,0)),"") -> JAQUETA | E141: =IFERROR(VLOOKUP(D141,Configurações!$N$5:$O$46,2,FALSE()),"OUTROS") -> VESTUÁRIO | F141: =IFERROR(INDEX(SKUs!$F$6:$F$1997,MATCH(B141,SKUs!$C$6:$C$1997,0)),"") -> JAQUETA COPA FEM. | G141: =IFERROR(INDEX(SKUs!$G$6:$G$1997,MATCH(B141,SKUs!$C$6:$C$1997,0)),"") -> AZUL | H141: =IFERROR(INDEX(SKUs!$H$6:$H$1997,MATCH(B141,SKUs!$C$6:$C$1997,0)),"") -> P | I141: =IFERROR(INDEX(SKUs!#REF!,MATCH(B141,SKUs!$C$6:$C$1997,0)),"") | J141: =SUMIFS(SKUs!$I$6:$I$1997,SKUs!$C$6:$C$1997,B141) -> 8 | K141: =IFERROR(I141*J141,0) -> 0 | L141: =COUNTIF(SKUs!$C$6:$C$1997,B141) -> 1 | U141: =SUM(M141:R141) -> 0 | V141: =IF(B141="","",J141) -> 8
...

Sheet SKUs
A1: BTG PACTUAL · SKUs (OPERACIONAL) · 1 linha por caixa física
A5: CÓD. BTG | B5: ESTOQUE | C5: CÓD. CLIENTE | D5: GÊNERO | E5: CATEGORIA | F5: PRODUTO | G5: COR | H5: TAM | I5: ESTOQUE ATUAL | J5: ESTADO | K5: RUA | L5: PRATELEIRA | M5: CAIXA | N5: ENDEREÇO | P5: aux 1ªRuaPrat | Q5: aux 1ªRuaCaixa | R5: aux 1ªCaixa | T5: aux rankBusca
A6: BTG-001 | B6: Eventos | C6: A.01.0782.001.P | D6: =IF(C6="","",IFERROR(IF(TRIM(MID(SUBSTITUTE(C6,".",REPT(" ",50)),51,50))="01","Masculino",IF(TRIM(MID(SUBSTITUTE(C6,".",REPT(" ",50)),51,50))="02","Feminino",IF(TRIM(MID(SUBSTITUTE(C6,".",REPT(" ",50)),51,50))="03","Outros","—"))),"—")) -> Masculino | E6: POLO | F6: POLO COPA MASC. | G6: AZUL | H6: G | I6: =SUMIFS(Movimentações!$F$6:$F$4998,Movimentações!$C$6:$C$4998,A6,Movimentações!$M$6:$M$4998,M6) -> 0 | J6: ✅ Ótimo | K6: A | L6: 1 | M6: C-01 | N6: =IF(AND(K6="",L6="",M6=""),"⚠ sem endereço","Rua "&K6&IF(L6="",""," · Prat "&L6)&IF(M6="",""," · "&M6)) -> Rua A · Prat 1 · C-01 | P6: =IF(A6="","",IF(AND(K6<>"",L6<>""),IF(COUNTIFS($K$6:K6,K6,$L$6:L6,L6)=1,1,0),0)) -> 1 | Q6: =IF(A6="","",IF(AND(K6<>"",M6<>""),IF(COUNTIFS($K$6:K6,K6,$M$6:M6,M6)=1,1,0),0)) -> 1 | R6: =IF(A6="","",IF(M6<>"",IF(COUNTIF($M$6:M6,M6)=1,1,0),0)) -> 1 | T6: =IF(AND($M6<>"",$M6='Mapa do Galpão'!$C$20),COUNTIF($M$6:$M6,'Mapa do Galpão'!$C$20),"")
A7: BTG-002 | B7: Eventos | C7: A.01.0782.001.M | D7: =IF(C7="","",IFERROR(IF(TRIM(MID(SUBSTITUTE(C7,".",REPT(" ",50)),51,50))="01","Masculino",IF(TRIM(MID(SUBSTITUTE(C7,".",REPT(" ",50)),51,50))="02","Feminino",IF(TRIM(MID(SUBSTITUTE(C7,".",REPT(" ",50)),51,50))="03","Outros","—"))),"—")) -> Masculino | E7: POLO | F7: POLO COPA MASC. | G7: AZUL | H7: M | I7: =SUMIFS(Movimentações!$F$6:$F$4998,Movimentações!$C$6:$C$4998,A7,Movimentações!$M$6:$M$4998,M7) -> 0 | J7: ✅ Ótimo | K7: A | L7: 1 | M7: C-01 | N7: =IF(AND(K7="",L7="",M7=""),"⚠ sem endereço","Rua "&K7&IF(L7="",""," · Prat "&L7)&IF(M7="",""," · "&M7)) -> Rua A · Prat 1 · C-01 | P7: =IF(A7="","",IF(AND(K7<>"",L7<>""),IF(COUNTIFS($K$6:K7,K7,$L$6:L7,L7)=1,1,0),0)) -> 0 | Q7: =IF(A7="","",IF(AND(K7<>"",M7<>""),IF(COUNTIFS($K$6:K7,K7,$M$6:M7,M7)=1,1,0),0)) -> 0 | R7: =IF(A7="","",IF(M7<>"",IF(COUNTIF($M$6:M7,M7)=1,1,0),0)) -> 0 | T7: =IF(AND($M7<>"",$M7='Mapa do Galpão'!$C$20),COUNTIF($M$6:$M7,'Mapa do Galpão'!$C$20),"")
A8: BTG-003 | B8: Eventos | C8: A.01.0782.001.G | D8: =IF(C8="","",IFERROR(IF(TRIM(MID(SUBSTITUTE(C8,".",REPT(" ",50)),51,50))="01","Masculino",IF(TRIM(MID(SUBSTITUTE(C8,".",REPT(" ",50)),51,50))="02","Feminino",IF(TRIM(MID(SUBSTITUTE(C8,".",REPT(" ",50)),51,50))="03","Outros","—"))),"—")) -> Masculino | E8: POLO | F8: POLO COPA MASC. | G8: AZUL | H8: XG | I8: =SUMIFS(Movimentações!$F$6:$F$4998,Movimentações!$C$6:$C$4998,A8,Movimentações!$M$6:$M$4998,M8) -> 0 | J8: ✅ Ótimo | K8: A | L8: 1 | M8: C-01 | N8: =IF(AND(K8="",L8="",M8=""),"⚠ sem endereço","Rua "&K8&IF(L8="",""," · Prat "&L8)&IF(M8="",""," · "&M8)) -> Rua A · Prat 1 · C-01 | P8: =IF(A8="","",IF(AND(K8<>"",L8<>""),IF(COUNTIFS($K$6:K8,K8,$L$6:L8,L8)=1,1,0),0)) -> 0 | Q8: =IF(A8="","",IF(AND(K8<>"",M8<>""),IF(COUNTIFS($K$6:K8,K8,$M$6:M8,M8)=1,1,0),0)) -> 0 | R8: =IF(A8="","",IF(M8<>"",IF(COUNTIF($M$6:M8,M8)=1,1,0),0)) -> 0 | T8: =IF(AND($M8<>"",$M8='Mapa do Galpão'!$C$20),COUNTIF($M$6:$M8,'Mapa do Galpão'!$C$20),"")
A9: BTG-003 | B9: Eventos | C9: A.01.0782.001.G | D9: =IF(C9="","",IFERROR(IF(TRIM(MID(SUBSTITUTE(C9,".",REPT(" ",50)),51,50))="01","Masculino",IF(TRIM(MID(SUBSTITUTE(C9,".",REPT(" ",50)),51,50))="02","Feminino",IF(TRIM(MID(SUBSTITUTE(C9,".",REPT(" ",50)),51,50))="03","Outros","—"))),"—")) -> Masculino | E9: POLO | F9: POLO COPA MASC. | G9: AZUL | H9: XG | I9: =SUMIFS(Movimentações!$F$6:$F$4998,Movimentações!$C$6:$C$4998,A9,Movimentações!$M$6:$M$4998,M9) -> 0 | J9: ✅ Ótimo | K9: A | L9: 1 | M9: C-02 | N9: =IF(AND(K9="",L9="",M9=""),"⚠ sem endereço","Rua "&K9&IF(L9="",""," · Prat "&L9)&IF(M9="",""," · "&M9)) -> Rua A · Prat 1 · C-02 | P9: =IF(A9="","",IF(AND(K9<>"",L9<>""),IF(COUNTIFS($K$6:K9,K9,$L$6:L9,L9)=1,1,0),0)) -> 0 | Q9: =IF(A9="","",IF(AND(K9<>"",M9<>""),IF(COUNTIFS($K$6:K9,K9,$M$6:M9,M9)=1,1,0),0)) -> 1 | R9: =IF(A9="","",IF(M9<>"",IF(COUNTIF($M$6:M9,M9)=1,1,0),0)) -> 1 | T9: =IF(AND($M9<>"",$M9='Mapa do Galpão'!$C$20),COUNTIF($M$6:$M9,'Mapa do Galpão'!$C$20),"")
A10: BTG-004 | B10: Eventos | C10: A.01.0782.001.2G | D10: =IF(C10="","",IFERROR(IF(TRIM(MID(SUBSTITUTE(C10,".",REPT(" ",50)),51,50))="01","Masculino",IF(TRIM(MID(SUBSTITUTE(C10,".",REPT(" ",50)),51,50))="02","Feminino",IF(TRIM(MID(SUBSTITUTE(C10,".",REPT(" ",50)),51,50))="03","Outros","—"))),"—")) -> Masculino | E10: POLO | F10: POLO COPA MASC. | G10: AZUL | H10: P | I10: =SUMIFS(Movimentações!$F$6:$F$4998,Movimentações!$C$6:$C$4998,A10,Movimentações!$M$6:$M$4998,M10) -> 0 | J10: ✅ Ótimo | K10: A | L10: 1 | M10: C-01 | N10: =IF(AND(K10="",L10="",M10=""),"⚠ sem endereço","Rua "&K10&IF(L10="",""," · Prat "&L10)&IF(M10="",""," · "&M10)) -> Rua A · Prat 1 · C-01 | P10: =IF(A10="","",IF(AND(K10<>"",L10<>""),IF(COUNTIFS($K$6:K10,K10,$L$6:L10,L10)=1,1,0),0)) -> 0 | Q10: =IF(A10="","",IF(AND(K10<>"",M10<>""),IF(COUNTIFS($K$6:K10,K10,$M$6:M10,M10)=1,1,0),0)) -> 0 | R10: =IF(A10="","",IF(M10<>"",IF(COUNTIF($M$6:M10,M10)=1,1,0),0)) -> 0 | T10: =IF(AND($M10<>"",$M10='Mapa do Galpão'!$C$20),COUNTIF($M$6:$M10,'Mapa do Galpão'!$C$20),"")
A11: BTG-004 | B11: Eventos | C11: A.01.0782.001.2G | D11: =IF(C11="","",IFERROR(IF(TRIM(MID(SUBSTITUTE(C11,".",REPT(" ",50)),51,50))="01","Masculino",IF(TRIM(MID(SUBSTITUTE(C11,".",REPT(" ",50)),51,50))="02","Feminino",IF(TRIM(MID(SUBSTITUTE(C11,".",REPT(" ",50)),51,50))="03","Outros","—"))),"—")) -> Masculino | E11: POLO | F11: POLO COPA MASC. | G11: AZUL | H11: P | I11: =SUMIFS(Movimentações!$F$6:$F$4998,Movimentações!$C$6:$C$4998,A11,Movimentações!$M$6:$M$4998,M11) -> 0 | J11: ✅ Ótimo | K11: A | L11: 1 | M11: C-02 | N11: =IF(AND(K11="",L11="",M11=""),"⚠ sem endereço","Rua "&K11&IF(L11="",""," · Prat "&L11)&IF(M11="",""," · "&M11)) -> Rua A · Prat 1 · C-02 | P11: =IF(A11="","",IF(AND(K11<>"",L11<>""),IF(COUNTIFS($K$6:K11,K11,$L$6:L11,L11)=1,1,0),0)) -> 0 | Q11: =IF(A11="","",IF(AND(K11<>"",M11<>""),IF(COUNTIFS($K$6:K11,K11,$M$6:M11,M11)=1,1,0),0)) -> 0 | R11: =IF(A11="","",IF(M11<>"",IF(COUNTIF($M$6:M11,M11)=1,1,0),0)) -> 0 | T11: =IF(AND($M11<>"",$M11='Mapa do Galpão'!$C$20),COUNTIF($M$6:$M11,'Mapa do Galpão'!$C$20),"")
A12: BTG-005 | B12: Eventos | C12: A.01.0782.001.3G | D12: =IF(C12="","",IFERROR(IF(TRIM(MID(SUBSTITUTE(C12,".",REPT(" ",50)),51,50))="01","Masculino",IF(TRIM(MID(SUBSTITUTE(C12,".",REPT(" ",50)),51,50))="02","Feminino",IF(TRIM(MID(SUBSTITUTE(C12,".",REPT(" ",50)),51,50))="03","Outros","—"))),"—")) -> Masculino | E12: POLO | F12: POLO COPA MASC. | G12: AZUL | H12: GG | I12: =SUMIFS(Movimentações!$F$6:$F$4998,Movimentações!$C$6:$C$4998,A12,Movimentações!$M$6:$M$4998,M12) -> 0 | J12: ✅ Ótimo | K12: A | L12: 1 | M12: C-02 | N12: =IF(AND(K12="",L12="",M12=""),"⚠ sem endereço","Rua "&K12&IF(L12="",""," · Prat "&L12)&IF(M12="",""," · "&M12)) -> Rua A · Prat 1 · C-02 | P12: =IF(A12="","",IF(AND(K12<>"",L12<>""),IF(COUNTIFS($K$6:K12,K12,$L$6:L12,L12)=1,1,0),0)) -> 0 | Q12: =IF(A12="","",IF(AND(K12<>"",M12<>""),IF(COUNTIFS($K$6:K12,K12,$M$6:M12,M12)=1,1,0),0)) -> 0 | R12: =IF(A12="","",IF(M12<>"",IF(COUNTIF($M$6:M12,M12)=1,1,0),0)) -> 0 | T12: =IF(AND($M12<>"",$M12='Mapa do Galpão'!$C$20),COUNTIF($M$6:$M12,'Mapa do Galpão'!$C$20),"")
A13: BTG-006 | B13: Eventos | C13: A.01.0782.001.4G | D13: =IF(C13="","",IFERROR(IF(TRIM(MID(SUBSTITUTE(C13,".",REPT(" ",50)),51,50))="01","Masculino",IF(TRIM(MID(SUBSTITUTE(C13,".",REPT(" ",50)),51,50))="02","Feminino",IF(TRIM(MID(SUBSTITUTE(C13,".",REPT(" ",50)),51,50))="03","Outros","—"))),"—")) -> Masculino | E13: CAMISETA | F13: CAMISETA COPA MASC. | G13: AZUL | H13: P | I13: =SUMIFS(Movimentações!$F$6:$F$4998,Movimentações!$C$6:$C$4998,A13,Movimentações!$M$6:$M$4998,M13) -> 0 | J13: ✅ Ótimo | K13: A | L13: 1 | M13: C-03 | N13: =IF(AND(K13="",L13="",M13=""),"⚠ sem endereço","Rua "&K13&IF(L13="",""," · Prat "&L13)&IF(M13="",""," · "&M13)) -> Rua A · Prat 1 · C-03 | P13: =IF(A13="","",IF(AND(K13<>"",L13<>""),IF(COUNTIFS($K$6:K13,K13,$L$6:L13,L13)=1,1,0),0)) -> 0 | Q13: =IF(A13="","",IF(AND(K13<>"",M13<>""),IF(COUNTIFS($K$6:K13,K13,$M$6:M13,M13)=1,1,0),0)) -> 1 | R13: =IF(A13="","",IF(M13<>"",IF(COUNTIF($M$6:M13,M13)=1,1,0),0)) -> 1 | T13: =IF(AND($M13<>"",$M13='Mapa do Galpão'!$C$20),COUNTIF($M$6:$M13,'Mapa do Galpão'!$C$20),"")
A14: BTG-007 | B14: Eventos | C14: A.01.0776.001.M | D14: =IF(C14="","",IFERROR(IF(TRIM(MID(SUBSTITUTE(C14,".",REPT(" ",50)),51,50))="01","Masculino",IF(TRIM(MID(SUBSTITUTE(C14,".",REPT(" ",50)),51,50))="02","Feminino",IF(TRIM(MID(SUBSTITUTE(C14,".",REPT(" ",50)),51,50))="03","Outros","—"))),"—")) -> Masculino | E14: CAMISETA | F14: CAMISETA COPA MASC. | G14: AZUL | H14: M | I14: =SUMIFS(Movimentações!$F$6:$F$4998,Movimentações!$C$6:$C$4998,A14,Movimentações!$M$6:$M$4998,M14) -> 0 | J14: ✅ Ótimo | K14: A | L14: 1 | M14: C-03 | N14: =IF(AND(K14="",L14="",M14=""),"⚠ sem endereço","Rua "&K14&IF(L14="",""," · Prat "&L14)&IF(M14="",""," · "&M14)) -> Rua A · Prat 1 · C-03 | P14: =IF(A14="","",IF(AND(K14<>"",L14<>""),IF(COUNTIFS($K$6:K14,K14,$L$6:L14,L14)=1,1,0),0)) -> 0 | Q14: =IF(A14="","",IF(AND(K14<>"",M14<>""),IF(COUNTIFS($K$6:K14,K14,$M$6:M14,M14)=1,1,0),0)) -> 0 | R14: =IF(A14="","",IF(M14<>"",IF(COUNTIF($M$6:M14,M14)=1,1,0),0)) -> 0 | T14: =IF(AND($M14<>"",$M14='Mapa do Galpão'!$C$20),COUNTIF($M$6:$M14,'Mapa do Galpão'!$C$20),"")
A15: BTG-008 | B15: Eventos | C15: A.01.0776.001.G | D15: =IF(C15="","",IFERROR(IF(TRIM(MID(SUBSTITUTE(C15,".",REPT(" ",50)),51,50))="01","Masculino",IF(TRIM(MID(SUBSTITUTE(C15,".",REPT(" ",50)),51,50))="02","Feminino",IF(TRIM(MID(SUBSTITUTE(C15,".",REPT(" ",50)),51,50))="03","Outros","—"))),"—")) -> Masculino | E15: CAMISETA | F15: CAMISETA COPA MASC. | G15: AZUL | H15: GG | I15: =SUMIFS(Movimentações!$F$6:$F$4998,Movimentações!$C$6:$C$4998,A15,Movimentações!$M$6:$M$4998,M15) -> 0 | J15: ✅ Ótimo | K15: A | L15: 1 | M15: C-03 | N15: =IF(AND(K15="",L15="",M15=""),"⚠ sem endereço","Rua "&K15&IF(L15="",""," · Prat "&L15)&IF(M15="",""," · "&M15)) -> Rua A · Prat 1 · C-03 | P15: =IF(A15="","",IF(AND(K15<>"",L15<>""),IF(COUNTIFS($K$6:K15,K15,$L$6:L15,L15)=1,1,0),0)) -> 0 | Q15: =IF(A15="","",IF(AND(K15<>"",M15<>""),IF(COUNTIFS($K$6:K15,K15,$M$6:M15,M15)=1,1,0),0)) -> 0 | R15: =IF(A15="","",IF(M15<>"",IF(COUNTIF($M$6:M15,M15)=1,1,0),0)) -> 0 | T15: =IF(AND($M15<>"",$M15='Mapa do Galpão'!$C$20),COUNTIF($M$6:$M15,'Mapa do Galpão'!$C$20),"")
A16: BTG-009 | B16: Eventos | C16: A.01.0776.001.2G | D16: =IF(C16="","",IFERROR(IF(TRIM(MID(SUBSTITUTE(C16,".",REPT(" ",50)),51,50))="01","Masculino",IF(TRIM(MID(SUBSTITUTE(C16,".",REPT(" ",50)),51,50))="02","Feminino",IF(TRIM(MID(SUBSTITUTE(C16,".",REPT(" ",50)),51,50))="03","Outros","—"))),"—")) -> Masculino | E16: CAMISETA | F16: CAMISETA COPA MASC. | G16: AZUL | H16: G | I16: =SUMIFS(Movimentações!$F$6:$F$4998,Movimentações!$C$6:$C$4998,A16,Movimentações!$M$6:$M$4998,M16) -> 0 | J16: ✅ Ótimo | K16: A | L16: 1 | M16: C-03 | N16: =IF(AND(K16="",L16="",M16=""),"⚠ sem endereço","Rua "&K16&IF(L16="",""," · Prat "&L16)&IF(M16="",""," · "&M16)) -> Rua A · Prat 1 · C-03 | P16: =IF(A16="","",IF(AND(K16<>"",L16<>""),IF(COUNTIFS($K$6:K16,K16,$L$6:L16,L16)=1,1,0),0)) -> 0 | Q16: =IF(A16="","",IF(AND(K16<>"",M16<>""),IF(COUNTIFS($K$6:K16,K16,$M$6:M16,M16)=1,1,0),0)) -> 0 | R16: =IF(A16="","",IF(M16<>"",IF(COUNTIF($M$6:M16,M16)=1,1,0),0)) -> 0 | T16: =IF(AND($M16<>"",$M16='Mapa do Galpão'!$C$20),COUNTIF($M$6:$M16,'Mapa do Galpão'!$C$20),"")
A17: BTG-010 | B17: Eventos | C17: A.01.0776.001.3G | D17: =IF(C17="","",IFERROR(IF(TRIM(MID(SUBSTITUTE(C17,".",REPT(" ",50)),51,50))="01","Masculino",IF(TRIM(MID(SUBSTITUTE(C17,".",REPT(" ",50)),51,50))="02","Feminino",IF(TRIM(MID(SUBSTITUTE(C17,".",REPT(" ",50)),51,50))="03","Outros","—"))),"—")) -> Masculino | E17: CAMISETA | F17: CAMISETA COPA MASC. | G17: AZUL | H17: XG | I17: =SUMIFS(Movimentações!$F$6:$F$4998,Movimentações!$C$6:$C$4998,A17,Movimentações!$M$6:$M$4998,M17) -> 0 | J17: ✅ Ótimo | K17: A | L17: 1 | M17: C-03 | N17: =IF(AND(K17="",L17="",M17=""),"⚠ sem endereço","Rua "&K17&IF(L17="",""," · Prat "&L17)&IF(M17="",""," · "&M17)) -> Rua A · Prat 1 · C-03 | P17: =IF(A17="","",IF(AND(K17<>"",L17<>""),IF(COUNTIFS($K$6:K17,K17,$L$6:L17,L17)=1,1,0),0)) -> 0 | Q17: =IF(A17="","",IF(AND(K17<>"",M17<>""),IF(COUNTIFS($K$6:K17,K17,$M$6:M17,M17)=1,1,0),0)) -> 0 | R17: =IF(A17="","",IF(M17<>"",IF(COUNTIF($M$6:M17,M17)=1,1,0),0)) -> 0 | T17: =IF(AND($M17<>"",$M17='Mapa do Galpão'!$C$20),COUNTIF($M$6:$M17,'Mapa do Galpão'!$C$20),"")
... A29: BTG-022 | B29: Eventos | C29: A.01.0784.001.3G | D29: =IF(C29="","",IFERROR(IF(TRIM(MID(SUBSTITUTE(C29,".",REPT(" ",50)),51,50))="01","Masculino",IF(TRIM(MID(SUBSTITUTE(C29,".",REPT(" ",50)),51,50))="02","Feminino",IF(TRIM(MID(SUBSTITUTE(C29,".",REPT(" ",50)),51,50))="03","Outros","—"))),"—")) -> Masculino | E29: CAMISETA | F29: CAMISETA COPA MASC. | G29: ESPORTE | H29: XG | I29: =SUMIFS(Movimentações!$F$6:$F$4998,Movimentações!$C$6:$C$4998,A29,Movimentações!$M$6:$M$4998,M29) -> 0 | J29: ✅ Ótimo | K29: A | L29: 1 | M29: C-05 | N29: =IF(AND(K29="",L29="",M29=""),"⚠ sem endereço","Rua "&K29&IF(L29="",""," · Prat "&L29)&IF(M29="",""," · "&M29)) -> Rua A · Prat 1 · C-05 | P29: =IF(A29="","",IF(AND(K29<>"",L29<>""),IF(COUNTIFS($K$6:K29,K29,$L$6:L29,L29)=1,1,0),0)) -> 0 | Q29: =IF(A29="","",IF(AND(K29<>"",M29<>""),IF(COUNTIFS($K$6:K29,K29,$M$6:M29,M29)=1,1,0),0)) -> 0 | R29: =IF(A29="","",IF(M29<>"",IF(COUNTIF($M$6:M29,M29)=1,1,0),0)) -> 0 | T29: =IF(AND($M29<>"",$M29='Mapa do Galpão'!$C$20),COUNTIF($M$6:$M29,'Mapa do Galpão'!$C$20),"")
A30: BTG-023 | B30: Eventos | C30: A.01.0770.009.P | D30: =IF(C30="","",IFERROR(IF(TRIM(MID(SUBSTITUTE(C30,".",REPT(" ",50)),51,50))="01","Masculino",IF(TRIM(MID(SUBSTITUTE(C30,".",REPT(" ",50)),51,50))="02","Feminino",IF(TRIM(MID(SUBSTITUTE(C30,".",REPT(" ",50)),51,50))="03","Outros","—"))),"—")) -> Masculino | E30: JAQUETA | F30: JAQUETA COPA MASC. | G30: AMARELA | H30: P | I30: =SUMIFS(Movimentações!$F$6:$F$4998,Movimentações!$C$6:$C$4998,A30,Movimentações!$M$6:$M$4998,M30) -> 9 | J30: ✅ Ótimo | K30: A | L30: 14 | M30: C-06 | N30: =IF(AND(K30="",L30="",M30=""),"⚠ sem endereço","Rua "&K30&IF(L30="",""," · Prat "&L30)&IF(M30="",""," · "&M30)) -> Rua A · Prat 14 · C-06 | P30: =IF(A30="","",IF(AND(K30<>"",L30<>""),IF(COUNTIFS($K$6:K30,K30,$L$6:L30,L30)=1,1,0),0)) -> 1 | Q30: =IF(A30="","",IF(AND(K30<>"",M30<>""),IF(COUNTIFS($K$6:K30,K30,$M$6:M30,M30)=1,1,0),0)) -> 1 | R30: =IF(A30="","",IF(M30<>"",IF(COUNTIF($M$6:M30,M30)=1,1,0),0)) -> 1 | T30: =IF(AND($M30<>"",$M30='Mapa do Galpão'!$C$20),COUNTIF($M$6:$M30,'Mapa do Galpão'!$C$20),"")
A31: BTG-024 | B31: Eventos | C31: A.01.0770.009.M | D31: =IF(C31="","",IFERROR(IF(TRIM(MID(SUBSTITUTE(C31,".",REPT(" ",50)),51,50))="01","Masculino",IF(TRIM(MID(SUBSTITUTE(C31,".",REPT(" ",50)),51,50))="02","Feminino",IF(TRIM(MID(SUBSTITUTE(C31,".",REPT(" ",50)),51,50))="03","Outros","—"))),"—")) -> Masculino | E31: JAQUETA | F31: JAQUETA COPA MASC. | G31: AMARELA | H31: M | I31: =SUMIFS(Movimentações!$F$6:$F$4998,Movimentações!$C$6:$C$4998,A31,Movimentações!$M$6:$M$4998,M31) -> 9 | J31: ✅ Ótimo | K31: A | L31: 14 | M31: C-06 | N31: =IF(AND(K31="",L31="",M31=""),"⚠ sem endereço","Rua "&K31&IF(L31="",""," · Prat "&L31)&IF(M31="",""," · "&M31)) -> Rua A · Prat 14 · C-06 | P31: =IF(A31="","",IF(AND(K31<>"",L31<>""),IF(COUNTIFS($K$6:K31,K31,$L$6:L31,L31)=1,1,0),0)) -> 0 | Q31: =IF(A31="","",IF(AND(K31<>"",M31<>""),IF(COUNTIFS($K$6:K31,K31,$M$6:M31,M31)=1,1,0),0)) -> 0 | R31: =IF(A31="","",IF(M31<>"",IF(COUNTIF($M$6:M31,M31)=1,1,0),0)) -> 0 | T31: =IF(AND($M31<>"",$M31='Mapa do Galpão'!$C$20),COUNTIF($M$6:$M31,'Mapa do Galpão'!$C$20),"")
A32: BTG-025 | B32: Eventos | C32: A.01.0770.009.G | D32: =IF(C32="","",IFERROR(IF(TRIM(MID(SUBSTITUTE(C32,".",REPT(" ",50)),51,50))="01","Masculino",IF(TRIM(MID(SUBSTITUTE(C32,".",REPT(" ",50)),51,50))="02","Feminino",IF(TRIM(MID(SUBSTITUTE(C32,".",REPT(" ",50)),51,50))="03","Outros","—"))),"—")) -> Masculino | E32: JAQUETA | F32: JAQUETA COPA MASC. | G32: AMARELA | H32: G | I32: =SUMIFS(Movimentações!$F$6:$F$4998,Movimentações!$C$6:$C$4998,A32,Movimentações!$M$6:$M$4998,M32) -> 4 | J32: ✅ Ótimo | K32: A | L32: 14 | M32: C-06 | N32: =IF(AND(K32="",L32="",M32=""),"⚠ sem endereço","Rua "&K32&IF(L32="",""," · Prat "&L32)&IF(M32="",""," · "&M32)) -> Rua A · Prat 14 · C-06 | P32: =IF(A32="","",IF(AND(K32<>"",L32<>""),IF(COUNTIFS($K$6:K32,K32,$L$6:L32,L32)=1,1,0),0)) -> 0 | Q32: =IF(A32="","",IF(AND(K32<>"",M32<>""),IF(COUNTIFS($K$6:K32,K32,$M$6:M32,M32)=1,1,0),0)) -> 0 | R32: =IF(A32="","",IF(M32<>"",IF(COUNTIF($M$6:M32,M32)=1,1,0),0)) -> 0 | T32: =IF(AND($M32<>"",$M32='Mapa do Galpão'!$C$20),COUNTIF($M$6:$M32,'Mapa do Galpão'!$C$20),"")
A33: BTG-025 | B33: Eventos | C33: A.01.0770.009.G | D33: =IF(C33="","",IFERROR(IF(TRIM(MID(SUBSTITUTE(C33,".",REPT(" ",50)),51,50))="01","Masculino",IF(TRIM(MID(SUBSTITUTE(C33,".",REPT(" ",50)),51,50))="02","Feminino",IF(TRIM(MID(SUBSTITUTE(C33,".",REPT(" ",50)),51,50))="03","Outros","—"))),"—")) -> Masculino | E33: JAQUETA | F33: JAQUETA COPA MASC. | G33: AMARELA | H33: G | I33: =SUMIFS(Movimentações!$F$6:$F$4998,Movimentações!$C$6:$C$4998,A33,Movimentações!$M$6:$M$4998,M33) -> 4 | J33: ✅ Ótimo | K33: A | L33: 16 | M33: C-07 | N33: =IF(AND(K33="",L33="",M33=""),"⚠ sem endereço","Rua "&K33&IF(L33="",""," · Prat "&L33)&IF(M33="",""," · "&M33)) -> Rua A · Prat 16 · C-07 | P33: =IF(A33="","",IF(AND(K33<>"",L33<>""),IF(COUNTIFS($K$6:K33,K33,$L$6:L33,L33)=1,1,0),0)) -> 1 | Q33: =IF(A33="","",IF(AND(K33<>"",M33<>""),IF(COUNTIFS($K$6:K33,K33,$M$6:M33,M33)=1,1,0),0)) -> 1 | R33: =IF(A33="","",IF(M33<>"",IF(COUNTIF($M$6:M33,M33)=1,1,0),0)) -> 1 | T33: =IF(AND($M33<>"",$M33='Mapa do Galpão'!$C$20),COUNTIF($M$6:$M33,'Mapa do Galpão'!$C$20),"")
A34: BTG-026 | B34: Eventos | C34: A.01.0770.009.GG | D34: =IF(C34="","",IFERROR(IF(TRIM(MID(SUBSTITUTE(C34,".",REPT(" ",50)),51,50))="01","Masculino",IF(TRIM(MID(SUBSTITUTE(C34,".",REPT(" ",50)),51,50))="02","Feminino",IF(TRIM(MID(SUBSTITUTE(C34,".",REPT(" ",50)),51,50))="03","Outros","—"))),"—")) -> Masculino | E34: JAQUETA | F34: JAQUETA COPA MASC. | G34: AMARELA | H34: XG | I34: =SUMIFS(Movimentações!$F$6:$F$4998,Movimentações!$C$6:$C$4998,A34,Movimentações!$M$6:$M$4998,M34) -> 17 | J34: ✅ Ótimo | K34: A | L34: 16 | M34: C-07 | N34: =IF(AND(K34="",L34="",M34=""),"⚠ sem endereço","Rua "&K34&IF(L34="",""," · Prat "&L34)&IF(M34="",""," · "&M34)) -> Rua A · Prat 16 · C-07 | P34: =IF(A34="","",IF(AND(K34<>"",L34<>""),IF(COUNTIFS($K$6:K34,K34,$L$6:L34,L34)=1,1,0),0)) -> 0 | Q34: =IF(A34="","",IF(AND(K34<>"",M34<>""),IF(COUNTIFS($K$6:K34,K34,$M$6:M34,M34)=1,1,0),0)) -> 0 | R34: =IF(A34="","",IF(M34<>"",IF(COUNTIF($M$6:M34,M34)=1,1,0),0)) -> 0 | T34: =IF(AND($M34<>"",$M34='Mapa do Galpão'!$C$20),COUNTIF($M$6:$M34,'Mapa do Galpão'!$C$20),"")
A35: BTG-027 | B35: Eventos | C35: A.01.0770.009.XG | D35: =IF(C35="","",IFERROR(IF(TRIM(MID(SUBSTITUTE(C35,".",REPT(" ",50)),51,50))="01","Masculino",IF(TRIM(MID(SUBSTITUTE(C35,".",REPT(" ",50)),51,50))="02","Feminino",IF(TRIM(MID(SUBSTITUTE(C35,".",REPT(" ",50)),51,50))="03","Outros","—"))),"—")) -> Masculino | E35: JAQUETA | F35: JAQUETA COPA MASC. | G35: AMARELA | H35: GG | I35: =SUMIFS(Movimentações!$F$6:$F$4998,Movimentações!$C$6:$C$4998,A35,Movimentações!$M$6:$M$4998,M35) -> 16 | J35: ✅ Ótimo | K35: A | L35: 14 | M35: C-08 | N35: =IF(AND(K35="",L35="",M35=""),"⚠ sem endereço","Rua "&K35&IF(L35="",""," · Prat "&L35)&IF(M35="",""," · "&M35)) -> Rua A · Prat 14 · C-08 | P35: =IF(A35="","",IF(AND(K35<>"",L35<>""),IF(COUNTIFS($K$6:K35,K35,$L$6:L35,L35)=1,1,0),0)) -> 0 | Q35: =IF(A35="","",IF(AND(K35<>"",M35<>""),IF(COUNTIFS($K$6:K35,K35,$M$6:M35,M35)=1,1,0),0)) -> 1 | R35: =IF(A35="","",IF(M35<>"",IF(COUNTIF($M$6:M35,M35)=1,1,0),0)) -> 1 | T35: =IF(AND($M35<>"",$M35='Mapa do Galpão'!$C$20),COUNTIF($M$6:$M35,'Mapa do Galpão'!$C$20),"")
A36: BTG-028 | B36: Eventos | C36: A.01.0768.011.P | D36: =IF(C36="","",IFERROR(IF(TRIM(MID(SUBSTITUTE(C36,".",REPT(" ",50)),51,50))="01","Masculino",IF(TRIM(MID(SUBSTITUTE(C36,".",REPT(" ",50)),51,50))="02","Feminino",IF(TRIM(MID(SUBSTITUTE(C36,".",REPT(" ",50)),51,50))="03","Outros","—"))),"—")) -> Masculino | E36: JAQUETA | F36: JAQUETA COPA MASC. | G36: VERDE | H36: P | I36: =SUMIFS(Movimentações!$F$6:$F$4998,Movimentações!$C$6:$C$4998,A36,Movimentações!$M$6:$M$4998,M36) -> 10 | J36: ✅ Ótimo | K36: A | L36: 14 | M36: C-09 | N36: =IF(AND(K36="",L36="",M36=""),"⚠ sem endereço","Rua "&K36&IF(L36="",""," · Prat "&L36)&IF(M36="",""," · "&M36)) -> Rua A · Prat 14 · C-09 | P36: =IF(A36="","",IF(AND(K36<>"",L36<>""),IF(COUNTIFS($K$6:K36,K36,$L$6:L36,L36)=1,1,0),0)) -> 0 | Q36: =IF(A36="","",IF(AND(K36<>"",M36<>""),IF(COUNTIFS($K$6:K36,K36,$M$6:M36,M36)=1,1,0),0)) -> 1 | R36: =IF(A36="","",IF(M36<>"",IF(COUNTIF($M$6:M36,M36)=1,1,0),0)) -> 1 | T36: =IF(AND($M36<>"",$M36='Mapa do Galpão'!$C$20),COUNTIF($M$6:$M36,'Mapa do Galpão'!$C$20),"")
A37: BTG-029 | B37: Eventos | C37: A.01.0768.011.M | D37: =IF(C37="","",IFERROR(IF(TRIM(MID(SUBSTITUTE(C37,".",REPT(" ",50)),51,50))="01","Masculino",IF(TRIM(MID(SUBSTITUTE(C37,".",REPT(" ",50)),51,50))="02","Feminino",IF(TRIM(MID(SUBSTITUTE(C37,".",REPT(" ",50)),51,50))="03","Outros","—"))),"—")) -> Masculino | E37: JAQUETA | F37: JAQUETA COPA MASC. | G37: VERDE | H37: M | I37: =SUMIFS(Movimentações!$F$6:$F$4998,Movimentações!$C$6:$C$4998,A37,Movimentações!$M$6:$M$4998,M37) -> 10 | J37: ✅ Ótimo | K37: A | L37: 14 | M37: C-09 | N37: =IF(AND(K37="",L37="",M37=""),"⚠ sem endereço","Rua "&K37&IF(L37="",""," · Prat "&L37)&IF(M37="",""," · "&M37)) -> Rua A · Prat 14 · C-09 | P37: =IF(A37="","",IF(AND(K37<>"",L37<>""),IF(COUNTIFS($K$6:K37,K37,$L$6:L37,L37)=1,1,0),0)) -> 0 | Q37: =IF(A37="","",IF(AND(K37<>"",M37<>""),IF(COUNTIFS($K$6:K37,K37,$M$6:M37,M37)=1,1,0),0)) -> 0 | R37: =IF(A37="","",IF(M37<>"",IF(COUNTIF($M$6:M37,M37)=1,1,0),0)) -> 0 | T37: =IF(AND($M37<>"",$M37='Mapa do Galpão'!$C$20),COUNTIF($M$6:$M37,'Mapa do Galpão'!$C$20),"")
A38: BTG-030 | B38: Eventos | C38: A.01.0768.011.G | D38: =IF(C38="","",IFERROR(IF(TRIM(MID(SUBSTITUTE(C38,".",REPT(" ",50)),51,50))="01","Masculino",IF(TRIM(MID(SUBSTITUTE(C38,".",REPT(" ",50)),51,50))="02","Feminino",IF(TRIM(MID(SUBSTITUTE(C38,".",REPT(" ",50)),51,50))="03","Outros","—"))),"—")) -> Masculino | E38: JAQUETA | F38: JAQUETA COPA MASC. | G38: VERDE | H38: G | I38: =SUMIFS(Movimentações!$F$6:$F$4998,Movimentações!$C$6:$C$4998,A38,Movimentações!$M$6:$M$4998,M38) -> 10 | J38: ✅ Ótimo | K38: A | L38: 14 | M38: C-10 | N38: =IF(AND(K38="",L38="",M38=""),"⚠ sem endereço","Rua "&K38&IF(L38="",""," · Prat "&L38)&IF(M38="",""," · "&M38)) -> Rua A · Prat 14 · C-10 | P38: =IF(A38="","",IF(AND(K38<>"",L38<>""),IF(COUNTIFS($K$6:K38,K38,$L$6:L38,L38)=1,1,0),0)) -> 0 | Q38: =IF(A38="","",IF(AND(K38<>"",M38<>""),IF(COUNTIFS($K$6:K38,K38,$M$6:M38,M38)=1,1,0),0)) -> 1 | R38: =IF(A38="","",IF(M38<>"",IF(COUNTIF($M$6:M38,M38)=1,1,0),0)) -> 1 | T38: =IF(AND($M38<>"",$M38='Mapa do Galpão'!$C$20),COUNTIF($M$6:$M38,'Mapa do Galpão'!$C$20),"")
A39: BTG-031 | B39: Eventos | C39: A.01.0768.011.GG | D39: =IF(C39="","",IFERROR(IF(TRIM(MID(SUBSTITUTE(C39,".",REPT(" ",50)),51,50))="01","Masculino",IF(TRIM(MID(SUBSTITUTE(C39,".",REPT(" ",50)),51,50))="02","Feminino",IF(TRIM(MID(SUBSTITUTE(C39,".",REPT(" ",50)),51,50))="03","Outros","—"))),"—")) -> Masculino | E39: JAQUETA | F39: JAQUETA COPA MASC. | G39: VERDE | H39: GG | I39: =SUMIFS(Movimentações!$F$6:$F$4998,Movimentações!$C$6:$C$4998,A39,Movimentações!$M$6:$M$4998,M39) -> 0 | J39: ✅ Ótimo | K39: A | L39: 14 | M39: C-10 | N39: =IF(AND(K39="",L39="",M39=""),"⚠ sem endereço","Rua "&K39&IF(L39="",""," · Prat "&L39)&IF(M39="",""," · "&M39)) -> Rua A · Prat 14 · C-10 | P39: =IF(A39="","",IF(AND(K39<>"",L39<>""),IF(COUNTIFS($K$6:K39,K39,$L$6:L39,L39)=1,1,0),0)) -> 0 | Q39: =IF(A39="","",IF(AND(K39<>"",M39<>""),IF(COUNTIFS($K$6:K39,K39,$M$6:M39,M39)=1,1,0),0)) -> 0 | R39: =IF(A39="","",IF(M39<>"",IF(COUNTIF($M$6:M39,M39)=1,1,0),0)) -> 0 | T39: =IF(AND($M39<>"",$M39='Mapa do Galpão'!$C$20),COUNTIF($M$6:$M39,'Mapa do Galpão'!$C$20),"")
A40: BTG-032 | B40: Eventos | C40: A.01.0768.011.XG | D40: =IF(C40="","",IFERROR(IF(TRIM(MID(SUBSTITUTE(C40,".",REPT(" ",50)),51,50))="01","Masculino",IF(TRIM(MID(SUBSTITUTE(C40,".",REPT(" ",50)),51,50))="02","Feminino",IF(TRIM(MID(SUBSTITUTE(C40,".",REPT(" ",50)),51,50))="03","Outros","—"))),"—")) -> Masculino | E40: JAQUETA | F40: JAQUETA COPA MASC. | G40: VERDE | H40: XG | I40: =SUMIFS(Movimentações!$F$6:$F$4998,Movimentações!$C$6:$C$4998,A40,Movimentações!$M$6:$M$4998,M40) -> 0 | J40: ✅ Ótimo | K40: A | L40: 1 | M40: C-11 | N40: =IF(AND(K40="",L40="",M40=""),"⚠ sem endereço","Rua "&K40&IF(L40="",""," · Prat "&L40)&IF(M40="",""," · "&M40)) -> Rua A · Prat 1 · C-11 | P40: =IF(A40="","",IF(AND(K40<>"",L40<>""),IF(COUNTIFS($K$6:K40,K40,$L$6:L40,L40)=1,1,0),0)) -> 0 | Q40: =IF(A40="","",IF(AND(K40<>"",M40<>""),IF(COUNTIFS($K$6:K40,K40,$M$6:M40,M40)=1,1,0),0)) -> 1 | R40: =IF(A40="","",IF(M40<>"",IF(COUNTIF($M$6:M40,M40)=1,1,0),0)) -> 1 | T40: =IF(AND($M40<>"",$M40='Mapa do Galpão'!$C$20),COUNTIF($M$6:$M40,'Mapa do Galpão'!$C$20),"")
A41: BTG-033 | B41: Eventos | C41: A.01.0772.001.P | D41: =IF(C41="","",IFERROR(IF(TRIM(MID(SUBSTITUTE(C41,".",REPT(" ",50)),51,50))="01","Masculino",IF(TRIM(MID(SUBSTITUTE(C41,".",REPT(" ",50)),51,50))="02","Feminino",IF(TRIM(MID(SUBSTITUTE(C41,".",REPT(" ",50)),51,50))="03","Outros","—"))),"—")) -> Masculino | E41: JAQUETA | F41: JAQUETA COPA MASC. | G41: AZUL | H41: P | I41: =SUMIFS(Movimentações!$F$6:$F$4998,Movimentações!$C$6:$C$4998,A41,Movimentações!$M$6:$M$4998,M41) -> 10 | J41: ✅ Ótimo | K41: A | L41: 13 | M41: C-12 | N41: =IF(AND(K41="",L41="",M41=""),"⚠ sem endereço","Rua "&K41&IF(L41="",""," · Prat "&L41)&IF(M41="",""," · "&M41)) -> Rua A · Prat 13 · C-12 | P41: =IF(A41="","",IF(AND(K41<>"",L41<>""),IF(COUNTIFS($K$6:K41,K41,$L$6:L41,L41)=1,1,0),0)) -> 1 | Q41: =IF(A41="","",IF(AND(K41<>"",M41<>""),IF(COUNTIFS($K$6:K41,K41,$M$6:M41,M41)=1,1,0),0)) -> 1 | R41: =IF(A41="","",IF(M41<>"",IF(COUNTIF($M$6:M41,M41)=1,1,0),0)) -> 1 | T41: =IF(AND($M41<>"",$M41='Mapa do Galpão'!$C$20),COUNTIF($M$6:$M41,'Mapa do Galpão'!$C$20),"")
A42: BTG-034 | B42: Eventos | C42: A.01.0772.001.M | D42: =IF(C42="","",IFERROR(IF(TRIM(MID(SUBSTITUTE(C42,".",REPT(" ",50)),51,50))="01","Masculino",IF(TRIM(MID(SUBSTITUTE(C42,".",REPT(" ",50)),51,50))="02","Feminino",IF(TRIM(MID(SUBSTITUTE(C42,".",REPT(" ",50)),51,50))="03","Outros","—"))),"—")) -> Masculino | E42: JAQUETA | F42: JAQUETA COPA MASC. | G42: AZUL | H42: M | I42: =SUMIFS(Movimentações!$F$6:$F$4998,Movimentações!$C$6:$C$4998,A42,Movimentações!$M$6:$M$4998,M42) -> 10 | J42: ✅ Ótimo | K42: A | L42: 13 | M42: C-12 | N42: =IF(AND(K42="",L42="",M42=""),"⚠ sem endereço","Rua "&K42&IF(L42="",""," · Prat "&L42)&IF(M42="",""," · "&M42)) -> Rua A · Prat 13 · C-12 | P42: =IF(A42="","",IF(AND(K42<>"",L42<>""),IF(COUNTIFS($K$6:K42,K42,$L$6:L42,L42)=1,1,0),0)) -> 0 | Q42: =IF(A42="","",IF(AND(K42<>"",M42<>""),IF(COUNTIFS($K$6:K42,K42,$M$6:M42,M42)=1,1,0),0)) -> 0 | R42: =IF(A42="","",IF(M42<>"",IF(COUNTIF($M$6:M42,M42)=1,1,0),0)) -> 0 | T42: =IF(AND($M42<>"",$M42='Mapa do Galpão'!$C$20),COUNTIF($M$6:$M42,'Mapa do Galpão'!$C$20),"")
A43: BTG-035 | B43: Eventos | C43: A.01.0772.001.G | D43: =IF(C43="","",IFERROR(IF(TRIM(MID(SUBSTITUTE(C43,".",REPT(" ",50)),51,50))="01","Masculino",IF(TRIM(MID(SUBSTITUTE(C43,".",REPT(" ",50)),51,50))="02","Feminino",IF(TRIM(MID(SUBSTITUTE(C43,".",REPT(" ",50)),51,50))="03","Outros","—"))),"—")) -> Masculino | E43: JAQUETA | F43: JAQUETA COPA MASC. | G43: AZUL | H43: G | I43: =SUMIFS(Movimentações!$F$6:$F$4998,Movimentações!$C$6:$C$4998,A43,Movimentações!$M$6:$M$4998,M43) -> 8 | J43: ✅ Ótimo | K43: A | L43: 13 | M43: C-13 | N43: =IF(AND(K43="",L43="",M43=""),"⚠ sem endereço","Rua "&K43&IF(L43="",""," · Prat "&L43)&IF(M43="",""," · "&M43)) -> Rua A · Prat 13 · C-13 | P43: =IF(A43="","",IF(AND(K43<>"",L43<>""),IF(COUNTIFS($K$6:K43,K43,$L$6:L43,L43)=1,1,0),0)) -> 0 | Q43: =IF(A43="","",IF(AND(K43<>"",M43<>""),IF(COUNTIFS($K$6:K43,K43,$M$6:M43,M43)=1,1,0),0)) -> 1 | R43: =IF(A43="","",IF(M43<>"",IF(COUNTIF($M$6:M43,M43)=1,1,0),0)) -> 1 | T43: =IF(AND($M43<>"",$M43='Mapa do Galpão'!$C$20),COUNTIF($M$6:$M43,'Mapa do Galpão'!$C$20),"")
A44: BTG-036 | B44: Eventos | C44: A.01.0772.001.GG | D44: =IF(C44="","",IFERROR(IF(TRIM(MID(SUBSTITUTE(C44,".",REPT(" ",50)),51,50))="01","Masculino",IF(TRIM(MID(SUBSTITUTE(C44,".",REPT(" ",50)),51,50))="02","Feminino",IF(TRIM(MID(SUBSTITUTE(C44,".",REPT(" ",50)),51,50))="03","Outros","—"))),"—")) -> Masculino | E44: JAQUETA | F44: JAQUETA COPA MASC. | G44: AZUL | H44: GG | I44: =SUMIFS(Movimentações!$F$6:$F$4998,Movimentações!$C$6:$C$4998,A44,Movimentações!$M$6:$M$4998,M44) -> 9 | J44: ✅ Ótimo | K44: A | L44: 13 | M44: C-13 | N44: =IF(AND(K44="",L44="",M44=""),"⚠ sem endereço","Rua "&K44&IF(L44="",""," · Prat "&L44)&IF(M44="",""," · "&M44)) -> Rua A · Prat 13 · C-13 | P44: =IF(A44="","",IF(AND(K44<>"",L44<>""),IF(COUNTIFS($K$6:K44,K44,$L$6:L44,L44)=1,1,0),0)) -> 0 | Q44: =IF(A44="","",IF(AND(K44<>"",M44<>""),IF(COUNTIFS($K$6:K44,K44,$M$6:M44,M44)=1,1,0),0)) -> 0 | R44: =IF(A44="","",IF(M44<>"",IF(COUNTIF($M$6:M44,M44)=1,1,0),0)) -> 0 | T44: =IF(AND($M44<>"",$M44='Mapa do Galpão'!$C$20),COUNTIF($M$6:$M44,'Mapa do Galpão'!$C$20),"")
A45: BTG-037 | B45: Eventos | C45: A.01.0772.001.XG | D45: =IF(C45="","",IFERROR(IF(TRIM(MID(SUBSTITUTE(C45,".",REPT(" ",50)),51,50))="01","Masculino",IF(TRIM(MID(SUBSTITUTE(C45,".",REPT(" ",50)),51,50))="02","Feminino",IF(TRIM(MID(SUBSTITUTE(C45,".",REPT(" ",50)),51,50))="03","Outros","—"))),"—")) -> Masculino | E45: JAQUETA | F45: JAQUETA COPA MASC. | G45: AZUL | H45: XG | I45: =SUMIFS(Movimentações!$F$6:$F$4998,Movimentações!$C$6:$C$4998,A45,Movimentações!$M$6:$M$4998,M45) -> 11 | J45: ✅ Ótimo | K45: A | L45: 13 | M45: C-13 | N45: =IF(AND(K45="",L45="",M45=""),"⚠ sem endereço","Rua "&K45&IF(L45="",""," · Prat "&L45)&IF(M45="",""," · "&M45)) -> Rua A · Prat 13 · C-13 | P45: =IF(A45="","",IF(AND(K45<>"",L45<>""),IF(COUNTIFS($K$6:K45,K45,$L$6:L45,L45)=1,1,0),0)) -> 0 | Q45: =IF(A45="","",IF(AND(K45<>"",M45<>""),IF(COUNTIFS($K$6:K45,K45,$M$6:M45,M45)=1,1,0),0)) -> 0 | R45: =IF(A45="","",IF(M45<>"",IF(COUNTIF($M$6:M45,M45)=1,1,0),0)) -> 0 | T45: =IF(AND($M45<>"",$M45='Mapa do Galpão'!$C$20),COUNTIF($M$6:$M45,'Mapa do Galpão'!$C$20),"")
A46: BTG-038 | B46: Eventos | C46: A.01.0766.003.P | D46: =IF(C46="","",IFERROR(IF(TRIM(MID(SUBSTITUTE(C46,".",REPT(" ",50)),51,50))="01","Masculino",IF(TRIM(MID(SUBSTITUTE(C46,".",REPT(" ",50)),51,50))="02","Feminino",IF(TRIM(MID(SUBSTITUTE(C46,".",REPT(" ",50)),51,50))="03","Outros","—"))),"—")) -> Masculino | E46: JAQUETA | F46: JAQUETA COPA MASC. | G46: BRANCA | H46: P | I46: =SUMIFS(Movimentações!$F$6:$F$4998,Movimentações!$C$6:$C$4998,A46,Movimentações!$M$6:$M$4998,M46) -> 9 | J46: ✅ Ótimo | K46: A | L46: 14 | M46: C-14 | N46: =IF(AND(K46="",L46="",M46=""),"⚠ sem endereço","Rua "&K46&IF(L46="",""," · Prat "&L46)&IF(M46="",""," · "&M46)) -> Rua A · Prat 14 · C-14 | P46: =IF(A46="","",IF(AND(K46<>"",L46<>""),IF(COUNTIFS($K$6:K46,K46,$L$6:L46,L46)=1,1,0),0)) -> 0 | Q46: =IF(A46="","",IF(AND(K46<>"",M46<>""),IF(COUNTIFS($K$6:K46,K46,$M$6:M46,M46)=1,1,0),0)) -> 1 | R46: =IF(A46="","",IF(M46<>"",IF(COUNTIF($M$6:M46,M46)=1,1,0),0)) -> 1 | T46: =IF(AND($M46<>"",$M46='Mapa do Galpão'!$C$20),COUNTIF($M$6:$M46,'Mapa do Galpão'!$C$20),"")
A47: BTG-039 | B47: Eventos | C47: A.01.0766.003.M | D47: =IF(C47="","",IFERROR(IF(TRIM(MID(SUBSTITUTE(C47,".",REPT(" ",50)),51,50))="01","Masculino",IF(TRIM(MID(SUBSTITUTE(C47,".",REPT(" ",50)),51,50))="02","Feminino",IF(TRIM(MID(SUBSTITUTE(C47,".",REPT(" ",50)),51,50))="03","Outros","—"))),"—")) -> Masculino | E47: JAQUETA | F47: JAQUETA COPA MASC. | G47: BRANCA | H47: M | I47: =SUMIFS(Movimentações!$F$6:$F$4998,Movimentações!$C$6:$C$4998,A47,Movimentações!$M$6:$M$4998,M47) -> 8 | J47: ✅ Ótimo | K47: A | L47: 14 | M47: C-15 | N47: =IF(AND(K47="",L47="",M47=""),"⚠ sem endereço","Rua "&K47&IF(L47="",""," · Prat "&L47)&IF(M47="",""," · "&M47)) -> Rua A · Prat 14 · C-15 | P47: =IF(A47="","",IF(AND(K47<>"",L47<>""),IF(COUNTIFS($K$6:K47,K47,$L$6:L47,L47)=1,1,0),0)) -> 0 | Q47: =IF(A47="","",IF(AND(K47<>"",M47<>""),IF(COUNTIFS($K$6:K47,K47,$M$6:M47,M47)=1,1,0),0)) -> 1 | R47: =IF(A47="","",IF(M47<>"",IF(COUNTIF($M$6:M47,M47)=1,1,0),0)) -> 1 | T47: =IF(AND($M47<>"",$M47='Mapa do Galpão'!$C$20),COUNTIF($M$6:$M47,'Mapa do Galpão'!$C$20),"")
A48: BTG-040 | B48: Eventos | C48: A.01.0766.003.G | D48: =IF(C48="","",IFERROR(IF(TRIM(MID(SUBSTITUTE(C48,".",REPT(" ",50)),51,50))="01","Masculino",IF(TRIM(MID(SUBSTITUTE(C48,".",REPT(" ",50)),51,50))="02","Feminino",IF(TRIM(MID(SUBSTITUTE(C48,".",REPT(" ",50)),51,50))="03","Outros","—"))),"—")) -> Masculino | E48: JAQUETA | F48: JAQUETA COPA MASC. | G48: BRANCA | H48: G | I48: =SUMIFS(Movimentações!$F$6:$F$4998,Movimentações!$C$6:$C$4998,A48,Movimentações!$M$6:$M$4998,M48) -> 11 | J48: ✅ Ótimo | K48: A | L48: 14 | M48: C-14 | N48: =IF(AND(K48="",L48="",M48=""),"⚠ sem endereço","Rua "&K48&IF(L48="",""," · Prat "&L48)&IF(M48="",""," · "&M48)) -> Rua A · Prat 14 · C-14 | P48: =IF(A48="","",IF(AND(K48<>"",L48<>""),IF(COUNTIFS($K$6:K48,K48,$L$6:L48,L48)=1,1,0),0)) -> 0 | Q48: =IF(A48="","",IF(AND(K48<>"",M48<>""),IF(COUNTIFS($K$6:K48,K48,$M$6:M48,M48)=1,1,0),0)) -> 0 | R48: =IF(A48="","",IF(M48<>"",IF(COUNTIF($M$6:M48,M48)=1,1,0),0)) -> 0 | T48: =IF(AND($M48<>"",$M48='Mapa do Galpão'!$C$20),COUNTIF($M$6:$M48,'Mapa do Galpão'!$C$20),"")
A49: BTG-041 | B49: Eventos | C49: A.01.0766.003.GG | D49: =IF(C49="","",IFERROR(IF(TRIM(MID(SUBSTITUTE(C49,".",REPT(" ",50)),51,50))="01","Masculino",IF(TRIM(MID(SUBSTITUTE(C49,".",REPT(" ",50)),51,50))="02","Feminino",IF(TRIM(MID(SUBSTITUTE(C49,".",REPT(" ",50)),51,50))="03","Outros","—"))),"—")) -> Masculino | E49: JAQUETA | F49: JAQUETA COPA MASC. | G49: BRANCA | H49: GG | I49: =SUMIFS(Movimentações!$F$6:$F$4998,Movimentações!$C$6:$C$4998,A49,Movimentações!$M$6:$M$4998,M49) -> 9 | J49: ✅ Ótimo | K49: A | L49: 14 | M49: C-15 | N49: =IF(AND(K49="",L49="",M49=""),"⚠ sem endereço","Rua "&K49&IF(L49="",""," · Prat "&L49)&IF(M49="",""," · "&M49)) -> Rua A · Prat 14 · C-15 | P49: =IF(A49="","",IF(AND(K49<>"",L49<>""),IF(COUNTIFS($K$6:K49,K49,$L$6:L49,L49)=1,1,0),0)) -> 0 | Q49: =IF(A49="","",IF(AND(K49<>"",M49<>""),IF(COUNTIFS($K$6:K49,K49,$M$6:M49,M49)=1,1,0),0)) -> 0 | R49: =IF(A49="","",IF(M49<>"",IF(COUNTIF($M$6:M49,M49)=1,1,0),0)) -> 0 | T49: =IF(AND($M49<>"",$M49='Mapa do Galpão'!$C$20),COUNTIF($M$6:$M49,'Mapa do Galpão'!$C$20),"")
A50: BTG-042 | B50: Eventos | C50: A.01.0766.003.XG | D50: =IF(C50="","",IFERROR(IF(TRIM(MID(SUBSTITUTE(C50,".",REPT(" ",50)),51,50))="01","Masculino",IF(TRIM(MID(SUBSTITUTE(C50,".",REPT(" ",50)),51,50))="02","Feminino",IF(TRIM(MID(SUBSTITUTE(C50,".",REPT(" ",50)),51,50))="03","Outros","—"))),"—")) -> Masculino | E50: JAQUETA | F50: JAQUETA COPA MASC. | G50: BRANCA | H50: XG | I50: =SUMIFS(Movimentações!$F$6:$F$4998,Movimentações!$C$6:$C$4998,A50,Movimentações!$M$6:$M$4998,M50) -> 8 | J50: ✅ Ótimo | K50: A | L50: 14 | M50: C-15 | N50: =IF(AND(K50="",L50="",M50=""),"⚠ sem endereço","Rua "&K50&IF(L50="",""," · Prat "&L50)&IF(M50="",""," · "&M50)) -> Rua A · Prat 14 · C-15 | P50: =IF(A50="","",IF(AND(K50<>"",L50<>""),IF(COUNTIFS($K$6:K50,K50,$L$6:L50,L50)=1,1,0),0)) -> 0 | Q50: =IF(A50="","",IF(AND(K50<>"",M50<>""),IF(COUNTIFS($K$6:K50,K50,$M$6:M50,M50)=1,1,0),0)) -> 0 | R50: =IF(A50="","",IF(M50<>"",IF(COUNTIF($M$6:M50,M50)=1,1,0),0)) -> 0 | T50: =IF(AND($M50<>"",$M50='Mapa do Galpão'!$C$20),COUNTIF($M$6:$M50,'Mapa do Galpão'!$C$20),"")
A51: BTG-043 | B51: Eventos | C51: A.01.0774.003.P | D51: =IF(C51="","",IFERROR(IF(TRIM(MID(SUBSTITUTE(C51,".",REPT(" ",50)),51,50))="01","Masculino",IF(TRIM(MID(SUBSTITUTE(C51,".",REPT(" ",50)),51,50))="02","Feminino",IF(TRIM(MID(SUBSTITUTE(C51,".",REPT(" ",50)),51,50))="03","Outros","—"))),"—")) -> Masculino | E51: CAMISETA | F51: CAMISETA COPA MASC. | G51: BRANCA | H51: P | I51: =SUMIFS(Movimentações!$F$6:$F$4998,Movimentações!$C$6:$C$4998,A51,Movimentações!$M$6:$M$4998,M51) -> 0 | J51: ✅ Ótimo | K51: A | L51: 5 | M51: C-16 | N51: =IF(AND(K51="",L51="",M51=""),"⚠ sem endereço","Rua "&K51&IF(L51="",""," · Prat "&L51)&IF(M51="",""," · "&M51)) -> Rua A · Prat 5 · C-16 | P51: =IF(A51="","",IF(AND(K51<>"",L51<>""),IF(COUNTIFS($K$6:K51,K51,$L$6:L51,L51)=1,1,0),0)) -> 1 | Q51: =IF(A51="","",IF(AND(K51<>"",M51<>""),IF(COUNTIFS($K$6:K51,K51,$M$6:M51,M51)=1,1,0),0)) -> 1 | R51: =IF(A51="","",IF(M51<>"",IF(COUNTIF($M$6:M51,M51)=1,1,0),0)) -> 1 | T51: =IF(AND($M51<>"",$M51='Mapa do Galpão'!$C$20),COUNTIF($M$6:$M51,'Mapa do Galpão'!$C$20),"")
A52: BTG-043 | B52: Eventos | C52: A.01.0774.003.P | D52: =IF(C52="","",IFERROR(IF(TRIM(MID(SUBSTITUTE(C52,".",REPT(" ",50)),51,50))="01","Masculino",IF(TRIM(MID(SUBSTITUTE(C52,".",REPT(" ",50)),51,50))="02","Feminino",IF(TRIM(MID(SUBSTITUTE(C52,".",REPT(" ",50)),51,50))="03","Outros","—"))),"—")) -> Masculino | E52: CAMISETA | F52: CAMISETA COPA MASC. | G52: BRANCA | H52: P | I52: =SUMIFS(Movimentações!$F$6:$F$4998,Movimentações!$C$6:$C$4998,A52,Movimentações!$M$6:$M$4998,M52) -> 0 | J52: ✅ Ótimo | K52: A | L52: 6 | M52: C-37 | N52: =IF(AND(K52="",L52="",M52=""),"⚠ sem endereço","Rua "&K52&IF(L52="",""," · Prat "&L52)&IF(M52="",""," · "&M52)) -> Rua A · Prat 6 · C-37 | P52: =IF(A52="","",IF(AND(K52<>"",L52<>""),IF(COUNTIFS($K$6:K52,K52,$L$6:L52,L52)=1,1,0),0)) -> 1 | Q52: =IF(A52="","",IF(AND(K52<>"",M52<>""),IF(COUNTIFS($K$6:K52,K52,$M$6:M52,M52)=1,1,0),0)) -> 1 | R52: =IF(A52="","",IF(M52<>"",IF(COUNTIF($M$6:M52,M52)=1,1,0),0)) -> 1 | T52: =IF(AND($M52<>"",$M52='Mapa do Galpão'!$C$20),COUNTIF($M$6:$M52,'Mapa do Galpão'!$C$20),"")
A53: BTG-044 | B53: Eventos | C53: A.01.0774.003.M | D53: =IF(C53="","",IFERROR(IF(TRIM(MID(SUBSTITUTE(C53,".",REPT(" ",50)),51,50))="01","Masculino",IF(TRIM(MID(SUBSTITUTE(C53,".",REPT(" ",50)),51,50))="02","Feminino",IF(TRIM(MID(SUBSTITUTE(C53,".",REPT(" ",50)),51,50))="03","Outros","—"))),"—")) -> Masculino | E53: CAMISETA | F53: CAMISETA COPA MASC. | G53: BRANCA | H53: M | I53: =SUMIFS(Movimentações!$F$6:$F$4998,Movimentações!$C$6:$C$4998,A53,Movimentações!$M$6:$M$4998,M53) -> 0 | J53: ✅ Ótimo | K53: A | L53: 5 | M53: C-16 | N53: =IF(AND(K53="",L53="",M53=""),"⚠ sem endereço","Rua "&K53&IF(L53="",""," · Prat "&L53)&IF(M53="",""," · "&M53)) -> Rua A · Prat 5 · C-16 | P53: =IF(A53="","",IF(AND(K53<>"",L53<>""),IF(COUNTIFS($K$6:K53,K53,$L$6:L53,L53)=1,1,0),0)) -> 0 | Q53: =IF(A53="","",IF(AND(K53<>"",M53<>""),IF(COUNTIFS($K$6:K53,K53,$M$6:M53,M53)=1,1,0),0)) -> 0 | R53: =IF(A53="","",IF(M53<>"",IF(COUNTIF($M$6:M53,M53)=1,1,0),0)) -> 0 | T53: =IF(AND($M53<>"",$M53='Mapa do Galpão'!$C$20),COUNTIF($M$6:$M53,'Mapa do Galpão'!$C$20),"")
A54: BTG-044 | B54: Eventos | C54: A.01.0774.003.M | D54: =IF(C54="","",IFERROR(IF(TRIM(MID(SUBSTITUTE(C54,".",REPT(" ",50)),51,50))="01","Masculino",IF(TRIM(MID(SUBSTITUTE(C54,".",REPT(" ",50)),51,50))="02","Feminino",IF(TRIM(MID(SUBSTITUTE(C54,".",REPT(" ",50)),51,50))="03","Outros","—"))),"—")) -> Masculino | E54: CAMISETA | F54: CAMISETA COPA MASC. | G54: BRANCA | H54: M | I54: =SUMIFS(Movimentações!$F$6:$F$4998,Movimentações!$C$6:$C$4998,A54,Movimentações!$M$6:$M$4998,M54) -> 0 | J54: ✅ Ótimo | K54: A | L54: 6 | M54: C-37 | N54: =IF(AND(K54="",L54="",M54=""),"⚠ sem endereço","Rua "&K54&IF(L54="",""," · Prat "&L54)&IF(M54="",""," · "&M54)) -> Rua A · Prat 6 · C-37 | P54: =IF(A54="","",IF(AND(K54<>"",L54<>""),IF(COUNTIFS($K$6:K54,K54,$L$6:L54,L54)=1,1,0),0)) -> 0 | Q54: =IF(A54="","",IF(AND(K54<>"",M54<>""),IF(COUNTIFS($K$6:K54,K54,$M$6:M54,M54)=1,1,0),0)) -> 0 | R54: =IF(A54="","",IF(M54<>"",IF(COUNTIF($M$6:M54,M54)=1,1,0),0)) -> 0 | T54: =IF(AND($M54<>"",$M54='Mapa do Galpão'!$C$20),COUNTIF($M$6:$M54,'Mapa do Galpão'!$C$20),"")
A55: BTG-045 | B55: Eventos | C55: A.01.0774.003.G | D55: =IF(C55="","",IFERROR(IF(TRIM(MID(SUBSTITUTE(C55,".",REPT(" ",50)),51,50))="01","Masculino",IF(TRIM(MID(SUBSTITUTE(C55,".",REPT(" ",50)),51,50))="02","Feminino",IF(TRIM(MID(SUBSTITUTE(C55,".",REPT(" ",50)),51,50))="03","Outros","—"))),"—")) -> Masculino | E55: CAMISETA | F55: CAMISETA COPA MASC. | G55: BRANCA | H55: G | I55: =SUMIFS(Movimentações!$F$6:$F$4998,Movimentações!$C$6:$C$4998,A55,Movimentações!$M$6:$M$4998,M55) -> 0 | J55: ✅ Ótimo | K55: A | L55: 5 | M55: C-16 | N55: =IF(AND(K55="",L55="",M55=""),"⚠ sem endereço","Rua "&K55&IF(L55="",""," · Prat "&L55)&IF(M55="",""," · "&M55)) -> Rua A · Prat 5 · C-16 | P55: =IF(A55="","",IF(AND(K55<>"",L55<>""),IF(COUNTIFS($K$6:K55,K55,$L$6:L55,L55)=1,1,0),0)) -> 0 | Q55: =IF(A55="","",IF(AND(K55<>"",M55<>""),IF(COUNTIFS($K$6:K55,K55,$M$6:M55,M55)=1,1,0),0)) -> 0 | R55: =IF(A55="","",IF(M55<>"",IF(COUNTIF($M$6:M55,M55)=1,1,0),0)) -> 0 | T55: =IF(AND($M55<>"",$M55='Mapa do Galpão'!$C$20),COUNTIF($M$6:$M55,'Mapa do Galpão'!$C$20),"")
A56: BTG-045 | B56: Eventos | C56: A.01.0774.003.G | D56: =IF(C56="","",IFERROR(IF(TRIM(MID(SUBSTITUTE(C56,".",REPT(" ",50)),51,50))="01","Masculino",IF(TRIM(MID(SUBSTITUTE(C56,".",REPT(" ",50)),51,50))="02","Feminino",IF(TRIM(MID(SUBSTITUTE(C56,".",REPT(" ",50)),51,50))="03","Outros","—"))),"—")) -> Masculino | E56: CAMISETA | F56: CAMISETA COPA MASC. | G56: BRANCA | H56: G | I56: =SUMIFS(Movimentações!$F$6:$F$4998,Movimentações!$C$6:$C$4998,A56,Movimentações!$M$6:$M$4998,M56) -> 0 | J56: ✅ Ótimo | K56: A | L56: 6 | M56: C-37 | N56: =IF(AND(K56="",L56="",M56=""),"⚠ sem endereço","Rua "&K56&IF(L56="",""," · Prat "&L56)&IF(M56="",""," · "&M56)) -> Rua A · Prat 6 · C-37 | P56: =IF(A56="","",IF(AND(K56<>"",L56<>""),IF(COUNTIFS($K$6:K56,K56,$L$6:L56,L56)=1,1,0),0)) -> 0 | Q56: =IF(A56="","",IF(AND(K56<>"",M56<>""),IF(COUNTIFS($K$6:K56,K56,$M$6:M56,M56)=1,1,0),0)) -> 0 | R56: =IF(A56="","",IF(M56<>"",IF(COUNTIF($M$6:M56,M56)=1,1,0),0)) -> 0 | T56: =IF(AND($M56<>"",$M56='Mapa do Galpão'!$C$20),COUNTIF($M$6:$M56,'Mapa do Galpão'!$C$20),"")
A57: BTG-046 | B57: Eventos | C57: A.01.0774.003.2G | D57: =IF(C57="","",IFERROR(IF(TRIM(MID(SUBSTITUTE(C57,".",REPT(" ",50)),51,50))="01","Masculino",IF(TRIM(MID(SUBSTITUTE(C57,".",REPT(" ",50)),51,50))="02","Feminino",IF(TRIM(MID(SUBSTITUTE(C57,".",REPT(" ",50)),51,50))="03","Outros","—"))),"—")) -> Masculino | E57: CAMISETA | F57: CAMISETA COPA MASC. | G57: BRANCA | H57: GG | I57: =SUMIFS(Movimentações!$F$6:$F$4998,Movimentações!$C$6:$C$4998,A57,Movimentações!$M$6:$M$4998,M57) -> 0 | J57: ✅ Ótimo | K57: A | L57: 5 | M57: C-16 | N57: =IF(AND(K57="",L57="",M57=""),"⚠ sem endereço","Rua "&K57&IF(L57="",""," · Prat "&L57)&IF(M57="",""," · "&M57)) -> Rua A · Prat 5 · C-16 | P57: =IF(A57="","",IF(AND(K57<>"",L57<>""),IF(COUNTIFS($K$6:K57,K57,$L$6:L57,L57)=1,1,0),0)) -> 0 | Q57: =IF(A57="","",IF(AND(K57<>"",M57<>""),IF(COUNTIFS($K$6:K57,K57,$M$6:M57,M57)=1,1,0),0)) -> 0 | R57: =IF(A57="","",IF(M57<>"",IF(COUNTIF($M$6:M57,M57)=1,1,0),0)) -> 0 | T57: =IF(AND($M57<>"",$M57='Mapa do Galpão'!$C$20),COUNTIF($M$6:$M57,'Mapa do Galpão'!$C$20),"")
A58: BTG-046 | B58: Eventos | C58: A.01.0774.003.2G | D58: =IF(C58="","",IFERROR(IF(TRIM(MID(SUBSTITUTE(C58,".",REPT(" ",50)),51,50))="01","Masculino",IF(TRIM(MID(SUBSTITUTE(C58,".",REPT(" ",50)),51,50))="02","Feminino",IF(TRIM(MID(SUBSTITUTE(C58,".",REPT(" ",50)),51,50))="03","Outros","—"))),"—")) -> Masculino | E58: CAMISETA | F58: CAMISETA COPA MASC. | G58: BRANCA | H58: GG | I58: =SUMIFS(Movimentações!$F$6:$F$4998,Movimentações!$C$6:$C$4998,A58,Movimentações!$M$6:$M$4998,M58) -> 0 | J58: ✅ Ótimo | K58: A | L58: 6 | M58: C-37 | N58: =IF(AND(K58="",L58="",M58=""),"⚠ sem endereço","Rua "&K58&IF(L58="",""," · Prat "&L58)&IF(M58="",""," · "&M58)) -> Rua A · Prat 6 · C-37 | P58: =IF(A58="","",IF(AND(K58<>"",L58<>""),IF(COUNTIFS($K$6:K58,K58,$L$6:L58,L58)=1,1,0),0)) -> 0 | Q58: =IF(A58="","",IF(AND(K58<>"",M58<>""),IF(COUNTIFS($K$6:K58,K58,$M$6:M58,M58)=1,1,0),0)) -> 0 | R58: =IF(A58="","",IF(M58<>"",IF(COUNTIF($M$6:M58,M58)=1,1,0),0)) -> 0 | T58: =IF(AND($M58<>"",$M58='Mapa do Galpão'!$C$20),COUNTIF($M$6:$M58,'Mapa do Galpão'!$C$20),"")
A59: BTG-047 | B59: Eventos | C59: A.01.0774.003.3G | D59: =IF(C59="","",IFERROR(IF(TRIM(MID(SUBSTITUTE(C59,".",REPT(" ",50)),51,50))="01","Masculino",IF(TRIM(MID(SUBSTITUTE(C59,".",REPT(" ",50)),51,50))="02","Feminino",IF(TRIM(MID(SUBSTITUTE(C59,".",REPT(" ",50)),51,50))="03","Outros","—"))),"—")) -> Masculino | E59: CAMISETA | F59: CAMISETA COPA MASC. | G59: BRANCA | H59: XG | I59: =SUMIFS(Movimentações!$F$6:$F$4998,Movimentações!$C$6:$C$4998,A59,Movimentações!$M$6:$M$4998,M59) -> 0 | J59: ✅ Ótimo | K59: A | L59: 5 | M59: C-16 | N59: =IF(AND(K59="",L59="",M59=""),"⚠ sem endereço","Rua "&K59&IF(L59="",""," · Prat "&L59)&IF(M59="",""," · "&M59)) -> Rua A · Prat 5 · C-16 | P59: =IF(A59="","",IF(AND(K59<>"",L59<>""),IF(COUNTIFS($K$6:K59,K59,$L$6:L59,L59)=1,1,0),0)) -> 0 | Q59: =IF(A59="","",IF(AND(K59<>"",M59<>""),IF(COUNTIFS($K$6:K59,K59,$M$6:M59,M59)=1,1,0),0)) -> 0 | R59: =IF(A59="","",IF(M59<>"",IF(COUNTIF($M$6:M59,M59)=1,1,0),0)) -> 0 | T59: =IF(AND($M59<>"",$M59='Mapa do Galpão'!$C$20),COUNTIF($M$6:$M59,'Mapa do Galpão'!$C$20),"")
A60: BTG-047 | B60: Eventos | C60: A.01.0774.003.3G | D60: =IF(C60="","",IFERROR(IF(TRIM(MID(SUBSTITUTE(C60,".",REPT(" ",50)),51,50))="01","Masculino",IF(TRIM(MID(SUBSTITUTE(C60,".",REPT(" ",50)),51,50))="02","Feminino",IF(TRIM(MID(SUBSTITUTE(C60,".",REPT(" ",50)),51,50))="03","Outros","—"))),"—")) -> Masculino | E60: CAMISETA | F60: CAMISETA COPA MASC. | G60: BRANCA | H60: XG | I60: =SUMIFS(Movimentações!$F$6:$F$4998,Movimentações!$C$6:$C$4998,A60,Movimentações!$M$6:$M$4998,M60) -> 0 | J60: ✅ Ótimo | K60: A | L60: 6 | M60: C-37 | N60: =IF(AND(K60="",L60="",M60=""),"⚠ sem endereço","Rua "&K60&IF(L60="",""," · Prat "&L60)&IF(M60="",""," · "&M60)) -> Rua A · Prat 6 · C-37 | P60: =IF(A60="","",IF(AND(K60<>"",L60<>""),IF(COUNTIFS($K$6:K60,K60,$L$6:L60,L60)=1,1,0),0)) -> 0 | Q60: =IF(A60="","",IF(AND(K60<>"",M60<>""),IF(COUNTIFS($K$6:K60,K60,$M$6:M60,M60)=1,1,0),0)) -> 0 | R60: =IF(A60="","",IF(M60<>"",IF(COUNTIF($M$6:M60,M60)=1,1,0),0)) -> 0 | T60: =IF(AND($M60<>"",$M60='Mapa do Galpão'!$C$20),COUNTIF($M$6:$M60,'Mapa do Galpão'!$C$20),"")
A61: BTG-048 | B61: Eventos | C61: A.01.0774.003.4G | D61: =IF(C61="","",IFERROR(IF(TRIM(MID(SUBSTITUTE(C61,".",REPT(" ",50)),51,50))="01","Masculino",IF(TRIM(MID(SUBSTITUTE(C61,".",REPT(" ",50)),51,50))="02","Feminino",IF(TRIM(MID(SUBSTITUTE(C61,".",REPT(" ",50)),51,50))="03","Outros","—"))),"—")) -> Masculino | E61: CAMISETA | F61: CAMISETA COPA MASC. | G61: BRANCA | H61: 4G | I61: =SUMIFS(Movimentações!$F$6:$F$4998,Movimentações!$C$6:$C$4998,A61,Movimentações!$M$6:$M$4998,M61) -> 0 | J61: ✅ Ótimo | K61: A | L61: 5 | M61: C-16 | N61: =IF(AND(K61="",L61="",M61=""),"⚠ sem endereço","Rua "&K61&IF(L61="",""," · Prat "&L61)&IF(M61="",""," · "&M61)) -> Rua A · Prat 5 · C-16 | P61: =IF(A61="","",IF(AND(K61<>"",L61<>""),IF(COUNTIFS($K$6:K61,K61,$L$6:L61,L61)=1,1,0),0)) -> 0 | Q61: =IF(A61="","",IF(AND(K61<>"",M61<>""),IF(COUNTIFS($K$6:K61,K61,$M$6:M61,M61)=1,1,0),0)) -> 0 | R61: =IF(A61="","",IF(M61<>"",IF(COUNTIF($M$6:M61,M61)=1,1,0),0)) -> 0 | T61: =IF(AND($M61<>"",$M61='Mapa do Galpão'!$C$20),COUNTIF($M$6:$M61,'Mapa do Galpão'!$C$20),"")
A62: BTG-048 | B62: Eventos | C62: A.01.0774.003.4G | D62: =IF(C62="","",IFERROR(IF(TRIM(MID(SUBSTITUTE(C62,".",REPT(" ",50)),51,50))="01","Masculino",IF(TRIM(MID(SUBSTITUTE(C62,".",REPT(" ",50)),51,50))="02","Feminino",IF(TRIM(MID(SUBSTITUTE(C62,".",REPT(" ",50)),51,50))="03","Outros","—"))),"—")) -> Masculino | E62: CAMISETA | F62: CAMISETA COPA MASC. | G62: BRANCA | H62: 4G | I62: =SUMIFS(Movimentações!$F$6:$F$4998,Movimentações!$C$6:$C$4998,A62,Movimentações!$M$6:$M$4998,M62) -> 0 | J62: ✅ Ótimo | K62: A | L62: 6 | M62: C-37 | N62: =IF(AND(K62="",L62="",M62=""),"⚠ sem endereço","Rua "&K62&IF(L62="",""," · Prat "&L62)&IF(M62="",""," · "&M62)) -> Rua A · Prat 6 · C-37 | P62: =IF(A62="","",IF(AND(K62<>"",L62<>""),IF(COUNTIFS($K$6:K62,K62,$L$6:L62,L62)=1,1,0),0)) -> 0 | Q62: =IF(A62="","",IF(AND(K62<>"",M62<>""),IF(COUNTIFS($K$6:K62,K62,$M$6:M62,M62)=1,1,0),0)) -> 0 | R62: =IF(A62="","",IF(M62<>"",IF(COUNTIF($M$6:M62,M62)=1,1,0),0)) -> 0 | T62: =IF(AND($M62<>"",$M62='Mapa do Galpão'!$C$20),COUNTIF($M$6:$M62,'Mapa do Galpão'!$C$20),"")
A63: BTG-049 | B63: Eventos | C63: A.01.0709.004.PP | D63: =IF(C63="","",IFERROR(IF(TRIM(MID(SUBSTITUTE(C63,".",REPT(" ",50)),51,50))="01","Masculino",IF(TRIM(MID(SUBSTITUTE(C63,".",REPT(" ",50)),51,50))="02","Feminino",IF(TRIM(MID(SUBSTITUTE(C63,".",REPT(" ",50)),51,50))="03","Outros","—"))),"—")) -> Masculino | E63: POLO | F63: POLO PIQUET MASC. | G63: CINZA | H63: PP | I63: =SUMIFS(Movimentações!$F$6:$F$4998,Movimentações!$C$6:$C$4998,A63,Movimentações!$M$6:$M$4998,M63) -> 0 | J63: ✅ Ótimo | K63: A | L63: 15 | M63: C-17 | N63: =IF(AND(K63="",L63="",M63=""),"⚠ sem endereço","Rua "&K63&IF(L63="",""," · Prat "&L63)&IF(M63="",""," · "&M63)) -> Rua A · Prat 15 · C-17 | P63: =IF(A63="","",IF(AND(K63<>"",L63<>""),IF(COUNTIFS($K$6:K63,K63,$L$6:L63,L63)=1,1,0),0)) -> 1 | Q63: =IF(A63="","",IF(AND(K63<>"",M63<>""),IF(COUNTIFS($K$6:K63,K63,$M$6:M63,M63)=1,1,0),0)) -> 1 | R63: =IF(A63="","",IF(M63<>"",IF(COUNTIF($M$6:M63,M63)=1,1,0),0)) -> 1 | T63: =IF(AND($M63<>"",$M63='Mapa do Galpão'!$C$20),COUNTIF($M$6:$M63,'Mapa do Galpão'!$C$20),"")
A64: BTG-050 | B64: Eventos | C64: A.01.0709.004.P | D64: =IF(C64="","",IFERROR(IF(TRIM(MID(SUBSTITUTE(C64,".",REPT(" ",50)),51,50))="01","Masculino",IF(TRIM(MID(SUBSTITUTE(C64,".",REPT(" ",50)),51,50))="02","Feminino",IF(TRIM(MID(SUBSTITUTE(C64,".",REPT(" ",50)),51,50))="03","Outros","—"))),"—")) -> Masculino | E64: POLO | F64: POLO PIQUET MASC. | G64: CINZA | H64: P | I64: =SUMIFS(Movimentações!$F$6:$F$4998,Movimentações!$C$6:$C$4998,A64,Movimentações!$M$6:$M$4998,M64) -> 8 | J64: ✅ Ótimo | K64: A | L64: 12 | M64: C-18 | N64: =IF(AND(K64="",L64="",M64=""),"⚠ sem endereço","Rua "&K64&IF(L64="",""," · Prat "&L64)&IF(M64="",""," · "&M64)) -> Rua A · Prat 12 · C-18 | P64: =IF(A64="","",IF(AND(K64<>"",L64<>""),IF(COUNTIFS($K$6:K64,K64,$L$6:L64,L64)=1,1,0),0)) -> 1 | Q64: =IF(A64="","",IF(AND(K64<>"",M64<>""),IF(COUNTIFS($K$6:K64,K64,$M$6:M64,M64)=1,1,0),0)) -> 1 | R64: =IF(A64="","",IF(M64<>"",IF(COUNTIF($M$6:M64,M64)=1,1,0),0)) -> 1 | T64: =IF(AND($M64<>"",$M64='Mapa do Galpão'!$C$20),COUNTIF($M$6:$M64,'Mapa do Galpão'!$C$20),"")
A65: BTG-051 | B65: Eventos | C65: A.01.0709.004.M | D65: =IF(C65="","",IFERROR(IF(TRIM(MID(SUBSTITUTE(C65,".",REPT(" ",50)),51,50))="01","Masculino",IF(TRIM(MID(SUBSTITUTE(C65,".",REPT(" ",50)),51,50))="02","Feminino",IF(TRIM(MID(SUBSTITUTE(C65,".",REPT(" ",50)),51,50))="03","Outros","—"))),"—")) -> Masculino | E65: POLO | F65: POLO PIQUET MASC. | G65: CINZA | H65: M | I65: =SUMIFS(Movimentações!$F$6:$F$4998,Movimentações!$C$6:$C$4998,A65,Movimentações!$M$6:$M$4998,M65) -> 26 | J65: ✅ Ótimo | K65: A | L65: 12 | M65: C-18 | N65: =IF(AND(K65="",L65="",M65=""),"⚠ sem endereço","Rua "&K65&IF(L65="",""," · Prat "&L65)&IF(M65="",""," · "&M65)) -> Rua A · Prat 12 · C-18 | P65: =IF(A65="","",IF(AND(K65<>"",L65<>""),IF(COUNTIFS($K$6:K65,K65,$L$6:L65,L65)=1,1,0),0)) -> 0 | Q65: =IF(A65="","",IF(AND(K65<>"",M65<>""),IF(COUNTIFS($K$6:K65,K65,$M$6:M65,M65)=1,1,0),0)) -> 0 | R65: =IF(A65="","",IF(M65<>"",IF(COUNTIF($M$6:M65,M65)=1,1,0),0)) -> 0 | T65: =IF(AND($M65<>"",$M65='Mapa do Galpão'!$C$20),COUNTIF($M$6:$M65,'Mapa do Galpão'!$C$20),"")
A66: BTG-052 | B66: Eventos | C66: A.01.0709.004.G | D66: =IF(C66="","",IFERROR(IF(TRIM(MID(SUBSTITUTE(C66,".",REPT(" ",50)),51,50))="01","Masculino",IF(TRIM(MID(SUBSTITUTE(C66,".",REPT(" ",50)),51,50))="02","Feminino",IF(TRIM(MID(SUBSTITUTE(C66,".",REPT(" ",50)),51,50))="03","Outros","—"))),"—")) -> Masculino | E66: POLO | F66: POLO PIQUET MASC. | G66: CINZA | H66: G | I66: =SUMIFS(Movimentações!$F$6:$F$4998,Movimentações!$C$6:$C$4998,A66,Movimentações!$M$6:$M$4998,M66) -> 29 | J66: ✅ Ótimo | K66: A | L66: 15 | M66: C-17 | N66: =IF(AND(K66="",L66="",M66=""),"⚠ sem endereço","Rua "&K66&IF(L66="",""," · Prat "&L66)&IF(M66="",""," · "&M66)) -> Rua A · Prat 15 · C-17 | P66: =IF(A66="","",IF(AND(K66<>"",L66<>""),IF(COUNTIFS($K$6:K66,K66,$L$6:L66,L66)=1,1,0),0)) -> 0 | Q66: =IF(A66="","",IF(AND(K66<>"",M66<>""),IF(COUNTIFS($K$6:K66,K66,$M$6:M66,M66)=1,1,0),0)) -> 0 | R66: =IF(A66="","",IF(M66<>"",IF(COUNTIF($M$6:M66,M66)=1,1,0),0)) -> 0 | T66: =IF(AND($M66<>"",$M66='Mapa do Galpão'!$C$20),COUNTIF($M$6:$M66,'Mapa do Galpão'!$C$20),"")
A67: BTG-053 | B67: Eventos | C67: A.01.0709.004.GG | D67: =IF(C67="","",IFERROR(IF(TRIM(MID(SUBSTITUTE(C67,".",REPT(" ",50)),51,50))="01","Masculino",IF(TRIM(MID(SUBSTITUTE(C67,".",REPT(" ",50)),51,50))="02","Feminino",IF(TRIM(MID(SUBSTITUTE(C67,".",REPT(" ",50)),51,50))="03","Outros","—"))),"—")) -> Masculino | E67: POLO | F67: POLO PIQUET MASC. | G67: CINZA | H67: GG | I67: =SUMIFS(Movimentações!$F$6:$F$4998,Movimentações!$C$6:$C$4998,A67,Movimentações!$M$6:$M$4998,M67) -> 0 | J67: ✅ Ótimo | K67: A | L67: 12 | M67: C-18 | N67: =IF(AND(K67="",L67="",M67=""),"⚠ sem endereço","Rua "&K67&IF(L67="",""," · Prat "&L67)&IF(M67="",""," · "&M67)) -> Rua A · Prat 12 · C-18 | P67: =IF(A67="","",IF(AND(K67<>"",L67<>""),IF(COUNTIFS($K$6:K67,K67,$L$6:L67,L67)=1,1,0),0)) -> 0 | Q67: =IF(A67="","",IF(AND(K67<>"",M67<>""),IF(COUNTIFS($K$6:K67,K67,$M$6:M67,M67)=1,1,0),0)) -> 0 | R67: =IF(A67="","",IF(M67<>"",IF(COUNTIF($M$6:M67,M67)=1,1,0),0)) -> 0 | T67: =IF(AND($M67<>"",$M67='Mapa do Galpão'!$C$20),COUNTIF($M$6:$M67,'Mapa do Galpão'!$C$20),"")
A68: BTG-054 | B68: Eventos | C68: A.01.0709.004.XG | D68: =IF(C68="","",IFERROR(IF(TRIM(MID(SUBSTITUTE(C68,".",REPT(" ",50)),51,50))="01","Masculino",IF(TRIM(MID(SUBSTITUTE(C68,".",REPT(" ",50)),51,50))="02","Feminino",IF(TRIM(MID(SUBSTITUTE(C68,".",REPT(" ",50)),51,50))="03","Outros","—"))),"—")) -> Masculino | E68: POLO | F68: POLO PIQUET MASC. | G68: CINZA | H68: XG | I68: =SUMIFS(Movimentações!$F$6:$F$4998,Movimentações!$C$6:$C$4998,A68,Movimentações!$M$6:$M$4998,M68) -> 0 | J68: ✅ Ótimo | K68: A | L68: 12 | M68: C-18 | N68: =IF(AND(K68="",L68="",M68=""),"⚠ sem endereço","Rua "&K68&IF(L68="",""," · Prat "&L68)&IF(M68="",""," · "&M68)) -> Rua A · Prat 12 · C-18 | P68: =IF(A68="","",IF(AND(K68<>"",L68<>""),IF(COUNTIFS($K$6:K68,K68,$L$6:L68,L68)=1,1,0),0)) -> 0 | Q68: =IF(A68="","",IF(AND(K68<>"",M68<>""),IF(COUNTIFS($K$6:K68,K68,$M$6:M68,M68)=1,1,0),0)) -> 0 | R68: =IF(A68="","",IF(M68<>"",IF(COUNTIF($M$6:M68,M68)=1,1,0),0)) -> 0 | T68: =IF(AND($M68<>"",$M68='Mapa do Galpão'!$C$20),COUNTIF($M$6:$M68,'Mapa do Galpão'!$C$20),"")
A69: BTG-055 | B69: Eventos | C69: A.01.0703.002.PP | D69: =IF(C69="","",IFERROR(IF(TRIM(MID(SUBSTITUTE(C69,".",REPT(" ",50)),51,50))="01","Masculino",IF(TRIM(MID(SUBSTITUTE(C69,".",REPT(" ",50)),51,50))="02","Feminino",IF(TRIM(MID(SUBSTITUTE(C69,".",REPT(" ",50)),51,50))="03","Outros","—"))),"—")) -> Masculino | E69: POLO | F69: POLO PIQUET MASC. | G69: MARINHO-RISCOS | H69: PP | I69: =SUMIFS(Movimentações!$F$6:$F$4998,Movimentações!$C$6:$C$4998,A69,Movimentações!$M$6:$M$4998,M69) -> 0 | J69: ✅ Ótimo | K69: A | L69: 12 | M69: C-19 | N69: =IF(AND(K69="",L69="",M69=""),"⚠ sem endereço","Rua "&K69&IF(L69="",""," · Prat "&L69)&IF(M69="",""," · "&M69)) -> Rua A · Prat 12 · C-19 | P69: =IF(A69="","",IF(AND(K69<>"",L69<>""),IF(COUNTIFS($K$6:K69,K69,$L$6:L69,L69)=1,1,0),0)) -> 0 | Q69: =IF(A69="","",IF(AND(K69<>"",M69<>""),IF(COUNTIFS($K$6:K69,K69,$M$6:M69,M69)=1,1,0),0)) -> 1 | R69: =IF(A69="","",IF(M69<>"",IF(COUNTIF($M$6:M69,M69)=1,1,0),0)) -> 1 | T69: =IF(AND($M69<>"",$M69='Mapa do Galpão'!$C$20),COUNTIF($M$6:$M69,'Mapa do Galpão'!$C$20),"")
A70: BTG-056 | B70: Eventos | C70: A.01.0703.002.P | D70: =IF(C70="","",IFERROR(IF(TRIM(MID(SUBSTITUTE(C70,".",REPT(" ",50)),51,50))="01","Masculino",IF(TRIM(MID(SUBSTITUTE(C70,".",REPT(" ",50)),51,50))="02","Feminino",IF(TRIM(MID(SUBSTITUTE(C70,".",REPT(" ",50)),51,50))="03","Outros","—"))),"—")) -> Masculino | E70: POLO | F70: POLO PIQUET MASC. | G70: MARINHO-RISCOS | H70: P | I70: =SUMIFS(Movimentações!$F$6:$F$4998,Movimentações!$C$6:$C$4998,A70,Movimentações!$M$6:$M$4998,M70) -> 7 | J70: ✅ Ótimo | K70: A | L70: 12 | M70: C-19 | N70: =IF(AND(K70="",L70="",M70=""),"⚠ sem endereço","Rua "&K70&IF(L70="",""," · Prat "&L70)&IF(M70="",""," · "&M70)) -> Rua A · Prat 12 · C-19 | P70: =IF(A70="","",IF(AND(K70<>"",L70<>""),IF(COUNTIFS($K$6:K70,K70,$L$6:L70,L70)=1,1,0),0)) -> 0 | Q70: =IF(A70="","",IF(AND(K70<>"",M70<>""),IF(COUNTIFS($K$6:K70,K70,$M$6:M70,M70)=1,1,0),0)) -> 0 | R70: =IF(A70="","",IF(M70<>"",IF(COUNTIF($M$6:M70,M70)=1,1,0),0)) -> 0 | T70: =IF(AND($M70<>"",$M70='Mapa do Galpão'!$C$20),COUNTIF($M$6:$M70,'Mapa do Galpão'!$C$20),"")
A71: BTG-057 | B71: Eventos | C71: A.01.0703.002.M | D71: =IF(C71="","",IFERROR(IF(TRIM(MID(SUBSTITUTE(C71,".",REPT(" ",50)),51,50))="01","Masculino",IF(TRIM(MID(SUBSTITUTE(C71,".",REPT(" ",50)),51,50))="02","Feminino",IF(TRIM(MID(SUBSTITUTE(C71,".",REPT(" ",50)),51,50))="03","Outros","—"))),"—")) -> Masculino | E71: POLO | F71: POLO PIQUET MASC. | G71: MARINHO-RISCOS | H71: M | I71: =SUMIFS(Movimentações!$F$6:$F$4998,Movimentações!$C$6:$C$4998,A71,Movimentações!$M$6:$M$4998,M71) -> 23 | J71: ✅ Ótimo | K71: A | L71: 12 | M71: C-19 | N71: =IF(AND(K71="",L71="",M71=""),"⚠ sem endereço","Rua "&K71&IF(L71="",""," · Prat "&L71)&IF(M71="",""," · "&M71)) -> Rua A · Prat 12 · C-19 | P71: =IF(A71="","",IF(AND(K71<>"",L71<>""),IF(COUNTIFS($K$6:K71,K71,$L$6:L71,L71)=1,1,0),0)) -> 0 | Q71: =IF(A71="","",IF(AND(K71<>"",M71<>""),IF(COUNTIFS($K$6:K71,K71,$M$6:M71,M71)=1,1,0),0)) -> 0 | R71: =IF(A71="","",IF(M71<>"",IF(COUNTIF($M$6:M71,M71)=1,1,0),0)) -> 0 | T71: =IF(AND($M71<>"",$M71='Mapa do Galpão'!$C$20),COUNTIF($M$6:$M71,'Mapa do Galpão'!$C$20),"")
A72: BTG-058 | B72: Eventos | C72: A.01.0703.002.G | D72: =IF(C72="","",IFERROR(IF(TRIM(MID(SUBSTITUTE(C72,".",REPT(" ",50)),51,50))="01","Masculino",IF(TRIM(MID(SUBSTITUTE(C72,".",REPT(" ",50)),51,50))="02","Feminino",IF(TRIM(MID(SUBSTITUTE(C72,".",REPT(" ",50)),51,50))="03","Outros","—"))),"—")) -> Masculino | E72: POLO | F72: POLO PIQUET MASC. | G72: MARINHO-RISCOS | H72: G | I72: =SUMIFS(Movimentações!$F$6:$F$4998,Movimentações!$C$6:$C$4998,A72,Movimentações!$M$6:$M$4998,M72) -> 18 | J72: ✅ Ótimo | K72: A | L72: 12 | M72: C-19 | N72: =IF(AND(K72="",L72="",M72=""),"⚠ sem endereço","Rua "&K72&IF(L72="",""," · Prat "&L72)&IF(M72="",""," · "&M72)) -> Rua A · Prat 12 · C-19 | P72: =IF(A72="","",IF(AND(K72<>"",L72<>""),IF(COUNTIFS($K$6:K72,K72,$L$6:L72,L72)=1,1,0),0)) -> 0 | Q72: =IF(A72="","",IF(AND(K72<>"",M72<>""),IF(COUNTIFS($K$6:K72,K72,$M$6:M72,M72)=1,1,0),0)) -> 0 | R72: =IF(A72="","",IF(M72<>"",IF(COUNTIF($M$6:M72,M72)=1,1,0),0)) -> 0 | T72: =IF(AND($M72<>"",$M72='Mapa do Galpão'!$C$20),COUNTIF($M$6:$M72,'Mapa do Galpão'!$C$20),"")
A73: BTG-059 | B73: Eventos | C73: A.01.0703.002.GG | D73: =IF(C73="","",IFERROR(IF(TRIM(MID(SUBSTITUTE(C73,".",REPT(" ",50)),51,50))="01","Masculino",IF(TRIM(MID(SUBSTITUTE(C73,".",REPT(" ",50)),51,50))="02","Feminino",IF(TRIM(MID(SUBSTITUTE(C73,".",REPT(" ",50)),51,50))="03","Outros","—"))),"—")) -> Masculino | E73: POLO | F73: POLO PIQUET MASC. | G73: MARINHO-RISCOS | H73: GG | I73: =SUMIFS(Movimentações!$F$6:$F$4998,Movimentações!$C$6:$C$4998,A73,Movimentações!$M$6:$M$4998,M73) -> 0 | J73: ✅ Ótimo | K73: A | L73: 12 | M73: C-19 | N73: =IF(AND(K73="",L73="",M73=""),"⚠ sem endereço","Rua "&K73&IF(L73="",""," · Prat "&L73)&IF(M73="",""," · "&M73)) -> Rua A · Prat 12 · C-19 | P73: =IF(A73="","",IF(AND(K73<>"",L73<>""),IF(COUNTIFS($K$6:K73,K73,$L$6:L73,L73)=1,1,0),0)) -> 0 | Q73: =IF(A73="","",IF(AND(K73<>"",M73<>""),IF(COUNTIFS($K$6:K73,K73,$M$6:M73,M73)=1,1,0),0)) -> 0 | R73: =IF(A73="","",IF(M73<>"",IF(COUNTIF($M$6:M73,M73)=1,1,0),0)) -> 0 | T73: =IF(AND($M73<>"",$M73='Mapa do Galpão'!$C$20),COUNTIF($M$6:$M73,'Mapa do Galpão'!$C$20),"")
A74: BTG-060 | B74: Eventos | C74: A.01.0703.002.XG | D74: =IF(C74="","",IFERROR(IF(TRIM(MID(SUBSTITUTE(C74,".",REPT(" ",50)),51,50))="01","Masculino",IF(TRIM(MID(SUBSTITUTE(C74,".",REPT(" ",50)),51,50))="02","Feminino",IF(TRIM(MID(SUBSTITUTE(C74,".",REPT(" ",50)),51,50))="03","Outros","—"))),"—")) -> Masculino | E74: POLO | F74: POLO PIQUET MASC. | G74: MARINHO-RISCOS | H74: XG | I74: =SUMIFS(Movimentações!$F$6:$F$4998,Movimentações!$C$6:$C$4998,A74,Movimentações!$M$6:$M$4998,M74) -> 0 | J74: ✅ Ótimo | K74: A | L74: 12 | M74: C-19 | N74: =IF(AND(K74="",L74="",M74=""),"⚠ sem endereço","Rua "&K74&IF(L74="",""," · Prat "&L74)&IF(M74="",""," · "&M74)) -> Rua A · Prat 12 · C-19 | P74: =IF(A74="","",IF(AND(K74<>"",L74<>""),IF(COUNTIFS($K$6:K74,K74,$L$6:L74,L74)=1,1,0),0)) -> 0 | Q74: =IF(A74="","",IF(AND(K74<>"",M74<>""),IF(COUNTIFS($K$6:K74,K74,$M$6:M74,M74)=1,1,0),0)) -> 0 | R74: =IF(A74="","",IF(M74<>"",IF(COUNTIF($M$6:M74,M74)=1,1,0),0)) -> 0 | T74: =IF(AND($M74<>"",$M74='Mapa do Galpão'!$C$20),COUNTIF($M$6:$M74,'Mapa do Galpão'!$C$20),"")
A75: BTG-061 | B75: Eventos | C75: A.01.0711.004.PP | D75: =IF(C75="","",IFERROR(IF(TRIM(MID(SUBSTITUTE(C75,".",REPT(" ",50)),51,50))="01","Masculino",IF(TRIM(MID(SUBSTITUTE(C75,".",REPT(" ",50)),51,50))="02","Feminino",IF(TRIM(MID(SUBSTITUTE(C75,".",REPT(" ",50)),51,50))="03","Outros","—"))),"—")) -> Masculino | E75: POLO | F75: POLO PIQUET MASC. | G75: BRANCA | H75: PP | I75: =SUMIFS(Movimentações!$F$6:$F$4998,Movimentações!$C$6:$C$4998,A75,Movimentações!$M$6:$M$4998,M75) -> 0 | J75: ✅ Ótimo | K75: A | L75: 5 | M75: C-20 | N75: =IF(AND(K75="",L75="",M75=""),"⚠ sem endereço","Rua "&K75&IF(L75="",""," · Prat "&L75)&IF(M75="",""," · "&M75)) -> Rua A · Prat 5 · C-20 | P75: =IF(A75="","",IF(AND(K75<>"",L75<>""),IF(COUNTIFS($K$6:K75,K75,$L$6:L75,L75)=1,1,0),0)) -> 0 | Q75: =IF(A75="","",IF(AND(K75<>"",M75<>""),IF(COUNTIFS($K$6:K75,K75,$M$6:M75,M75)=1,1,0),0)) -> 1 | R75: =IF(A75="","",IF(M75<>"",IF(COUNTIF($M$6:M75,M75)=1,1,0),0)) -> 1 | T75: =IF(AND($M75<>"",$M75='Mapa do Galpão'!$C$20),COUNTIF($M$6:$M75,'Mapa do Galpão'!$C$20),"")
A76: BTG-062 | B76: Eventos | C76: A.01.0711.004.P | D76: =IF(C76="","",IFERROR(IF(TRIM(MID(SUBSTITUTE(C76,".",REPT(" ",50)),51,50))="01","Masculino",IF(TRIM(MID(SUBSTITUTE(C76,".",REPT(" ",50)),51,50))="02","Feminino",IF(TRIM(MID(SUBSTITUTE(C76,".",REPT(" ",50)),51,50))="03","Outros","—"))),"—")) -> Masculino | E76: POLO | F76: POLO PIQUET MASC. | G76: BRANCA | H76: P | I76: =SUMIFS(Movimentações!$F$6:$F$4998,Movimentações!$C$6:$C$4998,A76,Movimentações!$M$6:$M$4998,M76) -> 0 | J76: ✅ Ótimo | K76: A | L76: 5 | M76: C-20 | N76: =IF(AND(K76="",L76="",M76=""),"⚠ sem endereço","Rua "&K76&IF(L76="",""," · Prat "&L76)&IF(M76="",""," · "&M76)) -> Rua A · Prat 5 · C-20 | P76: =IF(A76="","",IF(AND(K76<>"",L76<>""),IF(COUNTIFS($K$6:K76,K76,$L$6:L76,L76)=1,1,0),0)) -> 0 | Q76: =IF(A76="","",IF(AND(K76<>"",M76<>""),IF(COUNTIFS($K$6:K76,K76,$M$6:M76,M76)=1,1,0),0)) -> 0 | R76: =IF(A76="","",IF(M76<>"",IF(COUNTIF($M$6:M76,M76)=1,1,0),0)) -> 0 | T76: =IF(AND($M76<>"",$M76='Mapa do Galpão'!$C$20),COUNTIF($M$6:$M76,'Mapa do Galpão'!$C$20),"")
A77: BTG-063 | B77: Eventos | C77: A.01.0711.004.M | D77: =IF(C77="","",IFERROR(IF(TRIM(MID(SUBSTITUTE(C77,".",REPT(" ",50)),51,50))="01","Masculino",IF(TRIM(MID(SUBSTITUTE(C77,".",REPT(" ",50)),51,50))="02","Feminino",IF(TRIM(MID(SUBSTITUTE(C77,".",REPT(" ",50)),51,50))="03","Outros","—"))),"—")) -> Masculino | E77: POLO | F77: POLO PIQUET MASC. | G77: BRANCA | H77: M | I77: =SUMIFS(Movimentações!$F$6:$F$4998,Movimentações!$C$6:$C$4998,A77,Movimentações!$M$6:$M$4998,M77) -> 0 | J77: ✅ Ótimo | K77: A | L77: 5 | M77: C-20 | N77: =IF(AND(K77="",L77="",M77=""),"⚠ sem endereço","Rua "&K77&IF(L77="",""," · Prat "&L77)&IF(M77="",""," · "&M77)) -> Rua A · Prat 5 · C-20 | P77: =IF(A77="","",IF(AND(K77<>"",L77<>""),IF(COUNTIFS($K$6:K77,K77,$L$6:L77,L77)=1,1,0),0)) -> 0 | Q77: =IF(A77="","",IF(AND(K77<>"",M77<>""),IF(COUNTIFS($K$6:K77,K77,$M$6:M77,M77)=1,1,0),0)) -> 0 | R77: =IF(A77="","",IF(M77<>"",IF(COUNTIF($M$6:M77,M77)=1,1,0),0)) -> 0 | T77: =IF(AND($M77<>"",$M77='Mapa do Galpão'!$C$20),COUNTIF($M$6:$M77,'Mapa do Galpão'!$C$20),"")
A78: BTG-064 | B78: Eventos | C78: A.01.0711.004.G | D78: =IF(C78="","",IFERROR(IF(TRIM(MID(SUBSTITUTE(C78,".",REPT(" ",50)),51,50))="01","Masculino",IF(TRIM(MID(SUBSTITUTE(C78,".",REPT(" ",50)),51,50))="02","Feminino",IF(TRIM(MID(SUBSTITUTE(C78,".",REPT(" ",50)),51,50))="03","Outros","—"))),"—")) -> Masculino | E78: POLO | F78: POLO PIQUET MASC. | G78: BRANCA | H78: G | I78: =SUMIFS(Movimentações!$F$6:$F$4998,Movimentações!$C$6:$C$4998,A78,Movimentações!$M$6:$M$4998,M78) -> 0 | J78: ✅ Ótimo | K78: A | L78: 5 | M78: C-20 | N78: =IF(AND(K78="",L78="",M78=""),"⚠ sem endereço","Rua "&K78&IF(L78="",""," · Prat "&L78)&IF(M78="",""," · "&M78)) -> Rua A · Prat 5 · C-20 | P78: =IF(A78="","",IF(AND(K78<>"",L78<>""),IF(COUNTIFS($K$6:K78,K78,$L$6:L78,L78)=1,1,0),0)) -> 0 | Q78: =IF(A78="","",IF(AND(K78<>"",M78<>""),IF(COUNTIFS($K$6:K78,K78,$M$6:M78,M78)=1,1,0),0)) -> 0 | R78: =IF(A78="","",IF(M78<>"",IF(COUNTIF($M$6:M78,M78)=1,1,0),0)) -> 0 | T78: =IF(AND($M78<>"",$M78='Mapa do Galpão'!$C$20),COUNTIF($M$6:$M78,'Mapa do Galpão'!$C$20),"")
A79: BTG-065 | B79: Eventos | C79: A.01.0711.004.GG | D79: =IF(C79="","",IFERROR(IF(TRIM(MID(SUBSTITUTE(C79,".",REPT(" ",50)),51,50))="01","Masculino",IF(TRIM(MID(SUBSTITUTE(C79,".",REPT(" ",50)),51,50))="02","Feminino",IF(TRIM(MID(SUBSTITUTE(C79,".",REPT(" ",50)),51,50))="03","Outros","—"))),"—")) -> Masculino | E79: POLO | F79: POLO PIQUET MASC. | G79: BRANCA | H79: GG | I79: =SUMIFS(Movimentações!$F$6:$F$4998,Movimentações!$C$6:$C$4998,A79,Movimentações!$M$6:$M$4998,M79) -> 0 | J79: ✅ Ótimo | K79: A | L79: 5 | M79: C-20 | N79: =IF(AND(K79="",L79="",M79=""),"⚠ sem endereço","Rua "&K79&IF(L79="",""," · Prat "&L79)&IF(M79="",""," · "&M79)) -> Rua A · Prat 5 · C-20 | P79: =IF(A79="","",IF(AND(K79<>"",L79<>""),IF(COUNTIFS($K$6:K79,K79,$L$6:L79,L79)=1,1,0),0)) -> 0 | Q79: =IF(A79="","",IF(AND(K79<>"",M79<>""),IF(COUNTIFS($K$6:K79,K79,$M$6:M79,M79)=1,1,0),0)) -> 0 | R79: =IF(A79="","",IF(M79<>"",IF(COUNTIF($M$6:M79,M79)=1,1,0),0)) -> 0 | T79: =IF(AND($M79<>"",$M79='Mapa do Galpão'!$C$20),COUNTIF($M$6:$M79,'Mapa do Galpão'!$C$20),"")
A80: BTG-066 | B80: Eventos | C80: A.01.0711.004.XG | D80: =IF(C80="","",IFERROR(IF(TRIM(MID(SUBSTITUTE(C80,".",REPT(" ",50)),51,50))="01","Masculino",IF(TRIM(MID(SUBSTITUTE(C80,".",REPT(" ",50)),51,50))="02","Feminino",IF(TRIM(MID(SUBSTITUTE(C80,".",REPT(" ",50)),51,50))="03","Outros","—"))),"—")) -> Masculino | E80: POLO | F80: POLO PIQUET MASC. | G80: BRANCA | H80: XG | I80: =SUMIFS(Movimentações!$F$6:$F$4998,Movimentações!$C$6:$C$4998,A80,Movimentações!$M$6:$M$4998,M80) -> 0 | J80: ✅ Ótimo | K80: A | L80: 5 | M80: C-20 | N80: =IF(AND(K80="",L80="",M80=""),"⚠ sem endereço","Rua "&K80&IF(L80="",""," · Prat "&L80)&IF(M80="",""," · "&M80)) -> Rua A · Prat 5 · C-20 | P80: =IF(A80="","",IF(AND(K80<>"",L80<>""),IF(COUNTIFS($K$6:K80,K80,$L$6:L80,L80)=1,1,0),0)) -> 0 | Q80: =IF(A80="","",IF(AND(K80<>"",M80<>""),IF(COUNTIFS($K$6:K80,K80,$M$6:M80,M80)=1,1,0),0)) -> 0 | R80: =IF(A80="","",IF(M80<>"",IF(COUNTIF($M$6:M80,M80)=1,1,0),0)) -> 0 | T80: =IF(AND($M80<>"",$M80='Mapa do Galpão'!$C$20),COUNTIF($M$6:$M80,'Mapa do Galpão'!$C$20),"")
A81: BTG-067 | B81: Eventos | C81: A.01.0705.017.PP | D81: =IF(C81="","",IFERROR(IF(TRIM(MID(SUBSTITUTE(C81,".",REPT(" ",50)),51,50))="01","Masculino",IF(TRIM(MID(SUBSTITUTE(C81,".",REPT(" ",50)),51,50))="02","Feminino",IF(TRIM(MID(SUBSTITUTE(C81,".",REPT(" ",50)),51,50))="03","Outros","—"))),"—")) -> Masculino | E81: POLO | F81: POLO PIQUET MASC. | G81: INDIGO | H81: PP | I81: =SUMIFS(Movimentações!$F$6:$F$4998,Movimentações!$C$6:$C$4998,A81,Movimentações!$M$6:$M$4998,M81) -> 0 | J81: ✅ Ótimo | K81: A | L81: 13 | M81: C-21 | N81: =IF(AND(K81="",L81="",M81=""),"⚠ sem endereço","Rua "&K81&IF(L81="",""," · Prat "&L81)&IF(M81="",""," · "&M81)) -> Rua A · Prat 13 · C-21 | P81: =IF(A81="","",IF(AND(K81<>"",L81<>""),IF(COUNTIFS($K$6:K81,K81,$L$6:L81,L81)=1,1,0),0)) -> 0 | Q81: =IF(A81="","",IF(AND(K81<>"",M81<>""),IF(COUNTIFS($K$6:K81,K81,$M$6:M81,M81)=1,1,0),0)) -> 1 | R81: =IF(A81="","",IF(M81<>"",IF(COUNTIF($M$6:M81,M81)=1,1,0),0)) -> 1 | T81: =IF(AND($M81<>"",$M81='Mapa do Galpão'!$C$20),COUNTIF($M$6:$M81,'Mapa do Galpão'!$C$20),"")
A82: BTG-068 | B82: Eventos | C82: A.01.0705.017.P | D82: =IF(C82="","",IFERROR(IF(TRIM(MID(SUBSTITUTE(C82,".",REPT(" ",50)),51,50))="01","Masculino",IF(TRIM(MID(SUBSTITUTE(C82,".",REPT(" ",50)),51,50))="02","Feminino",IF(TRIM(MID(SUBSTITUTE(C82,".",REPT(" ",50)),51,50))="03","Outros","—"))),"—")) -> Masculino | E82: POLO | F82: POLO PIQUET MASC. | G82: INDIGO | H82: P | I82: =SUMIFS(Movimentações!$F$6:$F$4998,Movimentações!$C$6:$C$4998,A82,Movimentações!$M$6:$M$4998,M82) -> 0 | J82: ✅ Ótimo | K82: A | L82: 13 | M82: C-21 | N82: =IF(AND(K82="",L82="",M82=""),"⚠ sem endereço","Rua "&K82&IF(L82="",""," · Prat "&L82)&IF(M82="",""," · "&M82)) -> Rua A · Prat 13 · C-21 | P82: =IF(A82="","",IF(AND(K82<>"",L82<>""),IF(COUNTIFS($K$6:K82,K82,$L$6:L82,L82)=1,1,0),0)) -> 0 | Q82: =IF(A82="","",IF(AND(K82<>"",M82<>""),IF(COUNTIFS($K$6:K82,K82,$M$6:M82,M82)=1,1,0),0)) -> 0 | R82: =IF(A82="","",IF(M82<>"",IF(COUNTIF($M$6:M82,M82)=1,1,0),0)) -> 0 | T82: =IF(AND($M82<>"",$M82='Mapa do Galpão'!$C$20),COUNTIF($M$6:$M82,'Mapa do Galpão'!$C$20),"")
A83: BTG-069 | B83: Eventos | C83: A.01.0705.017.M | D83: =IF(C83="","",IFERROR(IF(TRIM(MID(SUBSTITUTE(C83,".",REPT(" ",50)),51,50))="01","Masculino",IF(TRIM(MID(SUBSTITUTE(C83,".",REPT(" ",50)),51,50))="02","Feminino",IF(TRIM(MID(SUBSTITUTE(C83,".",REPT(" ",50)),51,50))="03","Outros","—"))),"—")) -> Masculino | E83: POLO | F83: POLO PIQUET MASC. | G83: INDIGO | H83: M | I83: =SUMIFS(Movimentações!$F$6:$F$4998,Movimentações!$C$6:$C$4998,A83,Movimentações!$M$6:$M$4998,M83) -> 29 | J83: ✅ Ótimo | K83: A | L83: 13 | M83: C-21 | N83: =IF(AND(K83="",L83="",M83=""),"⚠ sem endereço","Rua "&K83&IF(L83="",""," · Prat "&L83)&IF(M83="",""," · "&M83)) -> Rua A · Prat 13 · C-21 | P83: =IF(A83="","",IF(AND(K83<>"",L83<>""),IF(COUNTIFS($K$6:K83,K83,$L$6:L83,L83)=1,1,0),0)) -> 0 | Q83: =IF(A83="","",IF(AND(K83<>"",M83<>""),IF(COUNTIFS($K$6:K83,K83,$M$6:M83,M83)=1,1,0),0)) -> 0 | R83: =IF(A83="","",IF(M83<>"",IF(COUNTIF($M$6:M83,M83)=1,1,0),0)) -> 0 | T83: =IF(AND($M83<>"",$M83='Mapa do Galpão'!$C$20),COUNTIF($M$6:$M83,'Mapa do Galpão'!$C$20),"")
A84: BTG-070 | B84: Eventos | C84: A.01.0705.017.G | D84: =IF(C84="","",IFERROR(IF(TRIM(MID(SUBSTITUTE(C84,".",REPT(" ",50)),51,50))="01","Masculino",IF(TRIM(MID(SUBSTITUTE(C84,".",REPT(" ",50)),51,50))="02","Feminino",IF(TRIM(MID(SUBSTITUTE(C84,".",REPT(" ",50)),51,50))="03","Outros","—"))),"—")) -> Masculino | E84: POLO | F84: POLO PIQUET MASC. | G84: INDIGO | H84: G | I84: =SUMIFS(Movimentações!$F$6:$F$4998,Movimentações!$C$6:$C$4998,A84,Movimentações!$M$6:$M$4998,M84) -> 18 | J84: ✅ Ótimo | K84: A | L84: 13 | M84: C-21 | N84: =IF(AND(K84="",L84="",M84=""),"⚠ sem endereço","Rua "&K84&IF(L84="",""," · Prat "&L84)&IF(M84="",""," · "&M84)) -> Rua A · Prat 13 · C-21 | P84: =IF(A84="","",IF(AND(K84<>"",L84<>""),IF(COUNTIFS($K$6:K84,K84,$L$6:L84,L84)=1,1,0),0)) -> 0 | Q84: =IF(A84="","",IF(AND(K84<>"",M84<>""),IF(COUNTIFS($K$6:K84,K84,$M$6:M84,M84)=1,1,0),0)) -> 0 | R84: =IF(A84="","",IF(M84<>"",IF(COUNTIF($M$6:M84,M84)=1,1,0),0)) -> 0 | T84: =IF(AND($M84<>"",$M84='Mapa do Galpão'!$C$20),COUNTIF($M$6:$M84,'Mapa do Galpão'!$C$20),"")
A85: BTG-071 | B85: Eventos | C85: A.01.0705.017.GG | D85: =IF(C85="","",IFERROR(IF(TRIM(MID(SUBSTITUTE(C85,".",REPT(" ",50)),51,50))="01","Masculino",IF(TRIM(MID(SUBSTITUTE(C85,".",REPT(" ",50)),51,50))="02","Feminino",IF(TRIM(MID(SUBSTITUTE(C85,".",REPT(" ",50)),51,50))="03","Outros","—"))),"—")) -> Masculino | E85: POLO | F85: POLO PIQUET MASC. | G85: INDIGO | H85: GG | I85: =SUMIFS(Movimentações!$F$6:$F$4998,Movimentações!$C$6:$C$4998,A85,Movimentações!$M$6:$M$4998,M85) -> 0 | J85: ✅ Ótimo | K85: A | L85: 13 | M85: C-21 | N85: =IF(AND(K85="",L85="",M85=""),"⚠ sem endereço","Rua "&K85&IF(L85="",""," · Prat "&L85)&IF(M85="",""," · "&M85)) -> Rua A · Prat 13 · C-21 | P85: =IF(A85="","",IF(AND(K85<>"",L85<>""),IF(COUNTIFS($K$6:K85,K85,$L$6:L85,L85)=1,1,0),0)) -> 0 | Q85: =IF(A85="","",IF(AND(K85<>"",M85<>""),IF(COUNTIFS($K$6:K85,K85,$M$6:M85,M85)=1,1,0),0)) -> 0 | R85: =IF(A85="","",IF(M85<>"",IF(COUNTIF($M$6:M85,M85)=1,1,0),0)) -> 0 | T85: =IF(AND($M85<>"",$M85='Mapa do Galpão'!$C$20),COUNTIF($M$6:$M85,'Mapa do Galpão'!$C$20),"")
A86: BTG-072 | B86: Eventos | C86: A.01.0705.017.XG | D86: =IF(C86="","",IFERROR(IF(TRIM(MID(SUBSTITUTE(C86,".",REPT(" ",50)),51,50))="01","Masculino",IF(TRIM(MID(SUBSTITUTE(C86,".",REPT(" ",50)),51,50))="02","Feminino",IF(TRIM(MID(SUBSTITUTE(C86,".",REPT(" ",50)),51,50))="03","Outros","—"))),"—")) -> Masculino | E86: POLO | F86: POLO PIQUET MASC. | G86: INDIGO | H86: XG | I86: =SUMIFS(Movimentações!$F$6:$F$4998,Movimentações!$C$6:$C$4998,A86,Movimentações!$M$6:$M$4998,M86) -> 0 | J86: ✅ Ótimo | K86: A | L86: 13 | M86: C-21 | N86: =IF(AND(K86="",L86="",M86=""),"⚠ sem endereço","Rua "&K86&IF(L86="",""," · Prat "&L86)&IF(M86="",""," · "&M86)) -> Rua A · Prat 13 · C-21 | P86: =IF(A86="","",IF(AND(K86<>"",L86<>""),IF(COUNTIFS($K$6:K86,K86,$L$6:L86,L86)=1,1,0),0)) -> 0 | Q86: =IF(A86="","",IF(AND(K86<>"",M86<>""),IF(COUNTIFS($K$6:K86,K86,$M$6:M86,M86)=1,1,0),0)) -> 0 | R86: =IF(A86="","",IF(M86<>"",IF(COUNTIF($M$6:M86,M86)=1,1,0),0)) -> 0 | T86: =IF(AND($M86<>"",$M86='Mapa do Galpão'!$C$20),COUNTIF($M$6:$M86,'Mapa do Galpão'!$C$20),"")
A87: BTG-073 | B87: Eventos | C87: A.01.0706.015.PP | D87: =IF(C87="","",IFERROR(IF(TRIM(MID(SUBSTITUTE(C87,".",REPT(" ",50)),51,50))="01","Masculino",IF(TRIM(MID(SUBSTITUTE(C87,".",REPT(" ",50)),51,50))="02","Feminino",IF(TRIM(MID(SUBSTITUTE(C87,".",REPT(" ",50)),51,50))="03","Outros","—"))),"—")) -> Masculino | E87: POLO | F87: POLO PIMA MASC. | G87: MESCLA - AZUL | H87: PP | I87: =SUMIFS(Movimentações!$F$6:$F$4998,Movimentações!$C$6:$C$4998,A87,Movimentações!$M$6:$M$4998,M87) -> 0 | J87: ✅ Ótimo | K87: A | L87: 5 | M87: C-22 | N87: =IF(AND(K87="",L87="",M87=""),"⚠ sem endereço","Rua "&K87&IF(L87="",""," · Prat "&L87)&IF(M87="",""," · "&M87)) -> Rua A · Prat 5 · C-22 | P87: =IF(A87="","",IF(AND(K87<>"",L87<>""),IF(COUNTIFS($K$6:K87,K87,$L$6:L87,L87)=1,1,0),0)) -> 0 | Q87: =IF(A87="","",IF(AND(K87<>"",M87<>""),IF(COUNTIFS($K$6:K87,K87,$M$6:M87,M87)=1,1,0),0)) -> 1 | R87: =IF(A87="","",IF(M87<>"",IF(COUNTIF($M$6:M87,M87)=1,1,0),0)) -> 1 | T87: =IF(AND($M87<>"",$M87='Mapa do Galpão'!$C$20),COUNTIF($M$6:$M87,'Mapa do Galpão'!$C$20),"")
A88: BTG-074 | B88: Eventos | C88: A.01.0706.015.P | D88: =IF(C88="","",IFERROR(IF(TRIM(MID(SUBSTITUTE(C88,".",REPT(" ",50)),51,50))="01","Masculino",IF(TRIM(MID(SUBSTITUTE(C88,".",REPT(" ",50)),51,50))="02","Feminino",IF(TRIM(MID(SUBSTITUTE(C88,".",REPT(" ",50)),51,50))="03","Outros","—"))),"—")) -> Masculino | E88: POLO | F88: POLO PIMA MASC. | G88: MESCLA - AZUL | H88: P | I88: =SUMIFS(Movimentações!$F$6:$F$4998,Movimentações!$C$6:$C$4998,A88,Movimentações!$M$6:$M$4998,M88) -> 0 | J88: ✅ Ótimo | K88: A | L88: 5 | M88: C-22 | N88: =IF(AND(K88="",L88="",M88=""),"⚠ sem endereço","Rua "&K88&IF(L88="",""," · Prat "&L88)&IF(M88="",""," · "&M88)) -> Rua A · Prat 5 · C-22 | P88: =IF(A88="","",IF(AND(K88<>"",L88<>""),IF(COUNTIFS($K$6:K88,K88,$L$6:L88,L88)=1,1,0),0)) -> 0 | Q88: =IF(A88="","",IF(AND(K88<>"",M88<>""),IF(COUNTIFS($K$6:K88,K88,$M$6:M88,M88)=1,1,0),0)) -> 0 | R88: =IF(A88="","",IF(M88<>"",IF(COUNTIF($M$6:M88,M88)=1,1,0),0)) -> 0 | T88: =IF(AND($M88<>"",$M88='Mapa do Galpão'!$C$20),COUNTIF($M$6:$M88,'Mapa do Galpão'!$C$20),"")
A89: BTG-075 | B89: Eventos | C89: A.01.0706.015.M | D89: =IF(C89="","",IFERROR(IF(TRIM(MID(SUBSTITUTE(C89,".",REPT(" ",50)),51,50))="01","Masculino",IF(TRIM(MID(SUBSTITUTE(C89,".",REPT(" ",50)),51,50))="02","Feminino",IF(TRIM(MID(SUBSTITUTE(C89,".",REPT(" ",50)),51,50))="03","Outros","—"))),"—")) -> Masculino | E89: POLO | F89: POLO PIMA MASC. | G89: MESCLA - AZUL | H89: M | I89: =SUMIFS(Movimentações!$F$6:$F$4998,Movimentações!$C$6:$C$4998,A89,Movimentações!$M$6:$M$4998,M89) -> 0 | J89: ✅ Ótimo | K89: A | L89: 5 | M89: C-22 | N89: =IF(AND(K89="",L89="",M89=""),"⚠ sem endereço","Rua "&K89&IF(L89="",""," · Prat "&L89)&IF(M89="",""," · "&M89)) -> Rua A · Prat 5 · C-22 | P89: =IF(A89="","",IF(AND(K89<>"",L89<>""),IF(COUNTIFS($K$6:K89,K89,$L$6:L89,L89)=1,1,0),0)) -> 0 | Q89: =IF(A89="","",IF(AND(K89<>"",M89<>""),IF(COUNTIFS($K$6:K89,K89,$M$6:M89,M89)=1,1,0),0)) -> 0 | R89: =IF(A89="","",IF(M89<>"",IF(COUNTIF($M$6:M89,M89)=1,1,0),0)) -> 0 | T89: =IF(AND($M89<>"",$M89='Mapa do Galpão'!$C$20),COUNTIF($M$6:$M89,'Mapa do Galpão'!$C$20),"")
A90: BTG-076 | B90: Eventos | C90: A.01.0706.015.G | D90: =IF(C90="","",IFERROR(IF(TRIM(MID(SUBSTITUTE(C90,".",REPT(" ",50)),51,50))="01","Masculino",IF(TRIM(MID(SUBSTITUTE(C90,".",REPT(" ",50)),51,50))="02","Feminino",IF(TRIM(MID(SUBSTITUTE(C90,".",REPT(" ",50)),51,50))="03","Outros","—"))),"—")) -> Masculino | E90: POLO | F90: POLO PIMA MASC. | G90: MESCLA - AZUL | H90: G | I90: =SUMIFS(Movimentações!$F$6:$F$4998,Movimentações!$C$6:$C$4998,A90,Movimentações!$M$6:$M$4998,M90) -> 0 | J90: ✅ Ótimo | K90: A | L90: 5 | M90: C-22 | N90: =IF(AND(K90="",L90="",M90=""),"⚠ sem endereço","Rua "&K90&IF(L90="",""," · Prat "&L90)&IF(M90="",""," · "&M90)) -> Rua A · Prat 5 · C-22 | P90: =IF(A90="","",IF(AND(K90<>"",L90<>""),IF(COUNTIFS($K$6:K90,K90,$L$6:L90,L90)=1,1,0),0)) -> 0 | Q90: =IF(A90="","",IF(AND(K90<>"",M90<>""),IF(COUNTIFS($K$6:K90,K90,$M$6:M90,M90)=1,1,0),0)) -> 0 | R90: =IF(A90="","",IF(M90<>"",IF(COUNTIF($M$6:M90,M90)=1,1,0),0)) -> 0 | T90: =IF(AND($M90<>"",$M90='Mapa do Galpão'!$C$20),COUNTIF($M$6:$M90,'Mapa do Galpão'!$C$20),"")
A91: BTG-077 | B91: Eventos | C91: A.01.0706.015.GG | D91: =IF(C91="","",IFERROR(IF(TRIM(MID(SUBSTITUTE(C91,".",REPT(" ",50)),51,50))="01","Masculino",IF(TRIM(MID(SUBSTITUTE(C91,".",REPT(" ",50)),51,50))="02","Feminino",IF(TRIM(MID(SUBSTITUTE(C91,".",REPT(" ",50)),51,50))="03","Outros","—"))),"—")) -> Masculino | E91: POLO | F91: POLO PIMA MASC. | G91: MESCLA - AZUL | H91: GG | I91: =SUMIFS(Movimentações!$F$6:$F$4998,Movimentações!$C$6:$C$4998,A91,Movimentações!$M$6:$M$4998,M91) -> 0 | J91: ✅ Ótimo | K91: A | L91: 5 | M91: C-22 | N91: =IF(AND(K91="",L91="",M91=""),"⚠ sem endereço","Rua "&K91&IF(L91="",""," · Prat "&L91)&IF(M91="",""," · "&M91)) -> Rua A · Prat 5 · C-22 | P91: =IF(A91="","",IF(AND(K91<>"",L91<>""),IF(COUNTIFS($K$6:K91,K91,$L$6:L91,L91)=1,1,0),0)) -> 0 | Q91: =IF(A91="","",IF(AND(K91<>"",M91<>""),IF(COUNTIFS($K$6:K91,K91,$M$6:M91,M91)=1,1,0),0)) -> 0 | R91: =IF(A91="","",IF(M91<>"",IF(COUNTIF($M$6:M91,M91)=1,1,0),0)) -> 0 | T91: =IF(AND($M91<>"",$M91='Mapa do Galpão'!$C$20),COUNTIF($M$6:$M91,'Mapa do Galpão'!$C$20),"")
A92: BTG-078 | B92: Eventos | C92: A.01.0706.015.XG | D92: =IF(C92="","",IFERROR(IF(TRIM(MID(SUBSTITUTE(C92,".",REPT(" ",50)),51,50))="01","Masculino",IF(TRIM(MID(SUBSTITUTE(C92,".",REPT(" ",50)),51,50))="02","Feminino",IF(TRIM(MID(SUBSTITUTE(C92,".",REPT(" ",50)),51,50))="03","Outros","—"))),"—")) -> Masculino | E92: POLO | F92: POLO PIMA MASC. | G92: MESCLA - AZUL | H92: XG | I92: =SUMIFS(Movimentações!$F$6:$F$4998,Movimentações!$C$6:$C$4998,A92,Movimentações!$M$6:$M$4998,M92) -> 0 | J92: ✅ Ótimo | K92: A | L92: 5 | M92: C-22 | N92: =IF(AND(K92="",L92="",M92=""),"⚠ sem endereço","Rua "&K92&IF(L92="",""," · Prat "&L92)&IF(M92="",""," · "&M92)) -> Rua A · Prat 5 · C-22 | P92: =IF(A92="","",IF(AND(K92<>"",L92<>""),IF(COUNTIFS($K$6:K92,K92,$L$6:L92,L92)=1,1,0),0)) -> 0 | Q92: =IF(A92="","",IF(AND(K92<>"",M92<>""),IF(COUNTIFS($K$6:K92,K92,$M$6:M92,M92)=1,1,0),0)) -> 0 | R92: =IF(A92="","",IF(M92<>"",IF(COUNTIF($M$6:M92,M92)=1,1,0),0)) -> 0 | T92: =IF(AND($M92<>"",$M92='Mapa do Galpão'!$C$20),COUNTIF($M$6:$M92,'Mapa do Galpão'!$C$20),"")
A93: BTG-079 | B93: Eventos | C93: A.01.0713.005.PP | D93: =IF(C93="","",IFERROR(IF(TRIM(MID(SUBSTITUTE(C93,".",REPT(" ",50)),51,50))="01","Masculino",IF(TRIM(MID(SUBSTITUTE(C93,".",REPT(" ",50)),51,50))="02","Feminino",IF(TRIM(MID(SUBSTITUTE(C93,".",REPT(" ",50)),51,50))="03","Outros","—"))),"—")) -> Masculino | E93: POLO | F93: POLO COTTON MASC. | G93: PRETA | H93: PP | I93: =SUMIFS(Movimentações!$F$6:$F$4998,Movimentações!$C$6:$C$4998,A93,Movimentações!$M$6:$M$4998,M93) -> 0 | J93: ✅ Ótimo | K93: A | L93: 11 | M93: C-23 | N93: =IF(AND(K93="",L93="",M93=""),"⚠ sem endereço","Rua "&K93&IF(L93="",""," · Prat "&L93)&IF(M93="",""," · "&M93)) -> Rua A · Prat 11 · C-23 | P93: =IF(A93="","",IF(AND(K93<>"",L93<>""),IF(COUNTIFS($K$6:K93,K93,$L$6:L93,L93)=1,1,0),0)) -> 1 | Q93: =IF(A93="","",IF(AND(K93<>"",M93<>""),IF(COUNTIFS($K$6:K93,K93,$M$6:M93,M93)=1,1,0),0)) -> 1 | R93: =IF(A93="","",IF(M93<>"",IF(COUNTIF($M$6:M93,M93)=1,1,0),0)) -> 1 | T93: =IF(AND($M93<>"",$M93='Mapa do Galpão'!$C$20),COUNTIF($M$6:$M93,'Mapa do Galpão'!$C$20),"")
A94: BTG-080 | B94: Eventos | C94: A.01.0713.005.P | D94: =IF(C94="","",IFERROR(IF(TRIM(MID(SUBSTITUTE(C94,".",REPT(" ",50)),51,50))="01","Masculino",IF(TRIM(MID(SUBSTITUTE(C94,".",REPT(" ",50)),51,50))="02","Feminino",IF(TRIM(MID(SUBSTITUTE(C94,".",REPT(" ",50)),51,50))="03","Outros","—"))),"—")) -> Masculino | E94: POLO | F94: POLO COTTON MASC. | G94: PRETA | H94: P | I94: =SUMIFS(Movimentações!$F$6:$F$4998,Movimentações!$C$6:$C$4998,A94,Movimentações!$M$6:$M$4998,M94) -> 6 | J94: ✅ Ótimo | K94: A | L94: 11 | M94: C-23 | N94: =IF(AND(K94="",L94="",M94=""),"⚠ sem endereço","Rua "&K94&IF(L94="",""," · Prat "&L94)&IF(M94="",""," · "&M94)) -> Rua A · Prat 11 · C-23 | P94: =IF(A94="","",IF(AND(K94<>"",L94<>""),IF(COUNTIFS($K$6:K94,K94,$L$6:L94,L94)=1,1,0),0)) -> 0 | Q94: =IF(A94="","",IF(AND(K94<>"",M94<>""),IF(COUNTIFS($K$6:K94,K94,$M$6:M94,M94)=1,1,0),0)) -> 0 | R94: =IF(A94="","",IF(M94<>"",IF(COUNTIF($M$6:M94,M94)=1,1,0),0)) -> 0 | T94: =IF(AND($M94<>"",$M94='Mapa do Galpão'!$C$20),COUNTIF($M$6:$M94,'Mapa do Galpão'!$C$20),"")
A95: BTG-080 | B95: Eventos | C95: A.01.0713.005.P | D95: =IF(C95="","",IFERROR(IF(TRIM(MID(SUBSTITUTE(C95,".",REPT(" ",50)),51,50))="01","Masculino",IF(TRIM(MID(SUBSTITUTE(C95,".",REPT(" ",50)),51,50))="02","Feminino",IF(TRIM(MID(SUBSTITUTE(C95,".",REPT(" ",50)),51,50))="03","Outros","—"))),"—")) -> Masculino | E95: POLO | F95: POLO COTTON MASC. | G95: PRETA | H95: P | I95: =SUMIFS(Movimentações!$F$6:$F$4998,Movimentações!$C$6:$C$4998,A95,Movimentações!$M$6:$M$4998,M95) -> 4 | J95: ✅ Ótimo | K95: A | L95: 11 | M95: C-24 | N95: =IF(AND(K95="",L95="",M95=""),"⚠ sem endereço","Rua "&K95&IF(L95="",""," · Prat "&L95)&IF(M95="",""," · "&M95)) -> Rua A · Prat 11 · C-24 | P95: =IF(A95="","",IF(AND(K95<>"",L95<>""),IF(COUNTIFS($K$6:K95,K95,$L$6:L95,L95)=1,1,0),0)) -> 0 | Q95: =IF(A95="","",IF(AND(K95<>"",M95<>""),IF(COUNTIFS($K$6:K95,K95,$M$6:M95,M95)=1,1,0),0)) -> 1 | R95: =IF(A95="","",IF(M95<>"",IF(COUNTIF($M$6:M95,M95)=1,1,0),0)) -> 1 | T95: =IF(AND($M95<>"",$M95='Mapa do Galpão'!$C$20),COUNTIF($M$6:$M95,'Mapa do Galpão'!$C$20),"")
A96: BTG-081 | B96: Eventos | C96: A.01.0713.005.M | D96: =IF(C96="","",IFERROR(IF(TRIM(MID(SUBSTITUTE(C96,".",REPT(" ",50)),51,50))="01","Masculino",IF(TRIM(MID(SUBSTITUTE(C96,".",REPT(" ",50)),51,50))="02","Feminino",IF(TRIM(MID(SUBSTITUTE(C96,".",REPT(" ",50)),51,50))="03","Outros","—"))),"—")) -> Masculino | E96: POLO | F96: POLO COTTON MASC. | G96: PRETA | H96: M | I96: =SUMIFS(Movimentações!$F$6:$F$4998,Movimentações!$C$6:$C$4998,A96,Movimentações!$M$6:$M$4998,M96) -> 20 | J96: ✅ Ótimo | K96: A | L96: 11 | M96: C-23 | N96: =IF(AND(K96="",L96="",M96=""),"⚠ sem endereço","Rua "&K96&IF(L96="",""," · Prat "&L96)&IF(M96="",""," · "&M96)) -> Rua A · Prat 11 · C-23 | P96: =IF(A96="","",IF(AND(K96<>"",L96<>""),IF(COUNTIFS($K$6:K96,K96,$L$6:L96,L96)=1,1,0),0)) -> 0 | Q96: =IF(A96="","",IF(AND(K96<>"",M96<>""),IF(COUNTIFS($K$6:K96,K96,$M$6:M96,M96)=1,1,0),0)) -> 0 | R96: =IF(A96="","",IF(M96<>"",IF(COUNTIF($M$6:M96,M96)=1,1,0),0)) -> 0 | T96: =IF(AND($M96<>"",$M96='Mapa do Galpão'!$C$20),COUNTIF($M$6:$M96,'Mapa do Galpão'!$C$20),"")
A97: BTG-081 | B97: Eventos | C97: A.01.0713.005.M | D97: =IF(C97="","",IFERROR(IF(TRIM(MID(SUBSTITUTE(C97,".",REPT(" ",50)),51,50))="01","Masculino",IF(TRIM(MID(SUBSTITUTE(C97,".",REPT(" ",50)),51,50))="02","Feminino",IF(TRIM(MID(SUBSTITUTE(C97,".",REPT(" ",50)),51,50))="03","Outros","—"))),"—")) -> Masculino | E97: POLO | F97: POLO COTTON MASC. | G97: PRETA | H97: M | I97: =SUMIFS(Movimentações!$F$6:$F$4998,Movimentações!$C$6:$C$4998,A97,Movimentações!$M$6:$M$4998,M97) -> 5 | J97: ✅ Ótimo | K97: A | L97: 11 | M97: C-24 | N97: =IF(AND(K97="",L97="",M97=""),"⚠ sem endereço","Rua "&K97&IF(L97="",""," · Prat "&L97)&IF(M97="",""," · "&M97)) -> Rua A · Prat 11 · C-24 | P97: =IF(A97="","",IF(AND(K97<>"",L97<>""),IF(COUNTIFS($K$6:K97,K97,$L$6:L97,L97)=1,1,0),0)) -> 0 | Q97: =IF(A97="","",IF(AND(K97<>"",M97<>""),IF(COUNTIFS($K$6:K97,K97,$M$6:M97,M97)=1,1,0),0)) -> 0 | R97: =IF(A97="","",IF(M97<>"",IF(COUNTIF($M$6:M97,M97)=1,1,0),0)) -> 0 | T97: =IF(AND($M97<>"",$M97='Mapa do Galpão'!$C$20),COUNTIF($M$6:$M97,'Mapa do Galpão'!$C$20),"")
A98: BTG-082 | B98: Eventos | C98: A.01.0713.005.G | D98: =IF(C98="","",IFERROR(IF(TRIM(MID(SUBSTITUTE(C98,".",REPT(" ",50)),51,50))="01","Masculino",IF(TRIM(MID(SUBSTITUTE(C98,".",REPT(" ",50)),51,50))="02","Feminino",IF(TRIM(MID(SUBSTITUTE(C98,".",REPT(" ",50)),51,50))="03","Outros","—"))),"—")) -> Masculino | E98: POLO | F98: POLO COTTON MASC. | G98: PRETA | H98: G | I98: =SUMIFS(Movimentações!$F$6:$F$4998,Movimentações!$C$6:$C$4998,A98,Movimentações!$M$6:$M$4998,M98) -> 9 | J98: ✅ Ótimo | K98: A | L98: 11 | M98: C-23 | N98: =IF(AND(K98="",L98="",M98=""),"⚠ sem endereço","Rua "&K98&IF(L98="",""," · Prat "&L98)&IF(M98="",""," · "&M98)) -> Rua A · Prat 11 · C-23 | P98: =IF(A98="","",IF(AND(K98<>"",L98<>""),IF(COUNTIFS($K$6:K98,K98,$L$6:L98,L98)=1,1,0),0)) -> 0 | Q98: =IF(A98="","",IF(AND(K98<>"",M98<>""),IF(COUNTIFS($K$6:K98,K98,$M$6:M98,M98)=1,1,0),0)) -> 0 | R98: =IF(A98="","",IF(M98<>"",IF(COUNTIF($M$6:M98,M98)=1,1,0),0)) -> 0 | T98: =IF(AND($M98<>"",$M98='Mapa do Galpão'!$C$20),COUNTIF($M$6:$M98,'Mapa do Galpão'!$C$20),"")
